Workbook

Sheet README
A1: Categorie are:
A2: 1.⁠ ⁠Gender-based (G) : jokes targeting gender roles, or gender features.
A3: 2.⁠ ⁠Racial/Ethnic (RE): jokes targeting race, nationality, or ethnicity.
A4: 3.⁠ ⁠Age-based (Age): jokes targeting age groups
A5: 4.⁠ ⁠Appearance/Physical condition (AP): jokes targeting looks, body type, or any disabilities or diseases.
A6: 5.⁠ ⁠Religion-based (R): jokes targeting religious groups or beliefs.
A7: 6.⁠ ⁠Class/Occupation (CO): jokes targeting professions or socioeconomic class.
A8: 7. Sexual orientation (S): jokes targeting LGBTQ+ identities.
A9: 8. Political/Ideological (PI): jokes targeting political figures, parties, or ideological groups.
A10: 9. Mental health (M): jokes targeting mental illness or psychological conditions.
A11: 10. None (N): No categories between those, or more than one
A13: You can use the code to simplify the labelling
... A17: Here is who does what:
A19: Sheet | B19: Annotator | C19: Adjudicator
A20: sample_1a | B20: Millan
A21: sample_1b | B21: Mathias
A22: conflict_1 | C22: Alice
A23: sample_2a | B23: Alice
A24: sample_2b | B24: Zuzana
A25: conflict_2 | C25: Barthélemy
A26: sample_3a | B26: Barthélemy
A27: sample_3b | B27: Millan
A28: conflict_3 | C28: Mathias
A29: sample_4a | B29: Mathias
A30: sample_4b | B30: Zuzana
A31: conflict_4 | C31: Millan
A32: sample_5a | B32: Alice
A33: sample_5b | B33: Barthélemy
A34: conflict_5 | C34: Zuzana

Sheet sample_1a
A1: id | B1: joke | C1: category_human
A2: 1 | B2: The best way to catch a Bear.. First you gotta dig a hole just big enough that the bear won't be able to climb it's way out. Then along the edges you put berries and other things bears eat and once you've done that you fill the hole in with ash. So once the bear comes up and starts to eat the berries you sneak behind him and kick him in the ash hole. | C2: N
A3: 2 | B3: What do you call a domineering pill bug? A controly-poly! | C3: N
A4: 3 | B4: What do you call someone whose filed bankruptcy 4 times and divorced twice? A GOP Presidential candidate. | C4: PI
A5: 4 | B5: Some girl told me today I was odd, I can't even... | C5: N
A6: 5 | B6: What did the pirate say on his eightieth birthday? Aye, Matey! | C6: N
A7: 6 | B7: What do you call a woman who smuggles things inside her? A cuntainer. | C7: G
A8: 7 | B8: I searched dirty jokes in google to repost on r/jokes My face popped up as the first result. | C8: M
A9: 8 | B9: where's the only living gay Saudi Arabian? just over a stones throw away | C9: S
A10: 9 | B10: I've heard all the Pro life vs Pro choice debates, and after hearing the debates, i came up with a compromise. I propose Pro Abortion, in which we abort everybody. | C10: R
A11: 10 | B11: My penis is only 4 inches... ...but I find most girls don't like it that wide. | C11: G
A12: 11 | B12: Abdul writes to his son Ahmed "Dear Ahmed," so goes the letter. "I want to plant some vegetables in my garden so that we can have some home-grown food in the winter. But you know how bad my back is. Could you please come visit me and help me with it?" The reply comes soon. "Father, I am sorry but I am preoccupied with work, so I can't help. And I'm not sure we should be digging up your garden, because as I recall, my friend Amir hid *the thing* there." The very next day, security services show up at Abdul's home, check every nook and cranny, cause the old man quite a fright, but eventually, finding nothing, they leave. Abdul, distressed, writes back to Ahmed. "Dear Ahmed! A bunch of guys in black suits showed up today, trampled mud all over the house, and poked their nose into everything they could find! They left and let me go, but what was that all about?" And the reply "Father; they dug up the garden too, haven't they? You can plant your vegetables now. Again, I am sorry I could not help otherwise, but I'll make it up to you with my potato salad that you like so much. Love, Ahmed." | C12: N, RE
A13: 12 | B13: Give a man a jacket... And he'll be able to leave the house. Teach a man to jacket, and he'll never leave the house. | C13: G
... A54: 53 | B54: Chung Hoi A famous American golfer is invited to go to China for a golfing tournament. From the second he gets there, he is treated like a king. He is given five-star treatment in a five-star hotel until the day of the tournament. The night before the tournament, he is sitting in his hotel room watching TV. A hot Asian girl walks up to his room and he says, "Wow. They must really love me here." He begins to have sex with her the whole night. She continues to scream, "Chung Hoi! Chung Hoi!," but he ignores it. At the tournament, the American golfer gets a hole-in-one and gets really excited. He starts yelling, "Chung Hoi! Chung Hoi!" One of the Chinese golfers says, "What do you mean 'WRONG HOLE'?" | C54: RE
A55: 54 | B55: A guy’s driving down the highway one day... ... when he sees a hitchhiker ahead. There’s hardly any traffic on the highway, and he figures that the poor guy will never get a ride, so he decides to help him out. After about 5 miles, the hitchhiker pulls a gun, and tells the driver that he won’t get hurt as long as he follows orders and doesn’t try anything stupid. The hitcher has the driver pull over and stop the car. “I just broke out of jail, and I need to get as far away from here as I can.” He makes the driver strip naked, ties his wrists to his ankles, and pushes him down a small ravine, just enough to waste some time getting back up. When the driver makes it to the side of the road, there’s no traffic. He’s so frustrated he’s about to cry. Then he sees a semi truck rolling down the road his way. Still tied up, he jumps up and down to be seen, and sure enough the truck pulls over. The trucker asks, “Well what happened to you?” The ex-driver says, “Some guy pulled a gun on me, tied me up like this and stole my car!” The trucker shakes his head as he starts to unzip his pants, smiles and says, “Son, it just ain’t your day, is it?”
A56: 55 | B56: Why didn't Pluto organise his birthday party? He couldn't planet. | C56: N
A57: 56 | B57: After a thorough research and survey scientists claim that the thicker your thighs, The more snacks you can lay on your lap. | C57: G
A58: 57 | B58: I think I want to be a garbage man. I hear the industry is picking up! | C58: CO
A59: 58 | B59: Who is the commander of cheese? Sargento | C59: N
A60: 59 | B60: Why does the KKK wear all white? Because they hate black, people!!! | C60: RE
A61: 60 | B61: Took my computer to a repair shop. He said here's your problem. Someone put peanutbutter in the hard drive. | C61: N
A62: 61 | B62: Why do Jewish men get circumcised? Because Jewish women won't touch anything unless it's 20% off | C62: R, RE
A63: 62 | B63: My colleagues thought it would be good to each wear a shirt representing our star sign for our ‘make a wish foundation’ fundraiser Now I’m here wearing the word CANCER across my chest and feel a right knob | C63: Age, AP
A64: 63 | B64: Did you hear about the guy who plotted to severely scorch his friend by trying to burn him alive with one of his diplomas when the weather was as cold as the freezing point of water? At zero degree Celsius, he attempted first degree murder, using his second degree as kindling, resulting in third degree burns. | C64: N
A65: 64 | B65: I can't watch the Super Bowl this year. It's all a LI | C65: N
A66: 65 | B66: Why was Helen Keller a bad driver? She was a woman | C66: G
A67: 66 | B67: Best porn star name Queef Latina | C67: G, RE
... A101: 100 | B101: I love pteradons They're my favorite dinosoars. | C101: N

Sheet sample_1b
A1: id | B1: joke | C1: category_human
A2: 1 | B2: The best way to catch a Bear.. First you gotta dig a hole just big enough that the bear won't be able to climb it's way out. Then along the edges you put berries and other things bears eat and once you've done that you fill the hole in with ash. So once the bear comes up and starts to eat the berries you sneak behind him and kick him in the ash hole. | C2: N
A3: 2 | B3: What do you call a domineering pill bug? A controly-poly! | C3: N
A4: 3 | B4: What do you call someone whose filed bankruptcy 4 times and divorced twice? A GOP Presidential candidate. | C4: PI
A5: 4 | B5: Some girl told me today I was odd, I can't even... | C5: N
A6: 5 | B6: What did the pirate say on his eightieth birthday? Aye, Matey! | C6: N
A7: 6 | B7: What do you call a woman who smuggles things inside her? A cuntainer. | C7: G
A8: 7 | B8: I searched dirty jokes in google to repost on r/jokes My face popped up as the first result. | C8: AP
A9: 8 | B9: where's the only living gay Saudi Arabian? just over a stones throw away | C9: S;RE
A10: 9 | B10: I've heard all the Pro life vs Pro choice debates, and after hearing the debates, i came up with a compromise. I propose Pro Abortion, in which we abort everybody. | C10: N
A11: 10 | B11: My penis is only 4 inches... ...but I find most girls don't like it that wide. | C11: N
A12: 11 | B12: Abdul writes to his son Ahmed "Dear Ahmed," so goes the letter. "I want to plant some vegetables in my garden so that we can have some home-grown food in the winter. But you know how bad my back is. Could you please come visit me and help me with it?" The reply comes soon. "Father, I am sorry but I am preoccupied with work, so I can't help. And I'm not sure we should be digging up your garden, because as I recall, my friend Amir hid *the thing* there." The very next day, security services show up at Abdul's home, check every nook and cranny, cause the old man quite a fright, but eventually, finding nothing, they leave. Abdul, distressed, writes back to Ahmed. "Dear Ahmed! A bunch of guys in black suits showed up today, trampled mud all over the house, and poked their nose into everything they could find! They left and let me go, but what was that all about?" And the reply "Father; they dug up the garden too, haven't they? You can plant your vegetables now. Again, I am sorry I could not help otherwise, but I'll make it up to you with my potato salad that you like so much. Love, Ahmed." | C12: RE
A13: 12 | B13: Give a man a jacket... And he'll be able to leave the house. Teach a man to jacket, and he'll never leave the house. | C13: N
... A88: 87 | B88: The past few days summed up Pepsi: We just pulled the worst PR stunt of the year. United Airlines: Hold my beer. Sean Spicer: LEEEEEEEEEEROY JEEENKINS. | C88: N
A89: 88 | B89: What do you call a moile in the Harry Potter wizarding world? Professor Snip
A90: 89 | B90: My descent into the cannibalistic devouring of a South African Bishop Call 00 8 22... | C90: N
A91: 90 | B91: An blobfish walks into 1 bar. The bartender asks, "Why the saggy face?" It became sad, so it decided to go to another bar. The blobfish is asked "Why the saggy face?" again, so it decides to go to another bar. However, the blobfish slowly began to return to normal. When he had already visited 15 bars, he was back to normal. ----- **^Note:** ^bar ^as ^in ^atmospheric ^pressure | C91: N
A92: 91 | B92: C sections. They really take it out of you. | C92: G
A93: 92 | B93: What happens when you go inside in a snow suit? It melts. | C93: N
A94: 93 | B94: What do you call a woman that makes more money than her husband? A widow. | C94: G
A95: 94 | B95: A bear walks up to a rabbit and asks "Do you have a problem with shit getting stuck in your fur?" Asks BEAR. The rabbit looked taken back, "Uhh, No" So the bear wiped his ass on the rabbit. | C95: N
A96: 95 | B96: What do my existence and an unsharpened pencil have in common? They're both dull and pointless. | C96: N
A97: 96 | B97: I went to the cinema to see a really, really sad film. The guy behind me was just wailing. Half way through, a harpoon hit the back of my head. | C97: N
A98: 97 | B98: The Billy saga continues... Mrs. Teacher is upset at being out-foxed by lil' Billy. So she decides to get even. Next week she tells the kids to study reallllly hard, because she will ask a question on Friday, that if one of them can answer it, he/she will get to have next Monday absence. So they study real hard. Come Friday, the teacher says "All right class, here's my question. How many gallons of water are in the ocean?" As the kids have no answer, they disappointedly trudge home to do the weekend homework. Next week the teacher tells them the same thing. "Study reallllly hard, and if you answer my question you get Monday absence." So the class studies hard. Come Friday, the teacher asks "All right class, here's my question. How many blades of grass are on the earth?" Once again, the kids trudge home disappointed. This time, Billy grabs a bag of ping pong balls, spray paints them all black, puts the bag in his backpack and bides his time for next week. Same thing next week. Come Friday, the class waits on the teacher. She says "All right class, here's my question..." And BAM! Billy bursts his bag of ping pong balls and the fly everywhere! One hits the teacher in the face! She grabs it, looks at it and asks "OK, who is the one with the crazy black balls??" Billy jumps up and answers "Eddie Murphy, teacher! I'll see you Tuesday!" | C98: Age
A99: 98 | B99: How many flies does it take to screw in a lightbulb? Two, but how’d they get in there? | C99: N
A100: 99 | B100: Dirty jokes is like water... It’s not always clean. | C100: N
A101: 100 | B101: I love pteradons They're my favorite dinosoars. | C101: N

Sheet conflict_1
A1: id | B1: joke | C1: Conflict | D1: Adjudication
A2: 1 | B2: The best way to catch a Bear.. First you gotta dig a hole just big enough that the bear won't be able to climb it's way out. Then along the edges you put berries and other things bears eat and once you've done that you fill the hole in with ash. So once the bear comes up and starts to eat the berries you sneak behind him and kick him in the ash hole. | C2: =IF(sample_1a!C2<>sample_1b!C2, sample_1a!C2 & " ≠ " & sample_1b!C2, "")
A3: 2 | B3: What do you call a domineering pill bug? A controly-poly! | C3: =IF(sample_1a!C3<>sample_1b!C3, sample_1a!C3 & " ≠ " & sample_1b!C3, "")
A4: 3 | B4: What do you call someone whose filed bankruptcy 4 times and divorced twice? A GOP Presidential candidate. | C4: =IF(sample_1a!C4<>sample_1b!C4, sample_1a!C4 & " ≠ " & sample_1b!C4, "")
A5: 4 | B5: Some girl told me today I was odd, I can't even... | C5: =IF(sample_1a!C5<>sample_1b!C5, sample_1a!C5 & " ≠ " & sample_1b!C5, "")
A6: 5 | B6: What did the pirate say on his eightieth birthday? Aye, Matey! | C6: =IF(sample_1a!C6<>sample_1b!C6, sample_1a!C6 & " ≠ " & sample_1b!C6, "")
A7: 6 | B7: What do you call a woman who smuggles things inside her? A cuntainer. | C7: =IF(sample_1a!C7<>sample_1b!C7, sample_1a!C7 & " ≠ " & sample_1b!C7, "")
A8: 7 | B8: I searched dirty jokes in google to repost on r/jokes My face popped up as the first result. | C8: =IF(sample_1a!C8<>sample_1b!C8, sample_1a!C8 & " ≠ " & sample_1b!C8, "") -> M ≠ AP | D8: AP
A9: 8 | B9: where's the only living gay Saudi Arabian? just over a stones throw away | C9: =IF(sample_1a!C9<>sample_1b!C9, sample_1a!C9 & " ≠ " & sample_1b!C9, "") -> S ≠ S;RE | D9: N
A10: 9 | B10: I've heard all the Pro life vs Pro choice debates, and after hearing the debates, i came up with a compromise. I propose Pro Abortion, in which we abort everybody. | C10: =IF(sample_1a!C10<>sample_1b!C10, sample_1a!C10 & " ≠ " & sample_1b!C10, "") -> R ≠ N | D10: G
A11: 10 | B11: My penis is only 4 inches... ...but I find most girls don't like it that wide. | C11: =IF(sample_1a!C11<>sample_1b!C11, sample_1a!C11 & " ≠ " & sample_1b!C11, "") -> G ≠ N | D11: G
A12: 11 | B12: Abdul writes to his son Ahmed "Dear Ahmed," so goes the letter. "I want to plant some vegetables in my garden so that we can have some home-grown food in the winter. But you know how bad my back is. Could you please come visit me and help me with it?" The reply comes soon. "Father, I am sorry but I am preoccupied with work, so I can't help. And I'm not sure we should be digging up your garden, because as I recall, my friend Amir hid *the thing* there." The very next day, security services show up at Abdul's home, check every nook and cranny, cause the old man quite a fright, but eventually, finding nothing, they leave. Abdul, distressed, writes back to Ahmed. "Dear Ahmed! A bunch of guys in black suits showed up today, trampled mud all over the house, and poked their nose into everything they could find! They left and let me go, but what was that all about?" And the reply "Father; they dug up the garden too, haven't they? You can plant your vegetables now. Again, I am sorry I could not help otherwise, but I'll make it up to you with my potato salad that you like so much. Love, Ahmed." | C12: =IF(sample_1a!C12<>sample_1b!C12, sample_1a!C12 & " ≠ " & sample_1b!C12, "") -> N, RE ≠ RE | D12: RE
A13: 12 | B13: Give a man a jacket... And he'll be able to leave the house. Teach a man to jacket, and he'll never leave the house. | C13: =IF(sample_1a!C13<>sample_1b!C13, sample_1a!C13 & " ≠ " & sample_1b!C13, "") -> G ≠ N | D13: G
A14: 13 | B14: If you’ve never tried blindfolded archery, let me tell you... You don’t know what you’re missing. | C14: =IF(sample_1a!C14<>sample_1b!C14, sample_1a!C14 & " ≠ " & sample_1b!C14, "")
A15: 14 | B15: A young woman was rummaging through her grandmother’s belongings, and she came across a mysterious lamp. A young woman was rummaging through her grandmother’s belongings, and she came across a mysterious lamp. Upon rubbing the lamp, Rick Astley appeared before her and said, “I will give you three wishes.” She thought for a moment and said, “For my first wish I would like to end world hunger.” “An admirable request. Consider it granted!” Rick said. “For my second wish, I would like world peace.” “Ah, this is a very difficult request, but it has been done. And for your final request?” She thought for a moment and decided to make this a selfish wish. “As a movie buff, I would like a copy of every movie in the world in my own private collection.” The genie a bit taken back . . . . paused and said, “This I cannot do . . .” “Why!?” The women exclaimed. “ You can fix world hunger and end all wars, but you cannot complete this simple task?!” The Genie looked away and said, “I can, but your collection will not be complete . . . you see . . . I’m never gunna give you Up!” | C15: =IF(sample_1a!C15<>sample_1b!C15, sample_1a!C15 & " ≠ " & sample_1b!C15, "")
A16: 15 | B16: Racism is a lot like Nickelback... Its fun to joke about, but you never want to see it in person. | C16: =IF(sample_1a!C16<>sample_1b!C16, sample_1a!C16 & " ≠ " & sample_1b!C16, "")
A17: 16 | B17: Is it ok to be against a certain race? because I hate relays. | C17: =IF(sample_1a!C17<>sample_1b!C17, sample_1a!C17 & " ≠ " & sample_1b!C17, "")
A18: 17 | B18: What do you call a smiling Roman with a hair in his teeth? Gladiator. | C18: =IF(sample_1a!C18<>sample_1b!C18, sample_1a!C18 & " ≠ " & sample_1b!C18, "") -> RE, N ≠ RE | D18: RE
A19: 18 | B19: The restaurant Hooters is known for two things... ...boobs. | C19: =IF(sample_1a!C19<>sample_1b!C19, sample_1a!C19 & " ≠ " & sample_1b!C19, "")
A20: 19 | B20: A Roman walks into a bar and holds up two fingers. "Five beers, please." | C20: =IF(sample_1a!C20<>sample_1b!C20, sample_1a!C20 & " ≠ " & sample_1b!C20, "")
A21: 20 | B21: “Excuse me, sir, have you seen a police officer around?” “Excuse me, sir, have you seen a police officer around?” - “No, not a soul, actually.” - “Very good, now give me your wallet, watch and laptop!” | C21: =IF(sample_1a!C21<>sample_1b!C21, sample_1a!C21 & " ≠ " & sample_1b!C21, "")
A22: 21 | B22: Today I learned that the elevator was named after Darth Vader's little sister. Ele. Ele Vader. | C22: =IF(sample_1a!C22<>sample_1b!C22, sample_1a!C22 & " ≠ " & sample_1b!C22, "")
A23: 22 | B23: I met a beautiful girl down at the park today. Sparks flew, she fell at my feet, and we ended up having sex right there and then. I fucking love my new Taser. | C23: =IF(sample_1a!C23<>sample_1b!C23, sample_1a!C23 & " ≠ " & sample_1b!C23, "")
A24: 23 | B24: A man has been having sex with his wife in the dark for 30 years and she just found out he's been using a dildo. Wife: "Explain the dildo." Man: "Then Explain the kids." | C24: =IF(sample_1a!C24<>sample_1b!C24, sample_1a!C24 & " ≠ " & sample_1b!C24, "") -> N, G ≠ G | D24: G
A25: 24 | B25: What do you call a pair of dancing Jews? A Jewet. | C25: =IF(sample_1a!C25<>sample_1b!C25, sample_1a!C25 & " ≠ " & sample_1b!C25, "") -> R, RE ≠ RE | D25: RE
A26: 25 | B26: There are two kinds of people in this world: (1) Those who can extrapolate from incomplete data. | C26: =IF(sample_1a!C26<>sample_1b!C26, sample_1a!C26 & " ≠ " & sample_1b!C26, "")
A27: 26 | B27: What did the egg say to the boiling water? "I don't think I can get hard -- I just got laid this morning! | C27: =IF(sample_1a!C27<>sample_1b!C27, sample_1a!C27 & " ≠ " & sample_1b!C27, "")
A28: 27 | B28: Russian computer: Please enter password Me: Beef_stew Russian computer: Password not stroganoff | C28: =IF(sample_1a!C28<>sample_1b!C28, sample_1a!C28 & " ≠ " & sample_1b!C28, "") -> RE ≠ N | D28: RE
A29: 28 | B29: Teacher/Student **The teacher says:** Today, we're going to talk about the tenses. Now, if I say "I am beautiful," which tense is it? **The student says:** Obviously it's the past tense. | C29: =IF(sample_1a!C29<>sample_1b!C29, sample_1a!C29 & " ≠ " & sample_1b!C29, "") -> Age, CO ≠ N | D29: Age
A30: 29 | B30: The German Shepherd cover up... I found my German Shepherd, Hondo, with the neighbor's pet rabbit in its mouth. The rabbit was dead, and I panicked.. I took the dirty, chewed-up rabbit into the house. I gave it a bath, blew dried its fur, and put it back into the cage at the neighbor's house, hoping they would think it died of natural causes. A few days later, the neighbor asked me, "Don, did you hear that Fluffy died?" I said, "Um... no... what happened?" The neighbor replied, "We found him dead in his cage one day, but the weird thing is that the day after we buried him, someone had dug him up, gave him a bath, and put him back into the cage. There are some real sick people out there!" | C30: =IF(sample_1a!C30<>sample_1b!C30, sample_1a!C30 & " ≠ " & sample_1b!C30, "")
A31: 30 | B31: What's the most powerful country after USA ? USB. | C31: =IF(sample_1a!C31<>sample_1b!C31, sample_1a!C31 & " ≠ " & sample_1b!C31, "")
A32: 31 | B32: You’re calling from inside one of the cartels?? "Yes, they wanted me to go with them" -Are you kidnapped? "Actually…No. I’m grownapped" -Have they hurt you in any way? "No. They just abduct-taped me" | C32: =IF(sample_1a!C32<>sample_1b!C32, sample_1a!C32 & " ≠ " & sample_1b!C32, "")
A33: 32 | B33: A confused Chinese student asks his master, "Master Shi, why do all Chinese look the same?" Then the master replied, "I am not master Shi." | C33: =IF(sample_1a!C33<>sample_1b!C33, sample_1a!C33 & " ≠ " & sample_1b!C33, "")
A34: 33 | B34: I baked a dog shaped dough in a local baking competition It was pure-bread. | C34: =IF(sample_1a!C34<>sample_1b!C34, sample_1a!C34 & " ≠ " & sample_1b!C34, "")
A35: 34 | B35: A boy brags to his friends that he just lost his virginity... A boy came running in a room full of his friends bragging about losing his virginity. His friends asked him to sit down and tell them the whole story. He replies "I can't sit down, my ass hurts." | C35: =IF(sample_1a!C35<>sample_1b!C35, sample_1a!C35 & " ≠ " & sample_1b!C35, "")
A36: 35 | B36: It Worked on the Other Side One night, a man and his wife were watching TV. It was about breast implants. The wife said, ”I wish I had bigger breast.” The man said, ”You don’t have to get silicone breasts, just wipe between your breast with toilet paper.” "How would that work?" asked the wife. The man said, "Well, you have been wiping your butt for 50 years and it's gotten bigger." | C36: =IF(sample_1a!C36<>sample_1b!C36, sample_1a!C36 & " ≠ " & sample_1b!C36, "")
A37: 36 | B37: A Guy takes his Friend to a bar A Guy takes his Friend to his favourite bar for the first time. They order a beer and someone shouts: "7"! Everyone started laughing. The Friend is visibly confused so the Guy explains: "Oh, right, you see, we've always been telling the same jokes over and over so we gave each a number, now instead of the joke you say the number and everyone knows what you mean". To prove it he says "24" and he gets a few chuckles. "That was a knock knock joke". The Friend decides to give it a try and says: "57". Everyone goes nuts, they all laugh like crazy. "Was it this funny?" he asks. Through tears the Guy says: "We haven't heard that one yet" | C37: =IF(sample_1a!C37<>sample_1b!C37, sample_1a!C37 & " ≠ " & sample_1b!C37, "")
A38: 37 | B38: I think I'm failing my marine biology class My grade is below C level. | C38: =IF(sample_1a!C38<>sample_1b!C38, sample_1a!C38 & " ≠ " & sample_1b!C38, "")
A39: 38 | B39: Post your best Chuck Norris Facts ! Chuck Norris once one a game of connect four in three moves ! | C39: =IF(sample_1a!C39<>sample_1b!C39, sample_1a!C39 & " ≠ " & sample_1b!C39, "")
A40: 39 | B40: There was a knock in my door "Who's there?" "Police" "Get out, I didn't call police, I called whores" "Your neighbors called us" "Let them fuck you then" | C40: =IF(sample_1a!C40<>sample_1b!C40, sample_1a!C40 & " ≠ " & sample_1b!C40, "") -> N ≠ CO | D40: CO
A41: 40 | B41: A man wants to jump off a bridge... (This joke is courtesy of Emo Philips) I was walking across a bridge one day, and I saw a man standing on the edge, about to jump off. So I ran over and said "Stop! Don't do it!" "Why shouldn't I?" he said. "Well, there's so much to live for!" "Like what?" "Well... are you religious?" He said yes. I said, "Me too! Are you Christian or Buddhist?" "Christian." "Me too! Are you Catholic or Protestant? "Protestant." "Me too! Are you Episcopalian or Baptist?" "Baptist" "Wow! Me too! Are you Baptist Church of God or Baptist Church of the Lord?" "Baptist Church of God!" "Me too! Are you original Baptist Church of God, or are you reformed Baptist Church of God?" "Reformed Baptist Church of God!" "Me too! Are you Reformed Baptist Church of God, reformation of 1879, or Reformed Baptist Church of God, reformation of 1915?" He said, "Reformed Baptist Church of God, reformation of 1915!" I said, "Die, heretic scum", and pushed him off. | C41: =IF(sample_1a!C41<>sample_1b!C41, sample_1a!C41 & " ≠ " & sample_1b!C41, "")
A42: 41 | B42: I make conversation like I play chess.... Plan 3 moves ahead then freak out when the other person doesn't do what I planned for. | C42: =IF(sample_1a!C42<>sample_1b!C42, sample_1a!C42 & " ≠ " & sample_1b!C42, "")
A43: 42 | B43: Hey girl, are you a parked car in July? Because I want to leave a baby in you. | C43: =IF(sample_1a!C43<>sample_1b!C43, sample_1a!C43 & " ≠ " & sample_1b!C43, "") -> Age ≠ G | D43: G
A44: 43 | B44: a visit to the ob-gyn A sweet young thing had just finished getting her annual exam at her ObGyn's. As he was finishing up her paperwork he asked her i she had any questions. After a bit of of a pause, the embarrassed girl admitted to having one question. "Can you get pregnant from anal sex?" she asked. The doctor gave he a serious look and replied, "of course you can, where do you think lawyers come from?". | C44: =IF(sample_1a!C44<>sample_1b!C44, sample_1a!C44 & " ≠ " & sample_1b!C44, "") -> CO, G ≠ G | D44: N
A45: 44 | B45: Head of lettuce... Sounds like a boring job... | C45: =IF(sample_1a!C45<>sample_1b!C45, sample_1a!C45 & " ≠ " & sample_1b!C45, "") -> CO ≠ N | D45: CO
A46: 45 | B46: A man walks into a tattoo parlor... And asks for a $100 bill to be tattoed on his penis. Curious, the tattoo artist asks him why he wanted a $100 bill tattoed on his penis. The man replies, "Three reasons- * I want to play with my money * I want to watch my money grow * The only thing my wife blows nowadays is a 100 dollars" | C46: =IF(sample_1a!C46<>sample_1b!C46, sample_1a!C46 & " ≠ " & sample_1b!C46, "")
A47: 46 | B47: What do snails use to travel across tidal pools? Snailboats. | C47: =IF(sample_1a!C47<>sample_1b!C47, sample_1a!C47 & " ≠ " & sample_1b!C47, "")
A48: 47 | B48: What does a Christmas tree and a monk have in common? They both have ornamental balls | C48: =IF(sample_1a!C48<>sample_1b!C48, sample_1a!C48 & " ≠ " & sample_1b!C48, "")
A49: 48 | B49: Seaworld has borrowed a shark to try and make one of their own sharks pregnant... Personally, I think I would have looked at other options before going to a loan shark... | C49: =IF(sample_1a!C49<>sample_1b!C49, sample_1a!C49 & " ≠ " & sample_1b!C49, "") -> CO ≠ N | D49: CO
A50: 49 | B50: Why did the guitarist go to jail? He fingered a minor. | C50: =IF(sample_1a!C50<>sample_1b!C50, sample_1a!C50 & " ≠ " & sample_1b!C50, "") -> Age ≠ N | D50: N
A51: 50 | B51: Classic Family Guy Joke Peter: Brian, Look! There is a message in my Alphabet Cereal. it says, "oooooo" Brian: Peter! You are eating Cheerios. | C51: =IF(sample_1a!C51<>sample_1b!C51, sample_1a!C51 & " ≠ " & sample_1b!C51, "")
A52: 51 | B52: Did you hear the one about the corduroy pillow? It's making headlines across the nation! | C52: =IF(sample_1a!C52<>sample_1b!C52, sample_1a!C52 & " ≠ " & sample_1b!C52, "")
A53: 52 | B53: Last year 52 Americans were shot by people who barely speak english, have no marketable skills, and are prone to angry outburst based on their views... ...toddlers are the worst. | C53: =IF(sample_1a!C53<>sample_1b!C53, sample_1a!C53 & " ≠ " & sample_1b!C53, "") -> Age, RE ≠ Age | D53: N
A54: 53 | B54: Chung Hoi A famous American golfer is invited to go to China for a golfing tournament. From the second he gets there, he is treated like a king. He is given five-star treatment in a five-star hotel until the day of the tournament. The night before the tournament, he is sitting in his hotel room watching TV. A hot Asian girl walks up to his room and he says, "Wow. They must really love me here." He begins to have sex with her the whole night. She continues to scream, "Chung Hoi! Chung Hoi!," but he ignores it. At the tournament, the American golfer gets a hole-in-one and gets really excited. He starts yelling, "Chung Hoi! Chung Hoi!" One of the Chinese golfers says, "What do you mean 'WRONG HOLE'?" | C54: =IF(sample_1a!C54<>sample_1b!C54, sample_1a!C54 & " ≠ " & sample_1b!C54, "") -> RE ≠ G | D54: RE
A55: 54 | B55: A guy’s driving down the highway one day... ... when he sees a hitchhiker ahead. There’s hardly any traffic on the highway, and he figures that the poor guy will never get a ride, so he decides to help him out. After about 5 miles, the hitchhiker pulls a gun, and tells the driver that he won’t get hurt as long as he follows orders and doesn’t try anything stupid. The hitcher has the driver pull over and stop the car. “I just broke out of jail, and I need to get as far away from here as I can.” He makes the driver strip naked, ties his wrists to his ankles, and pushes him down a small ravine, just enough to waste some time getting back up. When the driver makes it to the side of the road, there’s no traffic. He’s so frustrated he’s about to cry. Then he sees a semi truck rolling down the road his way. Still tied up, he jumps up and down to be seen, and sure enough the truck pulls over. The trucker asks, “Well what happened to you?” The ex-driver says, “Some guy pulled a gun on me, tied me up like this and stole my car!” The trucker shakes his head as he starts to unzip his pants, smiles and says, “Son, it just ain’t your day, is it?” | C55: =IF(sample_1a!C55<>sample_1b!C55, sample_1a!C55 & " ≠ " & sample_1b!C55, "") -> ≠ N
A56: 55 | B56: Why didn't Pluto organise his birthday party? He couldn't planet. | C56: =IF(sample_1a!C56<>sample_1b!C56, sample_1a!C56 & " ≠ " & sample_1b!C56, "")
A57: 56 | B57: After a thorough research and survey scientists claim that the thicker your thighs, The more snacks you can lay on your lap. | C57: =IF(sample_1a!C57<>sample_1b!C57, sample_1a!C57 & " ≠ " & sample_1b!C57, "") -> G ≠ N | D57: AP
A58: 57 | B58: I think I want to be a garbage man. I hear the industry is picking up! | C58: =IF(sample_1a!C58<>sample_1b!C58, sample_1a!C58 & " ≠ " & sample_1b!C58, "") -> CO ≠ N | D58: CO
A59: 58 | B59: Who is the commander of cheese? Sargento | C59: =IF(sample_1a!C59<>sample_1b!C59, sample_1a!C59 & " ≠ " & sample_1b!C59, "")
A60: 59 | B60: Why does the KKK wear all white? Because they hate black, people!!! | C60: =IF(sample_1a!C60<>sample_1b!C60, sample_1a!C60 & " ≠ " & sample_1b!C60, "")
A61: 60 | B61: Took my computer to a repair shop. He said here's your problem. Someone put peanutbutter in the hard drive. | C61: =IF(sample_1a!C61<>sample_1b!C61, sample_1a!C61 & " ≠ " & sample_1b!C61, "")
A62: 61 | B62: Why do Jewish men get circumcised? Because Jewish women won't touch anything unless it's 20% off | C62: =IF(sample_1a!C62<>sample_1b!C62, sample_1a!C62 & " ≠ " & sample_1b!C62, "") -> R, RE ≠ RE | D62: RE
A63: 62 | B63: My colleagues thought it would be good to each wear a shirt representing our star sign for our ‘make a wish foundation’ fundraiser Now I’m here wearing the word CANCER across my chest and feel a right knob | C63: =IF(sample_1a!C63<>sample_1b!C63, sample_1a!C63 & " ≠ " & sample_1b!C63, "") -> Age, AP ≠ N | D63: AP
A64: 63 | B64: Did you hear about the guy who plotted to severely scorch his friend by trying to burn him alive with one of his diplomas when the weather was as cold as the freezing point of water? At zero degree Celsius, he attempted first degree murder, using his second degree as kindling, resulting in third degree burns. | C64: =IF(sample_1a!C64<>sample_1b!C64, sample_1a!C64 & " ≠ " & sample_1b!C64, "")
A65: 64 | B65: I can't watch the Super Bowl this year. It's all a LI | C65: =IF(sample_1a!C65<>sample_1b!C65, sample_1a!C65 & " ≠ " & sample_1b!C65, "")
A66: 65 | B66: Why was Helen Keller a bad driver? She was a woman | C66: =IF(sample_1a!C66<>sample_1b!C66, sample_1a!C66 & " ≠ " & sample_1b!C66, "")
A67: 66 | B67: Best porn star name Queef Latina | C67: =IF(sample_1a!C67<>sample_1b!C67, sample_1a!C67 & " ≠ " & sample_1b!C67, "") -> G, RE ≠ G | D67: N
A68: 67 | B68: A captain is giving orders to soldiers staying in line After finishing he asked if anyone had a question to ask. One of the soldiers asks “I’m sorry Sir, but why do your boots have different colours, one black and one brown?” Captain realizes that he really has two different boots and says that he will go home and change them, and that soldiers should wait here till he comes back One hour passes, all soldiers are exhausted, and finally the captain appears, sad, and still wearing different boots A soldier asks why didn’t he change the boots, why are you still wearing one black and one brown boot? The captain replies, I couldn’t find a normal pair at home, the other two are also different | C68: =IF(sample_1a!C68<>sample_1b!C68, sample_1a!C68 & " ≠ " & sample_1b!C68, "") -> CO ≠ N | D68: CO
A69: 68 | B69: How do you tell which clan a Scotsman is from? Peek up his kilt. If he's got a quarter-pounder, he's a McDonald. | C69: =IF(sample_1a!C69<>sample_1b!C69, sample_1a!C69 & " ≠ " & sample_1b!C69, "")
A70: 69 | B70: A student at a management school came up to a pretty girl and hugged her without any warning.... The surprised girl said, “What was that?” The guy smiled at her, “Direct marketing!” The girl slapped him soundly. “What was that?!” said the boy, holding his cheek. “Customer feedback.” | C70: =IF(sample_1a!C70<>sample_1b!C70, sample_1a!C70 & " ≠ " & sample_1b!C70, "") -> CO ≠ G | D70: G
A71: 70 | B71: A chicken and an egg are lying in bed after sex. The chicken leans back, takes a drag on the cigarette and says "well that answers that old question...." | C71: =IF(sample_1a!C71<>sample_1b!C71, sample_1a!C71 & " ≠ " & sample_1b!C71, "")
A72: 71 | B72: Did you hear about the guy who lost his shovel? His name was Douglas | C72: =IF(sample_1a!C72<>sample_1b!C72, sample_1a!C72 & " ≠ " & sample_1b!C72, "")
A73: 72 | B73: What's a moths favourite band? Mothley crue | C73: =IF(sample_1a!C73<>sample_1b!C73, sample_1a!C73 & " ≠ " & sample_1b!C73, "")
A74: 73 | B74: Teenage gamer tosses a piss jug into my yard Me- I know that was your piss jug Teenage Gamer- what? Me- This is my yard, those are my trees, that is my lawn, can you guess who can piss in my yard? Teenage Gamer- you? Me- No...My dog...ya little shit | C74: =IF(sample_1a!C74<>sample_1b!C74, sample_1a!C74 & " ≠ " & sample_1b!C74, "") -> N ≠ Age | D74: N
A75: 74 | B75: Worst case of cultural appropriation. Today I saw the worst case of cultural appropriation ever. A white man knelt down and committed seppuku. What a dick. Hope he dies. | C75: =IF(sample_1a!C75<>sample_1b!C75, sample_1a!C75 & " ≠ " & sample_1b!C75, "")
A76: 75 | B76: A mother complained to her consultant about her daughter’s strange eating habits. –“All day long she lies in bed and eats yeast and car wax. What will happen to her?” –“Eventually,” said the consultant, “she will rise and shine.” | C76: =IF(sample_1a!C76<>sample_1b!C76, sample_1a!C76 & " ≠ " & sample_1b!C76, "") -> N ≠ CO | D76: M
A77: 76 | B77: [NSFW] Cure for anxiety Sex is very therapeutic If you lay me, you get laid back | C77: =IF(sample_1a!C77<>sample_1b!C77, sample_1a!C77 & " ≠ " & sample_1b!C77, "")
A78: 77 | B78: A place where stalkers meet and share their stalking stories.. The Stalk Exchange. | C78: =IF(sample_1a!C78<>sample_1b!C78, sample_1a!C78 & " ≠ " & sample_1b!C78, "")
A79: 78 | B79: The Ladies Department A man walked into the ladies department of a Macy's, one of the largest department store chains. He shyly walked up to the woman behind the counter and said, "I'd like to buy a bra for my wife." "What type of bra?" asked the clerk. "Type?" inquires the man "There is more than one type?" "Look Around," said the saleslady, as she showed a sea of bras in every shape, size color and material. "Actually, even with all of this variety, there are really only three types of bras," replied the salesclerk. Confused, the man asked what were the types. The saleslady replied "The Catholic type, the, Salvation Army type, and the Baptist type. Which one do you need?" Still confused the man asked, "What is the difference between them?" The lady responded "It is all really quite simple. The Catholic type supports the masses, the Salvation Army type lifts up the fallen, and the Baptist type makes mountains out of mole hills." | C79: =IF(sample_1a!C79<>sample_1b!C79, sample_1a!C79 & " ≠ " & sample_1b!C79, "") -> R ≠ G | D79: R
A80: 79 | B80: Me: Wow! You dimmed the light within 5 minutes. Aren’t you romantic? Optometrist: Sit, please read the letters on the screen. | C80: =IF(sample_1a!C80<>sample_1b!C80, sample_1a!C80 & " ≠ " & sample_1b!C80, "") -> AP ≠ CO | D80: CO
A81: 80 | B81: Why did Minotaur win an interior design award? Because his home was a maze thing. | C81: =IF(sample_1a!C81<>sample_1b!C81, sample_1a!C81 & " ≠ " & sample_1b!C81, "")
A82: 81 | B82: My dad was walking around the house screaming yesterday.... He kept shouting, "A, E, I, O, U". "What's wrong?", I asked him. To which he responded, "Nothing, I just have irritable vowel syndrome..." | C82: =IF(sample_1a!C82<>sample_1b!C82, sample_1a!C82 & " ≠ " & sample_1b!C82, "")
A83: 82 | B83: How do you fit an elephant in to a subway? Take the 's' out of "sub" and the 'f' out of "way" | C83: =IF(sample_1a!C83<>sample_1b!C83, sample_1a!C83 & " ≠ " & sample_1b!C83, "")
A84: 83 | B84: Why aren't any atheists buying a PS4 Pro? They don't believe in higher power. | C84: =IF(sample_1a!C84<>sample_1b!C84, sample_1a!C84 & " ≠ " & sample_1b!C84, "")
A85: 84 | B85: Final arrangements... A woman from New York was getting her affairs in order. She wrote her will and made her final arrangements. As part of these arrangements she met with her rabbi to talk about what type of funeral service she wanted. She told her rabbi she had two final requests. First, she wanted to be cremated, and second, she wanted her ashes scattered over Bloomindgales. "Bloomingdales!" the rabbi said. "Why Bloomingdales?" "That way, I am guaranteed to have my daughters visit me at least twice a week." | C85: =IF(sample_1a!C85<>sample_1b!C85, sample_1a!C85 & " ≠ " & sample_1b!C85, "") -> N ≠ R | D85: R
A86: 85 | B86: I've just found an origami porn channel! But it's paper view only :( | C86: =IF(sample_1a!C86<>sample_1b!C86, sample_1a!C86 & " ≠ " & sample_1b!C86, "")
A87: 86 | B87: TIFU by handing a pulled pork sandwich to my Muslim friend. drat, wrong sub! | C87: =IF(sample_1a!C87<>sample_1b!C87, sample_1a!C87 & " ≠ " & sample_1b!C87, "") -> R ≠ RE | D87: R
A88: 87 | B88: The past few days summed up Pepsi: We just pulled the worst PR stunt of the year. United Airlines: Hold my beer. Sean Spicer: LEEEEEEEEEEROY JEEENKINS. | C88: =IF(sample_1a!C88<>sample_1b!C88, sample_1a!C88 & " ≠ " & sample_1b!C88, "")
A89: 88 | B89: What do you call a moile in the Harry Potter wizarding world? Professor Snip | C89: =IF(sample_1a!C89<>sample_1b!C89, sample_1a!C89 & " ≠ " & sample_1b!C89, "") -> N ≠ | D89: N
A90: 89 | B90: My descent into the cannibalistic devouring of a South African Bishop Call 00 8 22... | C90: =IF(sample_1a!C90<>sample_1b!C90, sample_1a!C90 & " ≠ " & sample_1b!C90, "") -> R, RE ≠ N | D90: N
A91: 90 | B91: An blobfish walks into 1 bar. The bartender asks, "Why the saggy face?" It became sad, so it decided to go to another bar. The blobfish is asked "Why the saggy face?" again, so it decides to go to another bar. However, the blobfish slowly began to return to normal. When he had already visited 15 bars, he was back to normal. ----- **^Note:** ^bar ^as ^in ^atmospheric ^pressure | C91: =IF(sample_1a!C91<>sample_1b!C91, sample_1a!C91 & " ≠ " & sample_1b!C91, "")
A92: 91 | B92: C sections. They really take it out of you. | C92: =IF(sample_1a!C92<>sample_1b!C92, sample_1a!C92 & " ≠ " & sample_1b!C92, "") -> N ≠ G | D92: N
A93: 92 | B93: What happens when you go inside in a snow suit? It melts. | C93: =IF(sample_1a!C93<>sample_1b!C93, sample_1a!C93 & " ≠ " & sample_1b!C93, "")
A94: 93 | B94: What do you call a woman that makes more money than her husband? A widow. | C94: =IF(sample_1a!C94<>sample_1b!C94, sample_1a!C94 & " ≠ " & sample_1b!C94, "")
A95: 94 | B95: A bear walks up to a rabbit and asks "Do you have a problem with shit getting stuck in your fur?" Asks BEAR. The rabbit looked taken back, "Uhh, No" So the bear wiped his ass on the rabbit. | C95: =IF(sample_1a!C95<>sample_1b!C95, sample_1a!C95 & " ≠ " & sample_1b!C95, "")
A96: 95 | B96: What do my existence and an unsharpened pencil have in common? They're both dull and pointless. | C96: =IF(sample_1a!C96<>sample_1b!C96, sample_1a!C96 & " ≠ " & sample_1b!C96, "") -> M ≠ N | D96: M
A97: 96 | B97: I went to the cinema to see a really, really sad film. The guy behind me was just wailing. Half way through, a harpoon hit the back of my head. | C97: =IF(sample_1a!C97<>sample_1b!C97, sample_1a!C97 & " ≠ " & sample_1b!C97, "")
A98: 97 | B98: The Billy saga continues... Mrs. Teacher is upset at being out-foxed by lil' Billy. So she decides to get even. Next week she tells the kids to study reallllly hard, because she will ask a question on Friday, that if one of them can answer it, he/she will get to have next Monday absence. So they study real hard. Come Friday, the teacher says "All right class, here's my question. How many gallons of water are in the ocean?" As the kids have no answer, they disappointedly trudge home to do the weekend homework. Next week the teacher tells them the same thing. "Study reallllly hard, and if you answer my question you get Monday absence." So the class studies hard. Come Friday, the teacher asks "All right class, here's my question. How many blades of grass are on the earth?" Once again, the kids trudge home disappointed. This time, Billy grabs a bag of ping pong balls, spray paints them all black, puts the bag in his backpack and bides his time for next week. Same thing next week. Come Friday, the class waits on the teacher. She says "All right class, here's my question..." And BAM! Billy bursts his bag of ping pong balls and the fly everywhere! One hits the teacher in the face! She grabs it, looks at it and asks "OK, who is the one with the crazy black balls??" Billy jumps up and answers "Eddie Murphy, teacher! I'll see you Tuesday!" | C98: =IF(sample_1a!C98<>sample_1b!C98, sample_1a!C98 & " ≠ " & sample_1b!C98, "") -> RE ≠ Age | D98: Age
A99: 98 | B99: How many flies does it take to screw in a lightbulb? Two, but how’d they get in there? | C99: =IF(sample_1a!C99<>sample_1b!C99, sample_1a!C99 & " ≠ " & sample_1b!C99, "")
A100: 99 | B100: Dirty jokes is like water... It’s not always clean. | C100: =IF(sample_1a!C100<>sample_1b!C100, sample_1a!C100 & " ≠ " & sample_1b!C100, "")
...

Sheet sample_2a
A1: id | B1: joke | C1: category_human
A2: 1 | B2: Helen Keller walks into a bar Then a table, then a chair. | C2: AP
A3: 2 | B3: You don't need a parachute To go skydiving. You need a parachute to go skydiving twice... | C3: N
A4: 3 | B4: Sherlock Holmes was keeping his eyes on a stranger. "Do you mind?" "I am a master of Me Stary" | C4: N
A5: 4 | B5: 4 gay necropheliacs are sitting around a bonfire. They had made this a weekly occurence, every week coming back and talking about the adventures they had that week. Jim and John were married. Trevor and Tom were also married. So week after week the 4 would come back to meet up and chat around the campfire. One week Jim and John didn't show up. Trevor: Where are Jim and John? Tom: Unfortunately, John died a few days ago. Trevor: Oh no, that's terrible! How did Jim take it? Tom: Up the ass. | C5: S
A6: 5 | B6: In the forest. A girl and a boy, both young, sensual, and full of hormones, walk through the dense forest. At the countryhouse lives girl's father, an old and conservative man, so boy got absolute zero pussy while staying there: but now, in this impenetrable grove, there is a perfect opportunity. "Hey, Anna, do you want to screw for a bit?" "Sure", girl exitedly answers. The boy clears out a bit of undergrowth and starts pulling down his pants; the girl is already undressed. Suddenly, he feels a terrible urge to pee. "Sorry, I gotta take a leak, will be back in thirty seconds!" "No, Ivan, I'm naked and don't you know that Fast Gonzales lives in these woods? As soon as you are gonna he is gonna, you know." "Ok, sure, I'll just turn my back and pee here." "He is named Fast Gonzales not for nothing!" "Seriously? Alright, I'll turn my back, pee, and stick a finger in your cunt so that he doesn't start anything funny." The guy turns his back and sticks a finger into fast Gonzales' asshole. | C6: G
A7: 6 | B7: What has 4 letters, sometimes 9 letters, but never has 5 letters. hint hint: don't overthink | C7: N
A8: 7 | B8: What does the Cincinnati gorilla story tell us? It's the first time that black-on-black crime made national (even international) news. | C8: RE
A9: 8 | B9: A rope walks into a bar The bartender says "we don't serve your kind here." The rope leaves and cuts the top of his hair. He comes back the next day and the bartender says, "are you that rope I kicked outta here yesterday?" The rope says, "I'm a frayed knot." Then he gets shot in the face. | C9: N
A10: 9 | B10: What do you call a Greenpeace streaker? Free Willy | C10: N
A11: 10 | B11: Why was the clock always so itchy? Because it had tiks | C11: N
A12: 11 | B12: Three men are on a boat Three men are on a boat and have cigarettes but nothing to light them with. So one man throws a cigarette off the boat and the boat becomes a cigarette lighter. | C12: N
A13: 12 | B13: At times I hide my girlfriends asthma inhaler just to make her scream “give it to me, give it to me,” so that my neighbour thinks I have a great sex life. | C13: G
... A101: 100 | B101: There is a better man inside of Trump... And Putin has a large penis. | C101: PI

Sheet sample_2b
A1: id | B1: joke | C1: category_human
A2: 1 | B2: Helen Keller walks into a bar Then a table, then a chair. | C2: N
A3: 2 | B3: You don't need a parachute To go skydiving. You need a parachute to go skydiving twice... | C3: N
A4: 3 | B4: Sherlock Holmes was keeping his eyes on a stranger. "Do you mind?" "I am a master of Me Stary" | C4: N
A5: 4 | B5: 4 gay necropheliacs are sitting around a bonfire. They had made this a weekly occurence, every week coming back and talking about the adventures they had that week. Jim and John were married. Trevor and Tom were also married. So week after week the 4 would come back to meet up and chat around the campfire. One week Jim and John didn't show up. Trevor: Where are Jim and John? Tom: Unfortunately, John died a few days ago. Trevor: Oh no, that's terrible! How did Jim take it? Tom: Up the ass. | C5: S
A6: 5 | B6: In the forest. A girl and a boy, both young, sensual, and full of hormones, walk through the dense forest. At the countryhouse lives girl's father, an old and conservative man, so boy got absolute zero pussy while staying there: but now, in this impenetrable grove, there is a perfect opportunity. "Hey, Anna, do you want to screw for a bit?" "Sure", girl exitedly answers. The boy clears out a bit of undergrowth and starts pulling down his pants; the girl is already undressed. Suddenly, he feels a terrible urge to pee. "Sorry, I gotta take a leak, will be back in thirty seconds!" "No, Ivan, I'm naked and don't you know that Fast Gonzales lives in these woods? As soon as you are gonna he is gonna, you know." "Ok, sure, I'll just turn my back and pee here." "He is named Fast Gonzales not for nothing!" "Seriously? Alright, I'll turn my back, pee, and stick a finger in your cunt so that he doesn't start anything funny." The guy turns his back and sticks a finger into fast Gonzales' asshole. | C6: N
A7: 6 | B7: What has 4 letters, sometimes 9 letters, but never has 5 letters. hint hint: don't overthink | C7: N
A8: 7 | B8: What does the Cincinnati gorilla story tell us? It's the first time that black-on-black crime made national (even international) news. | C8: RE
A9: 8 | B9: A rope walks into a bar The bartender says "we don't serve your kind here." The rope leaves and cuts the top of his hair. He comes back the next day and the bartender says, "are you that rope I kicked outta here yesterday?" The rope says, "I'm a frayed knot." Then he gets shot in the face. | C9: N
A10: 9 | B10: What do you call a Greenpeace streaker? Free Willy | C10: PI
A11: 10 | B11: Why was the clock always so itchy? Because it had tiks | C11: N
A12: 11 | B12: Three men are on a boat Three men are on a boat and have cigarettes but nothing to light them with. So one man throws a cigarette off the boat and the boat becomes a cigarette lighter. | C12: N
A13: 12 | B13: At times I hide my girlfriends asthma inhaler just to make her scream “give it to me, give it to me,” so that my neighbour thinks I have a great sex life. | C13: AP
... A21: 20 | B21: Why did the dog cross the road? To catch his bark (my brother made up this joke when he was really young) | C21: N
A22: 21 | B22: I've been trying to find out what "flabby" means. But I couldn't see any definition.
A23: 22 | B23: A patient rushes to a hospital. Patient: NURSE I NEED A DOCTOR IMMEDIATELY!!! I'M HAVING A HUGE ISSUE RIGHT NOW. The nurse sees the distress in the patients eyes and calls over the doctor. Doctor: What seems to be the problem? Patient: I don't know doc. I woke up this morning and I'm half deaf. I only hear half of everything. Doctor: I'm sorry but that's not possible. It is just not possible to hear half of everything. Patient: No doc, I'm serious. I only hear half of everything. Doctor: Ok. We can check this out then. Repeat after me: fourty four Patient: Twenty two | C23: AP
A24: 23 | B24: How many snowboarders does it take to screw in a lightbulb? Only 3: One to screw it in, another to film it, and a last one to say "sick turns brah!" | C24: CO
A25: 24 | B25: Why would Donald Trump want to lose the election? Winning means he'd need to live in a smaller house in a black neighborhood | C25: PI
A26: 25 | B26: The German kid asks the math teacher... What’s 4 + 5? The math teacher responds that it’s nine but when the teacher grades the homework he hadn’t written anything. | C26: RE
A27: 26 | B27: The only reason why humans start wars is because we have time to kill | C27: N
A28: 27 | B28: What's the most searched word on Bing? Google | C28: N
A29: 28 | B29: What do you have if you've got a green ball in each hand? The Hulk's undivided attention. | C29: N
A30: 29 | B30: A man of the cloth was touring the country preaching. He stopped at an unfamiliar hotel chain for the night and asked for a room. He took his room key and told the young woman working behind the front desk, "There better be bibles in the nightstand and the porn channels disabled." She looked shocked and responded "No! They're normal you pervert!" | C30: RE
A31: 30 | B31: What do Rick and Morty season 3 and my girlfriend have in common? They both don't exist | C31: N
A32: 31 | B32: What is the warmest period in the history of the world's climate called? Climax. | C32: N
A33: 32 | B33: A man goes to the doctor. Man: "Doctor, I have this problem." Doctor: "What is the issue?" Man: "Everytime I'm driving with my friends, we go through this tunnel, and I just can't control myself. I freak right out." Doctor: "Sounds like you have Carpool Tunnel Syndrome." | C33: M
A34: 33 | B34: Where are the best elephant dentists? Tuscaloosa. | C34: N
... A101: 100 | B101: There is a better man inside of Trump... And Putin has a large penis. | C101: PI

Sheet conflict_2
A1: M | B1: joke | C1: Conflict | D1: Adjudication
A2: 1 | B2: Helen Keller walks into a bar Then a table, then a chair. | C2: =IF(sample_2a!C2<>sample_2b!C2, sample_2a!C2 & " ≠ " & sample_2b!C2, "") -> AP ≠ N | D2: AP
A3: 2 | B3: You don't need a parachute To go skydiving. You need a parachute to go skydiving twice... | C3: =IF(sample_2a!C3<>sample_2b!C3, sample_2a!C3 & " ≠ " & sample_2b!C3, "")
A4: 3 | B4: Sherlock Holmes was keeping his eyes on a stranger. "Do you mind?" "I am a master of Me Stary" | C4: =IF(sample_2a!C4<>sample_2b!C4, sample_2a!C4 & " ≠ " & sample_2b!C4, "")
A5: 4 | B5: 4 gay necropheliacs are sitting around a bonfire. They had made this a weekly occurence, every week coming back and talking about the adventures they had that week. Jim and John were married. Trevor and Tom were also married. So week after week the 4 would come back to meet up and chat around the campfire. One week Jim and John didn't show up. Trevor: Where are Jim and John? Tom: Unfortunately, John died a few days ago. Trevor: Oh no, that's terrible! How did Jim take it? Tom: Up the ass. | C5: =IF(sample_2a!C5<>sample_2b!C5, sample_2a!C5 & " ≠ " & sample_2b!C5, "")
A6: 5 | B6: In the forest. A girl and a boy, both young, sensual, and full of hormones, walk through the dense forest. At the countryhouse lives girl's father, an old and conservative man, so boy got absolute zero pussy while staying there: but now, in this impenetrable grove, there is a perfect opportunity. "Hey, Anna, do you want to screw for a bit?" "Sure", girl exitedly answers. The boy clears out a bit of undergrowth and starts pulling down his pants; the girl is already undressed. Suddenly, he feels a terrible urge to pee. "Sorry, I gotta take a leak, will be back in thirty seconds!" "No, Ivan, I'm naked and don't you know that Fast Gonzales lives in these woods? As soon as you are gonna he is gonna, you know." "Ok, sure, I'll just turn my back and pee here." "He is named Fast Gonzales not for nothing!" "Seriously? Alright, I'll turn my back, pee, and stick a finger in your cunt so that he doesn't start anything funny." The guy turns his back and sticks a finger into fast Gonzales' asshole. | C6: =IF(sample_2a!C6<>sample_2b!C6, sample_2a!C6 & " ≠ " & sample_2b!C6, "") -> G ≠ N | D6: N
A7: 6 | B7: What has 4 letters, sometimes 9 letters, but never has 5 letters. hint hint: don't overthink | C7: =IF(sample_2a!C7<>sample_2b!C7, sample_2a!C7 & " ≠ " & sample_2b!C7, "")
A8: 7 | B8: What does the Cincinnati gorilla story tell us? It's the first time that black-on-black crime made national (even international) news. | C8: =IF(sample_2a!C8<>sample_2b!C8, sample_2a!C8 & " ≠ " & sample_2b!C8, "")
A9: 8 | B9: A rope walks into a bar The bartender says "we don't serve your kind here." The rope leaves and cuts the top of his hair. He comes back the next day and the bartender says, "are you that rope I kicked outta here yesterday?" The rope says, "I'm a frayed knot." Then he gets shot in the face. | C9: =IF(sample_2a!C9<>sample_2b!C9, sample_2a!C9 & " ≠ " & sample_2b!C9, "")
A10: 9 | B10: What do you call a Greenpeace streaker? Free Willy | C10: =IF(sample_2a!C10<>sample_2b!C10, sample_2a!C10 & " ≠ " & sample_2b!C10, "") -> N ≠ PI | D10: PI
A11: 10 | B11: Why was the clock always so itchy? Because it had tiks | C11: =IF(sample_2a!C11<>sample_2b!C11, sample_2a!C11 & " ≠ " & sample_2b!C11, "")
A12: 11 | B12: Three men are on a boat Three men are on a boat and have cigarettes but nothing to light them with. So one man throws a cigarette off the boat and the boat becomes a cigarette lighter. | C12: =IF(sample_2a!C12<>sample_2b!C12, sample_2a!C12 & " ≠ " & sample_2b!C12, "")
A13: 12 | B13: At times I hide my girlfriends asthma inhaler just to make her scream “give it to me, give it to me,” so that my neighbour thinks I have a great sex life. | C13: =IF(sample_2a!C13<>sample_2b!C13, sample_2a!C13 & " ≠ " & sample_2b!C13, "") -> G ≠ AP | D13: AP
A14: 13 | B14: What’s the difference between a truck load of tennis balls and a truck load of dead babies? You can’t unload tennis balls with a pitchfork. | C14: =IF(sample_2a!C14<>sample_2b!C14, sample_2a!C14 & " ≠ " & sample_2b!C14, "")
A15: 14 | B15: A coworker was telling us how stingy Asians are with their money. "It's just their genes," he argued earnestly, "they were just born that way." Not one to let a racial slur slide, especially at a politically correct workplace, I was quick to correct him. "Steve, you can't say things like that. Even if you are mad at someone, two Wongs don't make a Wright." | C15: =IF(sample_2a!C15<>sample_2b!C15, sample_2a!C15 & " ≠ " & sample_2b!C15, "")
A16: 15 | B16: A Japanese man, two Italians, an elf, and a woman in armor walk into an Ice cream parlor. The vendor looks at the Japanese man and says, “are those cosplayers?” He responds with “no, these are my children.” One of the Italians said “We helped him-a program an upcoming-a game so that only one person can-a turn into a peach when they touch-a the crown.” “Everyone else will receive ten units of their respective currency.” The armored woman said. The elf silently took two blue rupees from his messenger bag. | C16: =IF(sample_2a!C16<>sample_2b!C16, sample_2a!C16 & " ≠ " & sample_2b!C16, "") -> RE ≠ N | D16: N
A17: 16 | B17: I was stacking rusty blocks yesterday and got poked I went to the doctor today and he told me i had tetris | C17: =IF(sample_2a!C17<>sample_2b!C17, sample_2a!C17 & " ≠ " & sample_2b!C17, "")
A18: 17 | B18: Infinity loop a woman walks into her hypnotherapists office and says " Doctor, I have been loyal to my husband for 12 years but, last night I broke that loyalty and had an affair. I just want you to make me forget it happened". The Doctor said " Not again" | C18: =IF(sample_2a!C18<>sample_2b!C18, sample_2a!C18 & " ≠ " & sample_2b!C18, "")
A19: 18 | B19: a simple one **what do you call a team of** **religious mutants?** **A-men** | C19: =IF(sample_2a!C19<>sample_2b!C19, sample_2a!C19 & " ≠ " & sample_2b!C19, "") -> R ≠ G | D19: R
A20: 19 | B20: Wonder woman Superman was kinda bored so he just started flying around looking for something to do. He's flying over Wonder Woman's house and sees her bedroom window is open. He stops for a glimpse and sees her lying on her bed naked. She's lying there and squirming around looking real hot. Superman was getting turned on looking at her so he decides what the hell, I can just fly in real quick, give her the ole' in-out and be out of there before she even knows what hit her. After all he is Superman. So, in he goes, wham-bam and he's out of there. Wonder Woman knew something happened and says, "What was that?" The invisible man says, "I don't know but, damn, is my ass sore." | C20: =IF(sample_2a!C20<>sample_2b!C20, sample_2a!C20 & " ≠ " & sample_2b!C20, "") -> G ≠ N | D20: N
A21: 20 | B21: Why did the dog cross the road? To catch his bark (my brother made up this joke when he was really young) | C21: =IF(sample_2a!C21<>sample_2b!C21, sample_2a!C21 & " ≠ " & sample_2b!C21, "")
A22: 21 | B22: I've been trying to find out what "flabby" means. But I couldn't see any definition. | C22: =IF(sample_2a!C22<>sample_2b!C22, sample_2a!C22 & " ≠ " & sample_2b!C22, "") -> AP ≠ | D22: AP
A23: 22 | B23: A patient rushes to a hospital. Patient: NURSE I NEED A DOCTOR IMMEDIATELY!!! I'M HAVING A HUGE ISSUE RIGHT NOW. The nurse sees the distress in the patients eyes and calls over the doctor. Doctor: What seems to be the problem? Patient: I don't know doc. I woke up this morning and I'm half deaf. I only hear half of everything. Doctor: I'm sorry but that's not possible. It is just not possible to hear half of everything. Patient: No doc, I'm serious. I only hear half of everything. Doctor: Ok. We can check this out then. Repeat after me: fourty four Patient: Twenty two | C23: =IF(sample_2a!C23<>sample_2b!C23, sample_2a!C23 & " ≠ " & sample_2b!C23, "") -> N ≠ AP | D23: AP
A24: 23 | B24: How many snowboarders does it take to screw in a lightbulb? Only 3: One to screw it in, another to film it, and a last one to say "sick turns brah!" | C24: =IF(sample_2a!C24<>sample_2b!C24, sample_2a!C24 & " ≠ " & sample_2b!C24, "") -> N ≠ CO | D24: CO
A25: 24 | B25: Why would Donald Trump want to lose the election? Winning means he'd need to live in a smaller house in a black neighborhood | C25: =IF(sample_2a!C25<>sample_2b!C25, sample_2a!C25 & " ≠ " & sample_2b!C25, "") -> RE ≠ PI | D25: N
A26: 25 | B26: The German kid asks the math teacher... What’s 4 + 5? The math teacher responds that it’s nine but when the teacher grades the homework he hadn’t written anything. | C26: =IF(sample_2a!C26<>sample_2b!C26, sample_2a!C26 & " ≠ " & sample_2b!C26, "")
A27: 26 | B27: The only reason why humans start wars is because we have time to kill | C27: =IF(sample_2a!C27<>sample_2b!C27, sample_2a!C27 & " ≠ " & sample_2b!C27, "")
A28: 27 | B28: What's the most searched word on Bing? Google | C28: =IF(sample_2a!C28<>sample_2b!C28, sample_2a!C28 & " ≠ " & sample_2b!C28, "")
A29: 28 | B29: What do you have if you've got a green ball in each hand? The Hulk's undivided attention. | C29: =IF(sample_2a!C29<>sample_2b!C29, sample_2a!C29 & " ≠ " & sample_2b!C29, "")
A30: 29 | B30: A man of the cloth was touring the country preaching. He stopped at an unfamiliar hotel chain for the night and asked for a room. He took his room key and told the young woman working behind the front desk, "There better be bibles in the nightstand and the porn channels disabled." She looked shocked and responded "No! They're normal you pervert!" | C30: =IF(sample_2a!C30<>sample_2b!C30, sample_2a!C30 & " ≠ " & sample_2b!C30, "") -> N ≠ RE | D30: N
A31: 30 | B31: What do Rick and Morty season 3 and my girlfriend have in common? They both don't exist | C31: =IF(sample_2a!C31<>sample_2b!C31, sample_2a!C31 & " ≠ " & sample_2b!C31, "")
A32: 31 | B32: What is the warmest period in the history of the world's climate called? Climax. | C32: =IF(sample_2a!C32<>sample_2b!C32, sample_2a!C32 & " ≠ " & sample_2b!C32, "")
A33: 32 | B33: A man goes to the doctor. Man: "Doctor, I have this problem." Doctor: "What is the issue?" Man: "Everytime I'm driving with my friends, we go through this tunnel, and I just can't control myself. I freak right out." Doctor: "Sounds like you have Carpool Tunnel Syndrome." | C33: =IF(sample_2a!C33<>sample_2b!C33, sample_2a!C33 & " ≠ " & sample_2b!C33, "") -> N ≠ M | D33: M
A34: 33 | B34: Where are the best elephant dentists? Tuscaloosa. | C34: =IF(sample_2a!C34<>sample_2b!C34, sample_2a!C34 & " ≠ " & sample_2b!C34, "")
A35: 34 | B35: I always park in handicapped spaces at the hospital Just to test their patients | C35: =IF(sample_2a!C35<>sample_2b!C35, sample_2a!C35 & " ≠ " & sample_2b!C35, "")
A36: 35 | B36: Four guys were working on a construction site They were talking about life and one of them misstepped on the scaffolding, fell from the fourth floor, hit his head and died on the spot. His friends were all shaken. They called 911, took all legal actions they should and their friend's body was removed. One of them, noticing they faced a problem, said: "Who's gonna tell his wife about this? "I'm not doing it!" Said another one. "Neither am I! You should do it!" Said the other. "I'm not going!" Said the first one. "Well, you're the most educated of us. It's better that you go, any other of us could deliver the news in a wrong way and give her a heart attack." Said the second guy. "All right, all right. I know how to do this." Said the first one and left to tell the new widow the sad news. The other two remained to close up the site and tidy up the place. A few minutes later the first guy comes back, six-pack of beer under his arm, drinking a cold one. "What the hell? Didn't you go tell the widow about our friend?" Said one guy. "I did exactly that." He said, taking another gulp. "And why are you back here with a six-pack?" "Well, I went to her house and she was at the door. I asked her: 'Aren't you the widow who was married to that guy who died on the construction site?' 'No, I'm not' she said. Then I said: 'Wanna bet a six-pack on it?'" *Sorry if this has been posted before. My father told me this one and I wanted to share.* | C36: =IF(sample_2a!C36<>sample_2b!C36, sample_2a!C36 & " ≠ " & sample_2b!C36, "")
A37: 36 | B37: The ass was phat. It was so phat it was alkaline. | C37: =IF(sample_2a!C37<>sample_2b!C37, sample_2a!C37 & " ≠ " & sample_2b!C37, "") -> N ≠ AP | D37: AP
A38: 37 | B38: What's the difference between Big Ben and the Queen of England? One is inhuman, intricately decorated, and exists only to mark the passage of time. &#x200B; The other one's a clock. | C38: =IF(sample_2a!C38<>sample_2b!C38, sample_2a!C38 & " ≠ " & sample_2b!C38, "") -> N ≠ PI | D38: PI
A39: 38 | B39: What do you call a monkey in a minefield? A baBOOM | C39: =IF(sample_2a!C39<>sample_2b!C39, sample_2a!C39 & " ≠ " & sample_2b!C39, "")
A40: 39 | B40: When I was a child, I loved astronomy and I actually saw Orion's belt many times. My Dad's nickname was Orion and he used to beat the shit out of me because I didn't like sports. | C40: =IF(sample_2a!C40<>sample_2b!C40, sample_2a!C40 & " ≠ " & sample_2b!C40, "")
A41: 40 | B41: A French guy got his Peugeot 206 stolen... So he bought a new one. One month later they stole his new Peugeot 206. He went to the cops and said : "Monsieur, They stole my 412!" | C41: =IF(sample_2a!C41<>sample_2b!C41, sample_2a!C41 & " ≠ " & sample_2b!C41, "") -> RE ≠ N | D41: RE
A42: 41 | B42: My wife left me because I’m too insecure. No wait, she's back. She just went to make a cup of tea. | C42: =IF(sample_2a!C42<>sample_2b!C42, sample_2a!C42 & " ≠ " & sample_2b!C42, "") -> N ≠ M | D42: N
A43: 42 | B43: What did Adam say when he woke up with a rib missing? Something smells fishy around here. | C43: =IF(sample_2a!C43<>sample_2b!C43, sample_2a!C43 & " ≠ " & sample_2b!C43, "")
A44: 43 | B44: If you wake up from a dream, but think you may still be in another dream... Tell someone nearby about the dream. If they seem interested, you're still asleep. | C44: =IF(sample_2a!C44<>sample_2b!C44, sample_2a!C44 & " ≠ " & sample_2b!C44, "")
A45: 44 | B45: Why can't the guy from Dirty Jobs get laid? He has a Mike Rowe penis. | C45: =IF(sample_2a!C45<>sample_2b!C45, sample_2a!C45 & " ≠ " & sample_2b!C45, "")
A46: 45 | B46: Tell a man a joke, he will laugh for a day Tell a redditor a joke, he will say it is a repost. | C46: =IF(sample_2a!C46<>sample_2b!C46, sample_2a!C46 & " ≠ " & sample_2b!C46, "") -> N ≠ CO | D46: N
A47: 46 | B47: My sister has a boyfriend He got mad because I fucked his girl. | C47: =IF(sample_2a!C47<>sample_2b!C47, sample_2a!C47 & " ≠ " & sample_2b!C47, "")
A48: 47 | B48: Bill Clinton ran a mile in nine and a half minutes. What happened next? Bush did 9:11. | C48: =IF(sample_2a!C48<>sample_2b!C48, sample_2a!C48 & " ≠ " & sample_2b!C48, "")
A49: 48 | B49: Which city in UK is known for it’s forest fires? Burningham. | C49: =IF(sample_2a!C49<>sample_2b!C49, sample_2a!C49 & " ≠ " & sample_2b!C49, "")
A50: 49 | B50: Did you hear about the toilet paper thieves? The police keep patting them down for clues... butt they're clean | C50: =IF(sample_2a!C50<>sample_2b!C50, sample_2a!C50 & " ≠ " & sample_2b!C50, "") -> N ≠ AP | D50: N
A51: 50 | B51: What do you have when you're holding two fuzzy green balls? Kermit's undivided attention. | C51: =IF(sample_2a!C51<>sample_2b!C51, sample_2a!C51 & " ≠ " & sample_2b!C51, "")
A52: 51 | B52: A man walks into a bar and sees his friend sitting beside a 12-inch pianist. He says to his friend, "That's amazing. How did you get that?" The man pulls out a bottle and tells him to rub it and make a wish. He rubs the bottle, and a puff of smoke pops out and tells him that he can have one wish. So the man thinks and says, "I wish I had a million bucks." The genie says, "OK, go outside, and your wish will be granted." The man goes outside, but all he finds are ducks filling the sky and roads. He goes back in and tells his friend what happend, and his friend replies, "I know. Did you really think I wanted a 12-inch pianist?" | C52: =IF(sample_2a!C52<>sample_2b!C52, sample_2a!C52 & " ≠ " & sample_2b!C52, "")
A53: 52 | B53: In a Russian deck of cards, what is the Trump card called? The Jack of Asses. | C53: =IF(sample_2a!C53<>sample_2b!C53, sample_2a!C53 & " ≠ " & sample_2b!C53, "")
A54: 53 | B54: Where do holy Russian and Greek ships park together? The Orthodocks | C54: =IF(sample_2a!C54<>sample_2b!C54, sample_2a!C54 & " ≠ " & sample_2b!C54, "")
A55: 54 | B55: I went to donate blood today, but they asked too many questions... Like, "who's blood is this" and "where did you get it?" | C55: =IF(sample_2a!C55<>sample_2b!C55, sample_2a!C55 & " ≠ " & sample_2b!C55, "") -> N ≠ AP | D55: N
A56: 55 | B56: Jesus is crucified and ascends to Heaven. When he arrives, he is beyond pissed at God. He says "Dad, why did you let them nail me to a piece of wood? That fucking hurt!" and God replies "Don't get cross with me, young man!" | C56: =IF(sample_2a!C56<>sample_2b!C56, sample_2a!C56 & " ≠ " & sample_2b!C56, "")
A57: 56 | B57: A little Jewish boy runs up to his mom and says, "Mama, I wanna sing really loud!" His mother says, "Shush with that! Not in the house!" So the boy runs up to his grandmother and says, "Gramma, I wanna sing really loud!" And his grandmother says, "My darling, you do whatever you want." So the boy takes in a deep breath... *"My Mom's tellin' me nooooo...* ***"BUT MY BUBBE!!! MY BUBBE'S TELLIN' ME YES!!!!!"*** | C57: =IF(sample_2a!C57<>sample_2b!C57, sample_2a!C57 & " ≠ " & sample_2b!C57, "")
A58: 57 | B58: Little Johnny once bought his Grandma a very nice... Little Johnny once bought his Grandma a very nice, luxurious toilet brush for her birthday. But when he went to visit her a couple of weeks later, it wasn't in the bathroom. Little Johnny asked his Grandma, “Gran, what happened to the toilet brush I gave you?” “Darling, I'm sorry but I just didn’t like it. After all those years, I’ve gotten used to the toilet paper, and this new thing was just too scratchy.” | C58: =IF(sample_2a!C58<>sample_2b!C58, sample_2a!C58 & " ≠ " & sample_2b!C58, "")
A59: 58 | B59: Why did the semen cross the road? I accidentally put on the wrong sock this morning. | C59: =IF(sample_2a!C59<>sample_2b!C59, sample_2a!C59 & " ≠ " & sample_2b!C59, "")
A60: 59 | B60: What is higher than a Giraffe's balls? Snoop Dogg | C60: =IF(sample_2a!C60<>sample_2b!C60, sample_2a!C60 & " ≠ " & sample_2b!C60, "")
A61: 60 | B61: If two soldiers give each other handjobs... Is it a Tug of War? | C61: =IF(sample_2a!C61<>sample_2b!C61, sample_2a!C61 & " ≠ " & sample_2b!C61, "") -> S ≠ CO | D61: N
A62: 61 | B62: Do you ever look at your balls and go "Aww nuts!" | C62: =IF(sample_2a!C62<>sample_2b!C62, sample_2a!C62 & " ≠ " & sample_2b!C62, "") -> G ≠ AP | D62: G
A63: 62 | B63: How many lovers does it take to screw in a lightbulb? Two, but it has to be a very large lightbulb. | C63: =IF(sample_2a!C63<>sample_2b!C63, sample_2a!C63 & " ≠ " & sample_2b!C63, "")
A64: 63 | B64: A lady's man goes to the doctor because he's been sick. After running several tests, the doctor tells the man, "I'm sorry, sir, but you have HAGS." "HAGS? What is that?" asks the startled man. "Herpes, AIDS, gonorrhea, and syphilis," replied the doctor. "What can you do for me, doc? Please, help me!" pleaded the man. "First, we have to quarantine you. Then, we put you on the HAGS diet," said the doctor. "What's the HAGS diet?" "Pancakes and pizza," the doctor answered. "Why pancakes and pizza?" the man asked. The doctor told him, "Those are the only two foods we can kick under the door." | C64: =IF(sample_2a!C64<>sample_2b!C64, sample_2a!C64 & " ≠ " & sample_2b!C64, "") -> S ≠ AP | D64: AP
A65: 64 | B65: Can someone come by and make my door frame bigger? I've fattened and I can't get out. | C65: =IF(sample_2a!C65<>sample_2b!C65, sample_2a!C65 & " ≠ " & sample_2b!C65, "")
A66: 65 | B66: All of my socks have holes in them It's where I put my feet | C66: =IF(sample_2a!C66<>sample_2b!C66, sample_2a!C66 & " ≠ " & sample_2b!C66, "") -> N ≠ AP | D66: N
A67: 66 | B67: How do you fit an elephant into a SafeWay grocery bag? You take 's' out of Safe and 'f' out of Way. | C67: =IF(sample_2a!C67<>sample_2b!C67, sample_2a!C67 & " ≠ " & sample_2b!C67, "")
A68: 67 | B68: What do you hate about repost? What do you hate about repost? | C68: =IF(sample_2a!C68<>sample_2b!C68, sample_2a!C68 & " ≠ " & sample_2b!C68, "")
A69: 68 | B69: What's the difference between a northern fairytale and a southern fairytale? A northern fairytale begins "Once upon a time ..." A southern fairytale begins "Y'all ain't gonna believe this shit ..." | C69: =IF(sample_2a!C69<>sample_2b!C69, sample_2a!C69 & " ≠ " & sample_2b!C69, "")
A70: 69 | B70: Why cant i differentiate between White Collar workers and Blue Collar workers? Its because i am Collarblind | C70: =IF(sample_2a!C70<>sample_2b!C70, sample_2a!C70 & " ≠ " & sample_2b!C70, "") -> CO ≠ RE/ CO | D70: CO
A71: 70 | B71: McDoogle walks into a bar. He starts ordering several shots to drown his sorrows. He says to the bar keep you know when someone builds houses does anyone say there goes McDoogle the house builder? No they don’t. McDoogle downs another shot and orders another. He takes the glass in his hand and says when someone rescues children from a burning building do they say there goes McDoogle the rescuer? No! They don’t. He downs the shot, but if you fuck one sheep... | C71: =IF(sample_2a!C71<>sample_2b!C71, sample_2a!C71 & " ≠ " & sample_2b!C71, "")
A72: 71 | B72: What is a priest's cell phone provider? Virgin mobile | C72: =IF(sample_2a!C72<>sample_2b!C72, sample_2a!C72 & " ≠ " & sample_2b!C72, "")
A73: 72 | B73: What should you do if a nutritionist knocks on your door? Vitamin! (Note: this only works with an American accent). | C73: =IF(sample_2a!C73<>sample_2b!C73, sample_2a!C73 & " ≠ " & sample_2b!C73, "") -> N ≠ CO | D73: RE
A74: 73 | B74: How I learned to mind my own business: I was walking past the mental hospital the other day, and all the patients were shouting "13,13,13. . ." The fence was too high to see over, but I saw a little gap in the planks, so I looked through to see what was going on. Some idiot poked me in the eye with a stick, then they all started shouting, "14, 14, 14. . .." | C74: =IF(sample_2a!C74<>sample_2b!C74, sample_2a!C74 & " ≠ " & sample_2b!C74, "") -> N ≠ M | D74: M
A75: 74 | B75: Paleontologists have just discovered a new species of dinosaur that was predominately lesbian... They're calling it the Lickalotopuss. | C75: =IF(sample_2a!C75<>sample_2b!C75, sample_2a!C75 & " ≠ " & sample_2b!C75, "")
A76: 75 | B76: I feel guilty about this parasite I ingested. It's been eating me up inside. | C76: =IF(sample_2a!C76<>sample_2b!C76, sample_2a!C76 & " ≠ " & sample_2b!C76, "") -> N ≠ AP | D76: N
A77: 76 | B77: A car mechanic bought a bed He slept under it | C77: =IF(sample_2a!C77<>sample_2b!C77, sample_2a!C77 & " ≠ " & sample_2b!C77, "")
A78: 77 | B78: My school has become an academy; it's sponsored by IKEA. Lessons are ok, but morning assembly takes ages. | C78: =IF(sample_2a!C78<>sample_2b!C78, sample_2a!C78 & " ≠ " & sample_2b!C78, "")
A79: 78 | B79: 'Doctor, I have a drinking problem!' 'I'm always drunk whenever I'm traveling between countries!' Doctor - 'Sounds like you're a borderline alcoholic.' | C79: =IF(sample_2a!C79<>sample_2b!C79, sample_2a!C79 & " ≠ " & sample_2b!C79, "") -> N ≠ M | D79: M
A80: 79 | B80: What do Ted Cruz and a tenage girl's bedroom have in common? **They're a mess.** Credit to [nimble navigator](https://www.reddit.com/r/The_Donald/comments/4bafa9/what_do_ted_cruz_and_a_teenage_girls_bedroom_have/) | C80: =IF(sample_2a!C80<>sample_2b!C80, sample_2a!C80 & " ≠ " & sample_2b!C80, "")
A81: 80 | B81: A priest and a rabbi are walking past a playground.... A priest and a rabbi are walking past a playground. The priest turns to the rabbi and says, "Let's go screw those kids." The rabbi replies, "Outta what?" | C81: =IF(sample_2a!C81<>sample_2b!C81, sample_2a!C81 & " ≠ " & sample_2b!C81, "")
A82: 81 | B82: The Spice Girls want to remind you to set your clocks back an hour tonight. Because tonight is the night, when two becomes one. | C82: =IF(sample_2a!C82<>sample_2b!C82, sample_2a!C82 & " ≠ " & sample_2b!C82, "")
A83: 82 | B83: My girlfriend says she doesn't trust me I guess that's just one more thing she has in common with my wife. | C83: =IF(sample_2a!C83<>sample_2b!C83, sample_2a!C83 & " ≠ " & sample_2b!C83, "") -> G ≠ N | D83: G
A84: 83 | B84: Why does killer whale feces smell so good? Because it's shampoo. | C84: =IF(sample_2a!C84<>sample_2b!C84, sample_2a!C84 & " ≠ " & sample_2b!C84, "")
A85: 84 | B85: I feel bad for eating all the Thanksgiving leftovers that were in the fridge... but it's hard to quit cold turkey. | C85: =IF(sample_2a!C85<>sample_2b!C85, sample_2a!C85 & " ≠ " & sample_2b!C85, "") -> N ≠ M | D85: M
A86: 85 | B86: Why does Donald Trump think Jesus was a liar? "He was a Middle-Easterner, but he had a Mexican name." | C86: =IF(sample_2a!C86<>sample_2b!C86, sample_2a!C86 & " ≠ " & sample_2b!C86, "") -> R ≠ PI | D86: N | E86: M, R, PI hence N
A87: 86 | B87: A priest wakes up on a Sunday morning He opens his window and sees that the sun is shining brightly, so he decides to call in sick for the day to play some golf. God and his angels sees this and is absolutely disgusted. How dare he miss a service just so he could play a silly game? 'Don't worry,' God says, 'I have just the *perfect* punishment for him.' The priest takes a swing and the ball bounces off several trees before rolling straight into the hole, scoring a perfect hole in one. One of the angels beside him says 'God, I thought you were going to *punish* the man?' And God responds 'I did. No one's ever going to believe him!' | C87: =IF(sample_2a!C87<>sample_2b!C87, sample_2a!C87 & " ≠ " & sample_2b!C87, "")
A88: 87 | B88: What do you call a sad/punk looking puppet? E(l)mo | C88: =IF(sample_2a!C88<>sample_2b!C88, sample_2a!C88 & " ≠ " & sample_2b!C88, "") -> N ≠ M | D88: M
A89: 88 | B89: Why do people wear glasses when they sleep? So that they can see their dreams. | C89: =IF(sample_2a!C89<>sample_2b!C89, sample_2a!C89 & " ≠ " & sample_2b!C89, "")
A90: 89 | B90: What's a Horse's favourite food? Bolo-Neigh-se | C90: =IF(sample_2a!C90<>sample_2b!C90, sample_2a!C90 & " ≠ " & sample_2b!C90, "")
A91: 90 | B91: Student : Sir, may I be excused? Lecturer : Although it's April, you May. | C91: =IF(sample_2a!C91<>sample_2b!C91, sample_2a!C91 & " ≠ " & sample_2b!C91, "")
A92: 91 | B92: Mickey Mouse and Minnie Mouse divorce In the courtroom the judge says to Mickey, “Mr Mouse, I don’t see any evidence to support your charge that Mrs Mouse has become insane”. Mickey gets a confused look on his face and says, “Judge, I never complained that she was insane. I said that she was fucking Goofy”. | C92: =IF(sample_2a!C92<>sample_2b!C92, sample_2a!C92 & " ≠ " & sample_2b!C92, "")
A93: 92 | B93: What do you call it when you dream about getting married? Bed wedding. | C93: =IF(sample_2a!C93<>sample_2b!C93, sample_2a!C93 & " ≠ " & sample_2b!C93, "")
A94: 93 | B94: Hitler, Salin, and EA were having a debate "Who amongst us is the most hated?" Hitler asked Stalin said "It is I, the Soviet Union killed more people than even you, Hitler!" EA says "NONSENSE! I've ruined dozens of game franchises. I am the most hated!" Hitler said "Why don't we hold a vote in hell and see who is the most hated of all?" The group agreed and Hitler left to go make the vote. After counting the ballots, Hitler returns and asks: "Who the fuck is Ajit Pai!?" *.*.*.*.*.*.*.*.*.*.*.* EDIT: I spell things poorly. EDIT 2: I made the front page, and was guilded! Thanks guys! I hope my joke made your day just a little better. | C94: =IF(sample_2a!C94<>sample_2b!C94, sample_2a!C94 & " ≠ " & sample_2b!C94, "")
A95: 94 | B95: What's the difference between a feminist and a suicide vest? People care if the vest gets triggered. | C95: =IF(sample_2a!C95<>sample_2b!C95, sample_2a!C95 & " ≠ " & sample_2b!C95, "")
A96: 95 | B96: why did the skeleton not ask his crush to the monster mash? He didn't have any guts | C96: =IF(sample_2a!C96<>sample_2b!C96, sample_2a!C96 & " ≠ " & sample_2b!C96, "") -> N ≠ AP | D96: N
A97: 96 | B97: I've invented a pie using French apples and Italian volcanoes Ive called it Pommepie | C97: =IF(sample_2a!C97<>sample_2b!C97, sample_2a!C97 & " ≠ " & sample_2b!C97, "")
A98: 97 | B98: Joe, Barrack, and Michele are out for dinner After a long day working at the White House, Obama decides to sit down for dinner with Biden and Michele. Even though he was aware of Biden's peanut allergy, Barrack decides to prank Biden by asking the White House chef to put peanuts in his food. When the food finally comes, Biden is furious. "Barrack! I've told you many times that I am very allergic to peanuts." Michelle steps in to defend her husband. "Calm down Joe! Honest mistakes happen and he is a busy man." Joe though does not buy Michelle's story. "Let's dispel the fiction that Barrack Obama does not know what he's doing. He knows exactly what he is doing." | C98: =IF(sample_2a!C98<>sample_2b!C98, sample_2a!C98 & " ≠ " & sample_2b!C98, "")
A99: 98 | B99: I've decided to keep my blender on the top shelf. It's a high whisk strategy. | C99: =IF(sample_2a!C99<>sample_2b!C99, sample_2a!C99 & " ≠ " & sample_2b!C99, "")
A100: 99 | B100: A man using Apple maps walks into a bar Or a pharmacy, or maybe a shoe store. | C100: =IF(sample_2a!C100<>sample_2b!C100, sample_2a!C100 & " ≠ " & sample_2b!C100, "")
...

Sheet sample_3a
A1: id | B1: joke | C1: category_human
A2: 1 | B2: Ironman walked up to Thor Ironman walked up to Thor and said "You have an ugly tie" Thor replied back "Respect my A-Thor-A-Tie!!!!" | C2: N
A3: 2 | B3: How do you manage to stop an aircraft from crashing? You buck up and man the controls, *plane* and simple. | C3: N
A4: 3 | B4: When people go underwater in movies, I like to hold my breath to see if I would have survived the same situation... Almost died in Finding Nemo | C4: N
A5: 4 | B5: I saw a refrigerator call a cab once Guess he was tired of running. | C5: N
A6: 5 | B6: Knight vs dragon A knight is fighting a dragon. He cuts its head, but the dragon grows two new heads. The knight cuts them, but the dragon grows 4 heads. The knight cuts them, the dragon grows 8 heads. The knight cuts them, the dragon grows 16 heads. The knight cuts them, the dragon grows 32 heads. The knight cuts them, the dragon grows 64 heads. The knight cuts them, the dragon grows 128 heads. The knight cuts them and the dragon is finally dead. It was an 8-bit dragon. | C6: N
A7: 6 | B7: Why can't miss piggy count to 100? She has a frog in her throat at 69 | C7: N
A8: 7 | B8: Why was the dolphin sad? Because it didn't know it's porpoise in life. Thank you. Thank you. | C8: N
A9: 8 | B9: What do you call a gay Asian guy? A Caucasian | C9: RE
A10: 9 | B10: The man who invented the Hokey Cokey died recently aged 93. At his funeral they went to put him in his coffin. They put his left leg in and then the fucking trouble started. | C10: N
A11: 10 | B11: What do you call it when someone impersonates himself on reddit? This guy this guys. | C11: N
A12: 11 | B12: Knock knock joke in China a: Knock knock b: Whose there? a: Yep! Its me, your buddy Hu! | C12: RE
A13: 12 | B13: What is your birthstone? Mine is rock bottom. | C13: N
... A101: 100 | B101: After arriving home from Bring Your Kid to Work day My son turned to me and said, “you have the most boring job ever. All you do is put people to sleep all day”...I’m an anesthesiologist | C101: CO

Sheet sample_3b
A1: id | B1: joke | C1: category_human
A2: 1 | B2: Ironman walked up to Thor Ironman walked up to Thor and said "You have an ugly tie" Thor replied back "Respect my A-Thor-A-Tie!!!!" | C2: N
A3: 2 | B3: How do you manage to stop an aircraft from crashing? You buck up and man the controls, *plane* and simple. | C3: N
A4: 3 | B4: When people go underwater in movies, I like to hold my breath to see if I would have survived the same situation... Almost died in Finding Nemo | C4: N
A5: 4 | B5: I saw a refrigerator call a cab once Guess he was tired of running. | C5: N
A6: 5 | B6: Knight vs dragon A knight is fighting a dragon. He cuts its head, but the dragon grows two new heads. The knight cuts them, but the dragon grows 4 heads. The knight cuts them, the dragon grows 8 heads. The knight cuts them, the dragon grows 16 heads. The knight cuts them, the dragon grows 32 heads. The knight cuts them, the dragon grows 64 heads. The knight cuts them, the dragon grows 128 heads. The knight cuts them and the dragon is finally dead. It was an 8-bit dragon. | C6: N
A7: 6 | B7: Why can't miss piggy count to 100? She has a frog in her throat at 69 | C7: G
A8: 7 | B8: Why was the dolphin sad? Because it didn't know it's porpoise in life. Thank you. Thank you. | C8: N
A9: 8 | B9: What do you call a gay Asian guy? A Caucasian | C9: S, RE
A10: 9 | B10: The man who invented the Hokey Cokey died recently aged 93. At his funeral they went to put him in his coffin. They put his left leg in and then the fucking trouble started. | C10: N
A11: 10 | B11: What do you call it when someone impersonates himself on reddit? This guy this guys. | C11: N
A12: 11 | B12: Knock knock joke in China a: Knock knock b: Whose there? a: Yep! Its me, your buddy Hu! | C12: RE
A13: 12 | B13: What is your birthstone? Mine is rock bottom. | C13: M
A14: 13 | B14: Old genie joke... Three men find themselves stranded on a deserted island. After several years, despite their differences, they become close friends out of necessity. One day, they find an old lamp. On rubbing it clean, they release a genie who grants them each one wish. "I wish to return to my old life!" Two of the men shout, disappearing in a puff of smoke. The third man, a little slow, looks around at the empty island. Overcome by loneliness, he mutters, "I wish my friends were here."
A15: 14 | B15: Potentially funny joke about a bed I just haven't made it up yet. | C15: N
A16: 15 | B16: As a vet, attention to detail is vital. However, attention to de rest of de animal is important too. | C16: CO
A17: 16 | B17: Why did the chicken cross the road To get to the other side lololol 😂😂😂 | C17: N
A18: 17 | B18: Police officers have been playing Pokemon Go a lot longer than the rest y'all have... 'Gotta catch Jamal' | C18: RE, CO
A19: 18 | B19: What's a skeleton's favorite insturment a trom**BONE** | C19: N
A20: 19 | B20: How do you know the hipster knows ju jitsu? He knew that move before you did. | C20: N
A21: 20 | B21: A man wants to jump off a bridge... (This joke is courtesy of Emo Philips) I was walking across a bridge one day, and I saw a man standing on the edge, about to jump off. So I ran over and said "Stop! Don't do it!" "Why shouldn't I?" he said. "Well, there's so much to live for!" "Like what?" "Well... are you religious?" He said yes. I said, "Me too! Are you Christian or Buddhist?" "Christian." "Me too! Are you Catholic or Protestant? "Protestant." "Me too! Are you Episcopalian or Baptist?" "Baptist" "Wow! Me too! Are you Baptist Church of God or Baptist Church of the Lord?" "Baptist Church of God!" "Me too! Are you original Baptist Church of God, or are you reformed Baptist Church of God?" "Reformed Baptist Church of God!" "Me too! Are you Reformed Baptist Church of God, reformation of 1879, or Reformed Baptist Church of God, reformation of 1915?" He said, "Reformed Baptist Church of God, reformation of 1915!" I said, "Die, heretic scum", and pushed him off. | C21: R
A22: 21 | B22: So 6ix9ine could be facing life in prison Maybe a mumble rapper will finally finish a sentence | C22: CO
A23: 22 | B23: So I went to the doctor to check on my exams. He asked me: - What’s you sign? Me: - Cancer Doctor: - Now that’s a coincidence. | C23: CO
A24: 23 | B24: Where is the safest place to be shopping during an earthquake? A stationary store. | C24: N
A25: 24 | B25: Just said Hi to this guy on the plane and everyone freaked out Apparently his name was Jack | C25: N
A26: 25 | B26: Why does Donald Trump secretly want to lose the election? To Make America Great Again | C26: PI
... A54: 53 | B54: At McDonald's Employee: Are you going to eat here? Customer: Well, now that you said it... I'll go to burger king! | C54: N
A55: 54 | B55: I don't know if digital anal sex toys would be legal.... But iAnal
A56: 55 | B56: An Englishman, Scotsman and an Irishman trying to get into the Olympics with no tickets The Englishman found a large wooden pole lying on the ground near him. He picked it up, put it under his arm, walked in the gate and said 'Bentley, England, pole vaulting' and they let him in. The Scotsman picked up a manhole cover, put it under his arm, walked in the gate and said 'McGregor, Scotland, discus' and they let him in. The Irish man picked up a roll of barbed wire, put it under his arm, walked in the gate and said 'Murphy, Ireland, fencing.' | C56: RE, CO
A57: 56 | B57: What do you call a typo on a tombstone A grave mistake. | C57: N
A58: 57 | B58: Why do they put a cock on a weather vane? Because if they put a cunt on there, the wind would blow right through it. | C58: G
A59: 58 | B59: How do you get away with murder? You kill a Saudi dissident. &#x200B; Were you expecting a longer punchline? | C59: RE, R
A60: 59 | B60: Four college students have been out partying for a night before an exam. The next morning, they wake up and realize they're late, so as they make their way to the exam, they come up with excuses to make for the professor. By the time they arrive the exam is almost over, so they head over to the professor to ask if they can take it the next day. They tell him they tried their best to come on time, but their tire blew out and it took too long to replace it. The professor tells them, "Don't worry about it. You can take it today and, since there's almost no time left, you only have to answer one question. If you get it right, I'll give you an A on the test. One thing, though- you all have to be in separate rooms." The students, thinking this is even better than they thought, excitedly go to their rooms, take their seats and look at the question: Which tire blew out? | C60: N
A61: 60 | B61: Thank you banks Thank you banks for the student loans, car loans and mortgages, which helped me survive my life. I don't know if I can ever repay you. | C61: N
A62: 61 | B62: What do you call an Indian who marries out of cast? Outcast | C62: RE
A63: 62 | B63: What is your best joke that involves soup? I need some help. Jokes just need to involve soup. Does not matter what kind of soup or what is being done with the soup. | C63: N
A64: 63 | B64: My ex left me two years ago because I was an insensitive bastard. I still don't think about her to this day. | C64: N
A65: 64 | B65: Joe fails his third test of the semester. His teacher meets with his mother after school that day and she agrees to talk to him about learning disabilities and getting extra help. After they meet, Joe is shaken. "I'm a slow learner?" thinks Joe. "Wow. You learn something new every couple of days." | C65: AP
A66: 65 | B66: I'm not a mute and that's more than some people can say. | C66: AP
A67: 66 | B67: What do you call a waffle that you dropped at the beach? sandy Eggo | C67: N
... A101: 100 | B101: After arriving home from Bring Your Kid to Work day My son turned to me and said, “you have the most boring job ever. All you do is put people to sleep all day”...I’m an anesthesiologist | C101: CO

Sheet conflict_3
A1: id | B1: joke | C1: Conflict | D1: Adjudication
A2: 1 | B2: Ironman walked up to Thor Ironman walked up to Thor and said "You have an ugly tie" Thor replied back "Respect my A-Thor-A-Tie!!!!" | C2: =IF(sample_3a!C2<>sample_3b!C2, sample_3a!C2 & " ≠ " & sample_3b!C2, "")
A3: 2 | B3: How do you manage to stop an aircraft from crashing? You buck up and man the controls, *plane* and simple. | C3: =IF(sample_3a!C3<>sample_3b!C3, sample_3a!C3 & " ≠ " & sample_3b!C3, "")
A4: 3 | B4: When people go underwater in movies, I like to hold my breath to see if I would have survived the same situation... Almost died in Finding Nemo | C4: =IF(sample_3a!C4<>sample_3b!C4, sample_3a!C4 & " ≠ " & sample_3b!C4, "")
A5: 4 | B5: I saw a refrigerator call a cab once Guess he was tired of running. | C5: =IF(sample_3a!C5<>sample_3b!C5, sample_3a!C5 & " ≠ " & sample_3b!C5, "")
A6: 5 | B6: Knight vs dragon A knight is fighting a dragon. He cuts its head, but the dragon grows two new heads. The knight cuts them, but the dragon grows 4 heads. The knight cuts them, the dragon grows 8 heads. The knight cuts them, the dragon grows 16 heads. The knight cuts them, the dragon grows 32 heads. The knight cuts them, the dragon grows 64 heads. The knight cuts them, the dragon grows 128 heads. The knight cuts them and the dragon is finally dead. It was an 8-bit dragon. | C6: =IF(sample_3a!C6<>sample_3b!C6, sample_3a!C6 & " ≠ " & sample_3b!C6, "")
A7: 6 | B7: Why can't miss piggy count to 100? She has a frog in her throat at 69 | C7: =IF(sample_3a!C7<>sample_3b!C7, sample_3a!C7 & " ≠ " & sample_3b!C7, "") -> N ≠ G | D7: N
A8: 7 | B8: Why was the dolphin sad? Because it didn't know it's porpoise in life. Thank you. Thank you. | C8: =IF(sample_3a!C8<>sample_3b!C8, sample_3a!C8 & " ≠ " & sample_3b!C8, "")
A9: 8 | B9: What do you call a gay Asian guy? A Caucasian | C9: =IF(sample_3a!C9<>sample_3b!C9, sample_3a!C9 & " ≠ " & sample_3b!C9, "") -> RE ≠ S, RE | D9: S, RE
A10: 9 | B10: The man who invented the Hokey Cokey died recently aged 93. At his funeral they went to put him in his coffin. They put his left leg in and then the fucking trouble started. | C10: =IF(sample_3a!C10<>sample_3b!C10, sample_3a!C10 & " ≠ " & sample_3b!C10, "")
A11: 10 | B11: What do you call it when someone impersonates himself on reddit? This guy this guys. | C11: =IF(sample_3a!C11<>sample_3b!C11, sample_3a!C11 & " ≠ " & sample_3b!C11, "")
A12: 11 | B12: Knock knock joke in China a: Knock knock b: Whose there? a: Yep! Its me, your buddy Hu! | C12: =IF(sample_3a!C12<>sample_3b!C12, sample_3a!C12 & " ≠ " & sample_3b!C12, "")
A13: 12 | B13: What is your birthstone? Mine is rock bottom. | C13: =IF(sample_3a!C13<>sample_3b!C13, sample_3a!C13 & " ≠ " & sample_3b!C13, "") -> N ≠ M | D13: M
A14: 13 | B14: Old genie joke... Three men find themselves stranded on a deserted island. After several years, despite their differences, they become close friends out of necessity. One day, they find an old lamp. On rubbing it clean, they release a genie who grants them each one wish. "I wish to return to my old life!" Two of the men shout, disappearing in a puff of smoke. The third man, a little slow, looks around at the empty island. Overcome by loneliness, he mutters, "I wish my friends were here." | C14: =IF(sample_3a!C14<>sample_3b!C14, sample_3a!C14 & " ≠ " & sample_3b!C14, "") -> N ≠ | D14: N
A15: 14 | B15: Potentially funny joke about a bed I just haven't made it up yet. | C15: =IF(sample_3a!C15<>sample_3b!C15, sample_3a!C15 & " ≠ " & sample_3b!C15, "")
A16: 15 | B16: As a vet, attention to detail is vital. However, attention to de rest of de animal is important too. | C16: =IF(sample_3a!C16<>sample_3b!C16, sample_3a!C16 & " ≠ " & sample_3b!C16, "")
A17: 16 | B17: Why did the chicken cross the road To get to the other side lololol 😂😂😂 | C17: =IF(sample_3a!C17<>sample_3b!C17, sample_3a!C17 & " ≠ " & sample_3b!C17, "")
A18: 17 | B18: Police officers have been playing Pokemon Go a lot longer than the rest y'all have... 'Gotta catch Jamal' | C18: =IF(sample_3a!C18<>sample_3b!C18, sample_3a!C18 & " ≠ " & sample_3b!C18, "") -> RE ≠ RE, CO | D18: RE, CO
A19: 18 | B19: What's a skeleton's favorite insturment a trom**BONE** | C19: =IF(sample_3a!C19<>sample_3b!C19, sample_3a!C19 & " ≠ " & sample_3b!C19, "")
A20: 19 | B20: How do you know the hipster knows ju jitsu? He knew that move before you did. | C20: =IF(sample_3a!C20<>sample_3b!C20, sample_3a!C20 & " ≠ " & sample_3b!C20, "") -> PI ≠ N | D20: PI
A21: 20 | B21: A man wants to jump off a bridge... (This joke is courtesy of Emo Philips) I was walking across a bridge one day, and I saw a man standing on the edge, about to jump off. So I ran over and said "Stop! Don't do it!" "Why shouldn't I?" he said. "Well, there's so much to live for!" "Like what?" "Well... are you religious?" He said yes. I said, "Me too! Are you Christian or Buddhist?" "Christian." "Me too! Are you Catholic or Protestant? "Protestant." "Me too! Are you Episcopalian or Baptist?" "Baptist" "Wow! Me too! Are you Baptist Church of God or Baptist Church of the Lord?" "Baptist Church of God!" "Me too! Are you original Baptist Church of God, or are you reformed Baptist Church of God?" "Reformed Baptist Church of God!" "Me too! Are you Reformed Baptist Church of God, reformation of 1879, or Reformed Baptist Church of God, reformation of 1915?" He said, "Reformed Baptist Church of God, reformation of 1915!" I said, "Die, heretic scum", and pushed him off. | C21: =IF(sample_3a!C21<>sample_3b!C21, sample_3a!C21 & " ≠ " & sample_3b!C21, "")
A22: 21 | B22: So 6ix9ine could be facing life in prison Maybe a mumble rapper will finally finish a sentence | C22: =IF(sample_3a!C22<>sample_3b!C22, sample_3a!C22 & " ≠ " & sample_3b!C22, "") -> N ≠ CO | D22: N
A23: 22 | B23: So I went to the doctor to check on my exams. He asked me: - What’s you sign? Me: - Cancer Doctor: - Now that’s a coincidence. | C23: =IF(sample_3a!C23<>sample_3b!C23, sample_3a!C23 & " ≠ " & sample_3b!C23, "") -> N ≠ CO | D23: N
A24: 23 | B24: Where is the safest place to be shopping during an earthquake? A stationary store. | C24: =IF(sample_3a!C24<>sample_3b!C24, sample_3a!C24 & " ≠ " & sample_3b!C24, "")
A25: 24 | B25: Just said Hi to this guy on the plane and everyone freaked out Apparently his name was Jack | C25: =IF(sample_3a!C25<>sample_3b!C25, sample_3a!C25 & " ≠ " & sample_3b!C25, "")
A26: 25 | B26: Why does Donald Trump secretly want to lose the election? To Make America Great Again | C26: =IF(sample_3a!C26<>sample_3b!C26, sample_3a!C26 & " ≠ " & sample_3b!C26, "")
A27: 26 | B27: A truck driver would keep himself entertained by running over lawyers. Every time he saw a lawyer walking along the road, he would swerve to hit him. There would be a loud "thud", and then he would swerve back on the road. As the truck driver drove along one day, he saw a priest hitch hiking, he pulled over and asked the priest, "Where are you going, Father?" The priest said he was on his way to his church up the road. "I'll give you a lift." The priest climbed into the passenger seat and the truck driver continued down the road. Suddenly, the truck driver saw a lawyer walking down the road and instinctively swerved to hit him. At the last minute, he remembered he had a priest in the truck and swerved back onto the road. Even though he knew he missed the lawyer, he still heard a loud "thud." Unsure of where the noise came from, he glanced in his mirrors. When he didn't see anything, he turned to the priest and said, "I'm sorry, Father. I almost hit a lawyer." The priest replied, "That's OK, I got the bitch with the door." | C27: =IF(sample_3a!C27<>sample_3b!C27, sample_3a!C27 & " ≠ " & sample_3b!C27, "") -> R ≠ R, CO | D27: R, CO
A28: 27 | B28: The only "B" word you should call women is beautiful. Bitches love being called beautiful. | C28: =IF(sample_3a!C28<>sample_3b!C28, sample_3a!C28 & " ≠ " & sample_3b!C28, "")
A29: 28 | B29: Why do laxatives have a best before date? &#x200B; If they go off, what's the worst that can happen?. | C29: =IF(sample_3a!C29<>sample_3b!C29, sample_3a!C29 & " ≠ " & sample_3b!C29, "")
A30: 29 | B30: Why should Tories use protection when dealing with Boris? Because a Johnson is known to induce Labour | C30: =IF(sample_3a!C30<>sample_3b!C30, sample_3a!C30 & " ≠ " & sample_3b!C30, "") -> N ≠ PI | D30: PI
A31: 30 | B31: A Mexican student was told to turn in his essay He said "No way, I ain't no snitch!" | C31: =IF(sample_3a!C31<>sample_3b!C31, sample_3a!C31 & " ≠ " & sample_3b!C31, "")
A32: 31 | B32: 26 letters walk into a bar. The bartender says, "I can't serve you!" because they're all lowercase. It was just as well, because they aren't there to buy any drinks. They're there to vandalize the place. The bartender gets angry. "What are you doing to my bar?!" The o told him, "We're protesting capitalism!" | C32: =IF(sample_3a!C32<>sample_3b!C32, sample_3a!C32 & " ≠ " & sample_3b!C32, "") -> N ≠ PI | D32: N
A33: 32 | B33: When is it ladyparts-grabbing time for Donald Trump? When the little hand is on the 10. | C33: =IF(sample_3a!C33<>sample_3b!C33, sample_3a!C33 & " ≠ " & sample_3b!C33, "") -> PI ≠ PI, G | D33: PI
A34: 33 | B34: One day, Gregor Samsa awakes to find himself turned into a real plant. The twist on the Kafka novel is called "The metamorphosynthesis" | C34: =IF(sample_3a!C34<>sample_3b!C34, sample_3a!C34 & " ≠ " & sample_3b!C34, "")
A35: 34 | B35: I peed on the elevator. That's wrong on SO many levels. | C35: =IF(sample_3a!C35<>sample_3b!C35, sample_3a!C35 & " ≠ " & sample_3b!C35, "")
A36: 35 | B36: Don't have sex with blondes. That would be fucking stupid. | C36: =IF(sample_3a!C36<>sample_3b!C36, sample_3a!C36 & " ≠ " & sample_3b!C36, "") -> AP ≠ G | D36: AP
A37: 36 | B37: What's the difference between an old bus stop and a lobster with breast implants? One is a crusty bus station and the other is a busty crustacean. | C37: =IF(sample_3a!C37<>sample_3b!C37, sample_3a!C37 & " ≠ " & sample_3b!C37, "") -> AP ≠ N | D37: N
A38: 37 | B38: I like to cook my meat like I like my women Low and slow. | C38: =IF(sample_3a!C38<>sample_3b!C38, sample_3a!C38 & " ≠ " & sample_3b!C38, "")
A39: 38 | B39: How does Gordon Ramsay spent his Friday nights? Fucking raw. | C39: =IF(sample_3a!C39<>sample_3b!C39, sample_3a!C39 & " ≠ " & sample_3b!C39, "")
A40: 39 | B40: To all the ladies that turned me down Man you dodged a bullet | C40: =IF(sample_3a!C40<>sample_3b!C40, sample_3a!C40 & " ≠ " & sample_3b!C40, "")
A41: 40 | B41: I sent ten puns to my friend, hoping at least one would make him laugh, but... No pun in ten did. | C41: =IF(sample_3a!C41<>sample_3b!C41, sample_3a!C41 & " ≠ " & sample_3b!C41, "")
A42: 41 | B42: q: What do you call a cow with no legs? A: Ground beef. Q: What do you call a cow with three legs? A: Lean beef. Q: What do you call a cow with two legs? A: Your mom. | C42: =IF(sample_3a!C42<>sample_3b!C42, sample_3a!C42 & " ≠ " & sample_3b!C42, "")
A43: 42 | B43: What long and hard thing does a Norwegian wife get on her wedding night? A last name | C43: =IF(sample_3a!C43<>sample_3b!C43, sample_3a!C43 & " ≠ " & sample_3b!C43, "") -> RE ≠ RE, G | D43: RE
A44: 43 | B44: What did the black pedophile say? "Hey kid, wanna help me snatch some candy?" | C44: =IF(sample_3a!C44<>sample_3b!C44, sample_3a!C44 & " ≠ " & sample_3b!C44, "")
A45: 44 | B45: I told my bengal kitten he cost me so much money I couldn’t help but love him. My gf asked if I felt the same way about her. Now it’s just me and kitten. | C45: =IF(sample_3a!C45<>sample_3b!C45, sample_3a!C45 & " ≠ " & sample_3b!C45, "")
A46: 45 | B46: Where did the identical twins go after they went crazy? The insame asylum | C46: =IF(sample_3a!C46<>sample_3b!C46, sample_3a!C46 & " ≠ " & sample_3b!C46, "")
A47: 46 | B47: Why do assembly programmers need to know how to swim? | C47: =IF(sample_3a!C47<>sample_3b!C47, sample_3a!C47 & " ≠ " & sample_3b!C47, "") -> N ≠ CO | D47: N
A48: 47 | B48: About a month before he died, my Uncle had his back covered in lard. After that, he went downhill fast. | C48: =IF(sample_3a!C48<>sample_3b!C48, sample_3a!C48 & " ≠ " & sample_3b!C48, "") -> N ≠ M | D48: N
A49: 48 | B49: A man stands in the middle of the sidewalk and is staring at an apartment building. The people around him got curious and they all stared at the same direction. Soon a crowd of 5 turned into twenties and then a hundred. Rumors have also formed, one suggested that maybe there is a suicide attempt about to take place. The rumor of a suicide turned into a homicide and even rape. The police soon joined and went into the building to investigate. The man who stared at the building finally looked down and walked away amidst the confusion of the crowd, "Why were you staring at the building? Was there an incident taking place?" Asked a person. The man replied, "No, my nose bled." | C49: =IF(sample_3a!C49<>sample_3b!C49, sample_3a!C49 & " ≠ " & sample_3b!C49, "")
A50: 49 | B50: So this man is on a plane, And he asks the flight attendant whether she will help him join the mile high club. "I'm sorry sir but I don't give a flying fuck" | C50: =IF(sample_3a!C50<>sample_3b!C50, sample_3a!C50 & " ≠ " & sample_3b!C50, "") -> N ≠ N, G | D50: N
A51: 50 | B51: Two guys walk into a bar.. You'd think that second one would have ducked. | C51: =IF(sample_3a!C51<>sample_3b!C51, sample_3a!C51 & " ≠ " & sample_3b!C51, "")
A52: 51 | B52: My dog died last night. Lucky bastard. | C52: =IF(sample_3a!C52<>sample_3b!C52, sample_3a!C52 & " ≠ " & sample_3b!C52, "") -> N ≠ M | D52: N
A53: 52 | B53: Black Ninja “I’m about to go incognegro” | C53: =IF(sample_3a!C53<>sample_3b!C53, sample_3a!C53 & " ≠ " & sample_3b!C53, "")
A54: 53 | B54: At McDonald's Employee: Are you going to eat here? Customer: Well, now that you said it... I'll go to burger king! | C54: =IF(sample_3a!C54<>sample_3b!C54, sample_3a!C54 & " ≠ " & sample_3b!C54, "")
A55: 54 | B55: I don't know if digital anal sex toys would be legal.... But iAnal | C55: =IF(sample_3a!C55<>sample_3b!C55, sample_3a!C55 & " ≠ " & sample_3b!C55, "") -> N ≠ | D55: N
A56: 55 | B56: An Englishman, Scotsman and an Irishman trying to get into the Olympics with no tickets The Englishman found a large wooden pole lying on the ground near him. He picked it up, put it under his arm, walked in the gate and said 'Bentley, England, pole vaulting' and they let him in. The Scotsman picked up a manhole cover, put it under his arm, walked in the gate and said 'McGregor, Scotland, discus' and they let him in. The Irish man picked up a roll of barbed wire, put it under his arm, walked in the gate and said 'Murphy, Ireland, fencing.' | C56: =IF(sample_3a!C56<>sample_3b!C56, sample_3a!C56 & " ≠ " & sample_3b!C56, "") -> RE ≠ RE, CO | D56: RE
A57: 56 | B57: What do you call a typo on a tombstone A grave mistake. | C57: =IF(sample_3a!C57<>sample_3b!C57, sample_3a!C57 & " ≠ " & sample_3b!C57, "")
A58: 57 | B58: Why do they put a cock on a weather vane? Because if they put a cunt on there, the wind would blow right through it. | C58: =IF(sample_3a!C58<>sample_3b!C58, sample_3a!C58 & " ≠ " & sample_3b!C58, "") -> N ≠ G | D58: N
A59: 58 | B59: How do you get away with murder? You kill a Saudi dissident. &#x200B; Were you expecting a longer punchline? | C59: =IF(sample_3a!C59<>sample_3b!C59, sample_3a!C59 & " ≠ " & sample_3b!C59, "") -> RE ≠ RE, R | D59: RE
A60: 59 | B60: Four college students have been out partying for a night before an exam. The next morning, they wake up and realize they're late, so as they make their way to the exam, they come up with excuses to make for the professor. By the time they arrive the exam is almost over, so they head over to the professor to ask if they can take it the next day. They tell him they tried their best to come on time, but their tire blew out and it took too long to replace it. The professor tells them, "Don't worry about it. You can take it today and, since there's almost no time left, you only have to answer one question. If you get it right, I'll give you an A on the test. One thing, though- you all have to be in separate rooms." The students, thinking this is even better than they thought, excitedly go to their rooms, take their seats and look at the question: Which tire blew out? | C60: =IF(sample_3a!C60<>sample_3b!C60, sample_3a!C60 & " ≠ " & sample_3b!C60, "") -> Age ≠ N | D60: N
A61: 60 | B61: Thank you banks Thank you banks for the student loans, car loans and mortgages, which helped me survive my life. I don't know if I can ever repay you. | C61: =IF(sample_3a!C61<>sample_3b!C61, sample_3a!C61 & " ≠ " & sample_3b!C61, "")
A62: 61 | B62: What do you call an Indian who marries out of cast? Outcast | C62: =IF(sample_3a!C62<>sample_3b!C62, sample_3a!C62 & " ≠ " & sample_3b!C62, "")
A63: 62 | B63: What is your best joke that involves soup? I need some help. Jokes just need to involve soup. Does not matter what kind of soup or what is being done with the soup. | C63: =IF(sample_3a!C63<>sample_3b!C63, sample_3a!C63 & " ≠ " & sample_3b!C63, "")
A64: 63 | B64: My ex left me two years ago because I was an insensitive bastard. I still don't think about her to this day. | C64: =IF(sample_3a!C64<>sample_3b!C64, sample_3a!C64 & " ≠ " & sample_3b!C64, "")
A65: 64 | B65: Joe fails his third test of the semester. His teacher meets with his mother after school that day and she agrees to talk to him about learning disabilities and getting extra help. After they meet, Joe is shaken. "I'm a slow learner?" thinks Joe. "Wow. You learn something new every couple of days." | C65: =IF(sample_3a!C65<>sample_3b!C65, sample_3a!C65 & " ≠ " & sample_3b!C65, "") -> M ≠ AP | D65: M
A66: 65 | B66: I'm not a mute and that's more than some people can say. | C66: =IF(sample_3a!C66<>sample_3b!C66, sample_3a!C66 & " ≠ " & sample_3b!C66, "") -> N ≠ AP | D66: N
A67: 66 | B67: What do you call a waffle that you dropped at the beach? sandy Eggo | C67: =IF(sample_3a!C67<>sample_3b!C67, sample_3a!C67 & " ≠ " & sample_3b!C67, "") -> AP ≠ N | D67: N
A68: 67 | B68: Plateaus are... ...the highest form of geographical flattery. | C68: =IF(sample_3a!C68<>sample_3b!C68, sample_3a!C68 & " ≠ " & sample_3b!C68, "")
A69: 68 | B69: During a job interview yesterday, I poured some water into a cup and it overflowed slightly. "Nervous?" asked the interviewer. "No," I said. "I always give 110%" | C69: =IF(sample_3a!C69<>sample_3b!C69, sample_3a!C69 & " ≠ " & sample_3b!C69, "")
A70: 69 | B70: One day, you wake up and everyone has a number over their heads. The number is counting down by the second. Eventually, someone's number reaches zero, and.... They sneeze. Their number resets. | C70: =IF(sample_3a!C70<>sample_3b!C70, sample_3a!C70 & " ≠ " & sample_3b!C70, "")
A71: 70 | B71: What's the difference between toilet paper and a towel? You don't know? So it was you! | C71: =IF(sample_3a!C71<>sample_3b!C71, sample_3a!C71 & " ≠ " & sample_3b!C71, "")
A72: 71 | B72: I MEAN, WHAT AM I SUPPOSED TO DO WITH THIS PENT-UP RIVER OF ANGER TO KEEP IT FROM SPILLING OUT??!?!?!!!?! DAM IT!! | C72: =IF(sample_3a!C72<>sample_3b!C72, sample_3a!C72 & " ≠ " & sample_3b!C72, "")
A73: 72 | B73: Where do sperm whales come from? The Testic Isles. (Or out of moby's dick). | C73: =IF(sample_3a!C73<>sample_3b!C73, sample_3a!C73 & " ≠ " & sample_3b!C73, "")
A74: 73 | B74: Criminals flood in from across the English Channel. "They have no respect for our laws," said a Marseille policeman ahead of England's first game. | C74: =IF(sample_3a!C74<>sample_3b!C74, sample_3a!C74 & " ≠ " & sample_3b!C74, "") -> N ≠ RE | D74: RE
A75: 74 | B75: So Pepe is now an international hate symbol... FeelsBadMan. | C75: =IF(sample_3a!C75<>sample_3b!C75, sample_3a!C75 & " ≠ " & sample_3b!C75, "")
A76: 75 | B76: I went skydiving today. The guy strapped himself to me, we jumped out of the plane, and as we began to fall he yelled in my ear "So how long you been an instructor? | C76: =IF(sample_3a!C76<>sample_3b!C76, sample_3a!C76 & " ≠ " & sample_3b!C76, "")
A77: 76 | B77: How many boxes of crayons can a Marine eat in a day? Semper Five | C77: =IF(sample_3a!C77<>sample_3b!C77, sample_3a!C77 & " ≠ " & sample_3b!C77, "") -> N ≠ CO | D77: CO
A78: 77 | B78: What did the Turks say to Mustafa Kemal when he introduced democracy? Atta' Turk! | C78: =IF(sample_3a!C78<>sample_3b!C78, sample_3a!C78 & " ≠ " & sample_3b!C78, "") -> N ≠ RE | D78: N
A79: 78 | B79: What's black and white and red all over? A nun falling down the stairs | C79: =IF(sample_3a!C79<>sample_3b!C79, sample_3a!C79 & " ≠ " & sample_3b!C79, "") -> R ≠ CO, R | D79: R
A80: 79 | B80: I finally got an A on my essay! Now I need to add US and get freedom. | C80: =IF(sample_3a!C80<>sample_3b!C80, sample_3a!C80 & " ≠ " & sample_3b!C80, "")
A81: 80 | B81: There is a fine line between a numerator and a denominator Only a fraction of people can understand this | C81: =IF(sample_3a!C81<>sample_3b!C81, sample_3a!C81 & " ≠ " & sample_3b!C81, "")
A82: 81 | B82: 3 Men and a Woman are stranded on an Island Like everyone, they try to establish contact to other people at first and they build a shelter. After about 3 Weeks the Men approach the Woman with a proposal to let one of the 3 have sex with her every other day so that everyones Sex drive could be fulfilled. The Woman agrees and they have a great year together. However, shortly after the 14th Month of being stranded, the woman dies. The first week is tough for the men, but they try to boost eachothers morale. The second week is almost unbearable. The third week makes them feel so bad they want to die. In the fourth week they finally decide that they should bury her corpse. | C82: =IF(sample_3a!C82<>sample_3b!C82, sample_3a!C82 & " ≠ " & sample_3b!C82, "")
A83: 82 | B83: My wife told me she is leaving me if I don't stop stealing her kitchen utensils But that's a whisk I am willing to take | C83: =IF(sample_3a!C83<>sample_3b!C83, sample_3a!C83 & " ≠ " & sample_3b!C83, "")
A84: 83 | B84: Who’s the worst Disney character? Bin Alladin, he flew a magic carpet straight into the twin towers. | C84: =IF(sample_3a!C84<>sample_3b!C84, sample_3a!C84 & " ≠ " & sample_3b!C84, "")
A85: 84 | B85: Love story An Engineer and a Doctor fell in love with the same woman. The Doctor used to give her a rose everyday, but the Engineer used to give her an apple everyday. Intrigued, the woman asked the Engineer one day "There is a meaning of giving rose in Love. Why are you giving me apple?" The Engineer replied, “An Apple a day keeps Doctor away.” | C85: =IF(sample_3a!C85<>sample_3b!C85, sample_3a!C85 & " ≠ " & sample_3b!C85, "")
A86: 85 | B86: How can California secede from the Us without any documents or agreements? Earthquakes | C86: =IF(sample_3a!C86<>sample_3b!C86, sample_3a!C86 & " ≠ " & sample_3b!C86, "")
A87: 86 | B87: What's orange and sounds like a parrot? Donald Trump repeating the same shit over and over again 😂 | C87: =IF(sample_3a!C87<>sample_3b!C87, sample_3a!C87 & " ≠ " & sample_3b!C87, "") -> N ≠ PI | D87: PI
A88: 87 | B88: If I had a dollar for every downvote... I'd be rich from this post. | C88: =IF(sample_3a!C88<>sample_3b!C88, sample_3a!C88 & " ≠ " & sample_3b!C88, "") -> N ≠ M | D88: N
A89: 88 | B89: What does idk stand for? Literally everyone I ask doesn't know. | C89: =IF(sample_3a!C89<>sample_3b!C89, sample_3a!C89 & " ≠ " & sample_3b!C89, "")
A90: 89 | B90: My friend told me shes sexually attracted to horses and its tearing her up inside Literally | C90: =IF(sample_3a!C90<>sample_3b!C90, sample_3a!C90 & " ≠ " & sample_3b!C90, "") -> N ≠ RE, N | D90: N
A91: 90 | B91: Why are nonces good at the recorder Because they are very experienced in blowing small holes | C91: =IF(sample_3a!C91<>sample_3b!C91, sample_3a!C91 & " ≠ " & sample_3b!C91, "") -> R ≠ Age, S | D91: R
A92: 91 | B92: I like my women like I like my whisky Twelve years old and named Jack Daniel's for some reason | C92: =IF(sample_3a!C92<>sample_3b!C92, sample_3a!C92 & " ≠ " & sample_3b!C92, "") -> S ≠ Age, S | D92: Age, S
A93: 92 | B93: What do you call it when a black man, a white man, an Asian man and an Indian man are all running alongside each other? The Human race | C93: =IF(sample_3a!C93<>sample_3b!C93, sample_3a!C93 & " ≠ " & sample_3b!C93, "") -> RE ≠ RE, N | D93: RE
A94: 93 | B94: So my wife walked in on me while I was shaving my balls and asked me what I was doing... Apparently “meal prepping” wasn’t the right answer. | C94: =IF(sample_3a!C94<>sample_3b!C94, sample_3a!C94 & " ≠ " & sample_3b!C94, "") -> N ≠ G | D94: N
A95: 94 | B95: What do you call a dog that can do magic? A Labracadabrador | C95: =IF(sample_3a!C95<>sample_3b!C95, sample_3a!C95 & " ≠ " & sample_3b!C95, "")
A96: 95 | B96: What if animals "were" injured in the making of a film. Do they list that in the credits? Tim hurt one monkey. He is very sorry. | C96: =IF(sample_3a!C96<>sample_3b!C96, sample_3a!C96 & " ≠ " & sample_3b!C96, "")
A97: 96 | B97: Two gay guys walk into a bar. One sits down slowly, the other pushes his stool in. | C97: =IF(sample_3a!C97<>sample_3b!C97, sample_3a!C97 & " ≠ " & sample_3b!C97, "")
A98: 97 | B98: She wanted space. My wife says I take things too literally. I say if you say you want "space" and I put you in a vacuum chamber chilled to 2.7 degrees Kelvin you got what you asked for. Roughly. | C98: =IF(sample_3a!C98<>sample_3b!C98, sample_3a!C98 & " ≠ " & sample_3b!C98, "")
A99: 98 | B99: An old grandma brings a bus driver a bag of peanuts every day. First the bus driver enjoyed the peanuts but after a week of eating them he asked: "Please granny, don't bring me peanuts anymore. Have them yourself.". The granny answers: "You know, I don't have teeth anymore. I just prefer to suck the chocolate around them." | C99: =IF(sample_3a!C99<>sample_3b!C99, sample_3a!C99 & " ≠ " & sample_3b!C99, "")
A100: 99 | B100: Why do gorillas have such big noses? Because they’ve got big fingers! | C100: =IF(sample_3a!C100<>sample_3b!C100, sample_3a!C100 & " ≠ " & sample_3b!C100, "")
...

Sheet sample_4a
A1: id | B1: joke | C1: category_human
A2: 1 | B2: True Story. So my grandpa, my father and I were out on a car ride to the beach when I was 11. I always loved riding with my grandpa because he told all of his war stories from serving in WWII, and as a kid they were always cool to hear. We stopped at a stop sign, and a car with 3 asian kids pulled up behind us ( maybe 18/19 year olds) and immediately started blaring the horn. My grandpa simply flips them the bird, and starts checking oncoming traffic. Impatient I guess, the car behind slams their gas and goes around us, yelling “f**k you* as they went by. My grandpa, mumbling and cussing. Just checks traffic and continues on. About 5 minutes after that, there’s the car that was behind us, in an accident on the side of the road. The kids were outside waving down traffic trying to get help, so my grandpa slowed down and rolled down his window. As we went by, he shouted “AND THAT’S FOR PEARL HARBOR” and continued to drive away, laughing so hard he couldn’t breathe | C2: RE;age
A3: 2 | B3: What animal has two gray legs and two brown legs? &#x200B; An elephant with diarrhea | C3: N
A4: 3 | B4: My father has the heart of a lion and a lifetime ban at the zoo. | C4: N
A5: 4 | B5: My fidget spinner finally helps me calm down. I sharpened it like a shuriken and I kill people with it now. | C5: N
A6: 5 | B6: Why did Barty Crouch quit drinking? Because it was making him moody. | C6: N
A7: 6 | B7: A man and his wife are having sex Out in the woods when a bee enters the woman's vagina. The couple stop and immediately go to the hospital. The doctor tells them there is a simple solution. Cover the mans penis in honey and have him lure the bee out. The husband says "what if the bee stings me?". The doctor replied there is a chance. The man is too scared so the doctor must do it. He takes off his clothes, slathers his Dick with honey, and inserts it. The bee flies out. "Is it over?" The husband says?" "Nah I think there's a nest in here let me try again" | C7: G
A8: 7 | B8: I was thinking to my myself earlier.... ...orchestra conductors are brilliant Hitler impersonators | C8: N
A9: 8 | B9: What do you call a unicorn with a soar throat? Horse... | C9: N
A10: 9 | B10: Jewish Business A fleeing Taliban, desperate for water, was trudging through the Afghanistan desert when he saw something far off in the distance. Hoping to find water, he hurried towards it, only to find a little old Jewish man at a small stand selling ties. The Taliban asked, “Do you have water?” The Jewish man replied, “I have no water. Would you like to buy a tie? They are only $5.” The Taliban shouted, “Infidel! I do not need an over-priced tie! I need water! I should kill you, but I must find water first!” “OK, OK” said the old Jewish man, “It does not matter that you do not want to buy a tie and that you hate me. I will show you that I am bigger than that. If you continue over that hill to the east for about two miles, you will find a lovely restaurant. It has all the ice cold water you need. Shalom.” Muttering, the Taliban staggered away over the hill. Several hours later he staggered back, almost dead… “Your f***ing brother won’t let me in without a tie!” | C10: RE;age
A11: 10 | B11: What std can you get from errape Hearing aids | C11: N
A12: 11 | B12: A guy walks into r/askhistorians and asks if there was such a thing as New World deniers Everybody knows the answer is Christopher Columbus and can't get the joke approved! | C12: N
A13: 12 | B13: So today the founder of IKEA passed away... I wonder how long it took his family to build his casket? | C13: N
... A21: 20 | B21: If you kill 10 children out of a 100.. Only 90 kids will remember | C21: Age
A22: 21 | B22: I used to have a friend called Vince, he was great until we had an argument and we stopped being friends Now he's Vincen't
A23: 22 | B23: The World Trade Centre ordered pizza They wanted pepperoni but all they got was plain | C23: PI
A24: 23 | B24: What do you call a prostitute who takes cookies as payment? An Oreho. | C24: CO;G
A25: 24 | B25: How do you keep bacon from curling in the pan? Take away their brooms. | C25: N
A26: 25 | B26: An ice cream man is driving his truck on a hot summer day. He glances in his rear-view mirror, and notices a man running behind the truck. The man looks sweaty and exhausted and it's clear that he's been chasing the truck for blocks, if not longer. The driver immediately pulls over. "I'm sorry I didn't see you!" he says to the man when he gets to the window. "What can I get for you?" "Oh, I don't want any ice cream," says the man, after a long pause to catch his breath. "I just wanted to let you know that I'm vegan." | C26: PI
A27: 26 | B27: Donald Trump and Hillary Clinton are on a sinking ship in the middle of the ocean. Who survives? AMERICA! | C27: PI
A28: 27 | B28: What do you call a pig with high aspirations in life? Hambitious | C28: N
A29: 28 | B29: What do you call a dog that floats in water? a good buoy | C29: N
A30: 29 | B30: Your wife is sick! Angry John barged into the Cardiologist clinic and held him by his collar. John: Did u tell my wife,she has a cute vagina? Doctor: U fuckin' idiot, I told her that she has Acute Angina..!! | C30: G;CO
A31: 30 | B31: Nietzsche's girlfriend said "honey, what's wrong?" He replied "nothing." | C31: G
A32: 31 | B32: Four men are in the hospital waiting room because their wives are having babies. A nurse goes up to the first guy and says, “Congratulations! You’re the father of twins.” “That’s odd,” answers the man. “I work for the Minnesota Twins!” A nurse says to the second guy, “Congratulations! You’re the father of triplets!” “That’s weird,” answers the second man. “I work for the 3M company!” A nurse tells the third man, “Congratulations! You’re the father of quadruplets!” “That’s strange,” he answers. “I work for the Four Seasons hotel!” The last man is groaning and banging his head against the wall. “What’s wrong?” the others ask. “I work for 7 Up!” | C32: G;CO
A33: 32 | B33: Hey did you hear about the fire at the circuis? It was in'tents' | C33: N
A34: 33 | B34: The sea level is going to rise 7 feet by 2100.... ...I think he could play center in the NBA. | C34: N
... A101: 100 | B101: What do you call an African-American California Highway Patrol Officer? A Chocolate CHiP. | C101: RE

Sheet sample_4b
A1: id | B1: joke | C1: category_human
A2: 1 | B2: True Story. So my grandpa, my father and I were out on a car ride to the beach when I was 11. I always loved riding with my grandpa because he told all of his war stories from serving in WWII, and as a kid they were always cool to hear. We stopped at a stop sign, and a car with 3 asian kids pulled up behind us ( maybe 18/19 year olds) and immediately started blaring the horn. My grandpa simply flips them the bird, and starts checking oncoming traffic. Impatient I guess, the car behind slams their gas and goes around us, yelling “f**k you* as they went by. My grandpa, mumbling and cussing. Just checks traffic and continues on. About 5 minutes after that, there’s the car that was behind us, in an accident on the side of the road. The kids were outside waving down traffic trying to get help, so my grandpa slowed down and rolled down his window. As we went by, he shouted “AND THAT’S FOR PEARL HARBOR” and continued to drive away, laughing so hard he couldn’t breathe | C2: PI
A3: 2 | B3: What animal has two gray legs and two brown legs? &#x200B; An elephant with diarrhea | C3: N
A4: 3 | B4: My father has the heart of a lion and a lifetime ban at the zoo. | C4: N
A5: 4 | B5: My fidget spinner finally helps me calm down. I sharpened it like a shuriken and I kill people with it now. | C5: M
A6: 5 | B6: Why did Barty Crouch quit drinking? Because it was making him moody. | C6: M
A7: 6 | B7: A man and his wife are having sex Out in the woods when a bee enters the woman's vagina. The couple stop and immediately go to the hospital. The doctor tells them there is a simple solution. Cover the mans penis in honey and have him lure the bee out. The husband says "what if the bee stings me?". The doctor replied there is a chance. The man is too scared so the doctor must do it. He takes off his clothes, slathers his Dick with honey, and inserts it. The bee flies out. "Is it over?" The husband says?" "Nah I think there's a nest in here let me try again" | C7: N
A8: 7 | B8: I was thinking to my myself earlier.... ...orchestra conductors are brilliant Hitler impersonators | C8: PI
A9: 8 | B9: What do you call a unicorn with a soar throat? Horse... | C9: N
A10: 9 | B10: Jewish Business A fleeing Taliban, desperate for water, was trudging through the Afghanistan desert when he saw something far off in the distance. Hoping to find water, he hurried towards it, only to find a little old Jewish man at a small stand selling ties. The Taliban asked, “Do you have water?” The Jewish man replied, “I have no water. Would you like to buy a tie? They are only $5.” The Taliban shouted, “Infidel! I do not need an over-priced tie! I need water! I should kill you, but I must find water first!” “OK, OK” said the old Jewish man, “It does not matter that you do not want to buy a tie and that you hate me. I will show you that I am bigger than that. If you continue over that hill to the east for about two miles, you will find a lovely restaurant. It has all the ice cold water you need. Shalom.” Muttering, the Taliban staggered away over the hill. Several hours later he staggered back, almost dead… “Your f***ing brother won’t let me in without a tie!” | C10: RE
A11: 10 | B11: What std can you get from errape Hearing aids | C11: AP
A12: 11 | B12: A guy walks into r/askhistorians and asks if there was such a thing as New World deniers Everybody knows the answer is Christopher Columbus and can't get the joke approved! | C12: PI
A13: 12 | B13: So today the founder of IKEA passed away... I wonder how long it took his family to build his casket? | C13: N
A14: 13 | B14: Say "Unreliable Airline" three times fast. Delta Delta Delta | C14: N | E14: <3
A15: 14 | B15: In case of WW3 or any other trouble on Earth, Elon Musk can Become next level Noah With his Elon's Ark. | C15: R
A16: 15 | B16: Once upon a time there was a sperm named Stanley who lived inside a famous movie actor. Stanley was a very healthy sperm. He'd do pushups and somersaults and limber himself up all the time, while the other sperm just lay around on their fat asses not doing a thing. One day, one of them became curious enough to ask Stanley why he exercised all day. Stanley said,"Look, pal, only one sperm gets a woman pregnant and when the right time comes, I am going to be that one." A few days later, they all felt themselves getting hotter and hotter, and they knew that it was getting to be their time to go. They were released abruptly and, sure enough, there was Stanley swimming far ahead of all the others. All of a sudden, Stanley stopped, turned around, and began to swim back with all his might. "Go back! Go Back!" he screamed. "It's a blow job!" | C16: N
A17: 16 | B17: I directed a movie about my broken leg. It had a stellar supporting cast. | C17: AP
A18: 17 | B18: Grandpa Goes Fishing With His Grandson (NSFW) One day, Grandpa decides to take his Grandson out on the lake to fish. About an hour in, Grandpa pulls out a cigarette and starts smoking. The Grandson looks over, "Hey Grandpa, that looks really cool, can I smoke a cigarette too?" Grandpa, "Well, can you touch your dick to your own asshole?" Grandson, "Uhhh, no?" Grandpa, "Then you're not old enough." So they keep fishing, and about half an hour later Grandpa pulls out a bottle of whiskey. Grandson, "Hey Grandpa, can I drink some whiskey too?" Grandpa, "Can you touch your dick to your own asshole?" Grandson, "No" Grandpa, "Then you're not old enough." Once it started getting dark they decided to pack up and head back home. Once they get home, both of their noses are filled with the wonderful smell of freshly baked cookies that Grandma had made. The Grandson starts chowing down on them, and the Grandpa leans over to his Grandson. Grandpa, "Hey Grandson, that looks pretty good. Do you mind if I have one? Grandson, "Can you touch your dick to your asshole?" Grandpa, "Actually, I can." Grandson, "Then go fuck yourself, these are my cookies!" My absolute go to joke to tell people | C18: N
A19: 18 | B19: Doctor: How is your headach Man: She is fine. | C19: G
A20: 19 | B20: Swedish Fisherman Once there were two Swedes out fishing in their dory. THen one of the Swedes remared to the other: "Look, theres a leak in our boat!" The other Swede replied: "No worries, we'll just drill a new hole, and the water will flow out again". | C20: RE
A21: 20 | B21: If you kill 10 children out of a 100.. Only 90 kids will remember | C21: N
A22: 21 | B22: I used to have a friend called Vince, he was great until we had an argument and we stopped being friends Now he's Vincen't | C22: N
A23: 22 | B23: The World Trade Centre ordered pizza They wanted pepperoni but all they got was plain | C23: N
A24: 23 | B24: What do you call a prostitute who takes cookies as payment? An Oreho. | C24: CO
A25: 24 | B25: How do you keep bacon from curling in the pan? Take away their brooms. | C25: N
A26: 25 | B26: An ice cream man is driving his truck on a hot summer day. He glances in his rear-view mirror, and notices a man running behind the truck. The man looks sweaty and exhausted and it's clear that he's been chasing the truck for blocks, if not longer. The driver immediately pulls over. "I'm sorry I didn't see you!" he says to the man when he gets to the window. "What can I get for you?" "Oh, I don't want any ice cream," says the man, after a long pause to catch his breath. "I just wanted to let you know that I'm vegan." | C26: PI
... A101: 100 | B101: What do you call an African-American California Highway Patrol Officer? A Chocolate CHiP. | C101: RE

Sheet conflict_4
A1: id | B1: joke | C1: Conflict | D1: Adjudication
A2: 1 | B2: True Story. So my grandpa, my father and I were out on a car ride to the beach when I was 11. I always loved riding with my grandpa because he told all of his war stories from serving in WWII, and as a kid they were always cool to hear. We stopped at a stop sign, and a car with 3 asian kids pulled up behind us ( maybe 18/19 year olds) and immediately started blaring the horn. My grandpa simply flips them the bird, and starts checking oncoming traffic. Impatient I guess, the car behind slams their gas and goes around us, yelling “f**k you* as they went by. My grandpa, mumbling and cussing. Just checks traffic and continues on. About 5 minutes after that, there’s the car that was behind us, in an accident on the side of the road. The kids were outside waving down traffic trying to get help, so my grandpa slowed down and rolled down his window. As we went by, he shouted “AND THAT’S FOR PEARL HARBOR” and continued to drive away, laughing so hard he couldn’t breathe | C2: =IF(sample_4a!C2<>sample_4b!C2, sample_4a!C2 & " ≠ " & sample_4b!C2, "") -> RE;age ≠ PI | D2: RE
A3: 2 | B3: What animal has two gray legs and two brown legs? &#x200B; An elephant with diarrhea | C3: =IF(sample_4a!C3<>sample_4b!C3, sample_4a!C3 & " ≠ " & sample_4b!C3, "")
A4: 3 | B4: My father has the heart of a lion and a lifetime ban at the zoo. | C4: =IF(sample_4a!C4<>sample_4b!C4, sample_4a!C4 & " ≠ " & sample_4b!C4, "")
A5: 4 | B5: My fidget spinner finally helps me calm down. I sharpened it like a shuriken and I kill people with it now. | C5: =IF(sample_4a!C5<>sample_4b!C5, sample_4a!C5 & " ≠ " & sample_4b!C5, "") -> N ≠ M | D5: M
A6: 5 | B6: Why did Barty Crouch quit drinking? Because it was making him moody. | C6: =IF(sample_4a!C6<>sample_4b!C6, sample_4a!C6 & " ≠ " & sample_4b!C6, "") -> N ≠ M | D6: N
A7: 6 | B7: A man and his wife are having sex Out in the woods when a bee enters the woman's vagina. The couple stop and immediately go to the hospital. The doctor tells them there is a simple solution. Cover the mans penis in honey and have him lure the bee out. The husband says "what if the bee stings me?". The doctor replied there is a chance. The man is too scared so the doctor must do it. He takes off his clothes, slathers his Dick with honey, and inserts it. The bee flies out. "Is it over?" The husband says?" "Nah I think there's a nest in here let me try again" | C7: =IF(sample_4a!C7<>sample_4b!C7, sample_4a!C7 & " ≠ " & sample_4b!C7, "") -> G ≠ N | D7: N
A8: 7 | B8: I was thinking to my myself earlier.... ...orchestra conductors are brilliant Hitler impersonators | C8: =IF(sample_4a!C8<>sample_4b!C8, sample_4a!C8 & " ≠ " & sample_4b!C8, "") -> N ≠ PI | D8: CO
A9: 8 | B9: What do you call a unicorn with a soar throat? Horse... | C9: =IF(sample_4a!C9<>sample_4b!C9, sample_4a!C9 & " ≠ " & sample_4b!C9, "")
A10: 9 | B10: Jewish Business A fleeing Taliban, desperate for water, was trudging through the Afghanistan desert when he saw something far off in the distance. Hoping to find water, he hurried towards it, only to find a little old Jewish man at a small stand selling ties. The Taliban asked, “Do you have water?” The Jewish man replied, “I have no water. Would you like to buy a tie? They are only $5.” The Taliban shouted, “Infidel! I do not need an over-priced tie! I need water! I should kill you, but I must find water first!” “OK, OK” said the old Jewish man, “It does not matter that you do not want to buy a tie and that you hate me. I will show you that I am bigger than that. If you continue over that hill to the east for about two miles, you will find a lovely restaurant. It has all the ice cold water you need. Shalom.” Muttering, the Taliban staggered away over the hill. Several hours later he staggered back, almost dead… “Your f***ing brother won’t let me in without a tie!” | C10: =IF(sample_4a!C10<>sample_4b!C10, sample_4a!C10 & " ≠ " & sample_4b!C10, "") -> RE;age ≠ RE | D10: RE
A11: 10 | B11: What std can you get from errape Hearing aids | C11: =IF(sample_4a!C11<>sample_4b!C11, sample_4a!C11 & " ≠ " & sample_4b!C11, "") -> N ≠ AP | D11: AP
A12: 11 | B12: A guy walks into r/askhistorians and asks if there was such a thing as New World deniers Everybody knows the answer is Christopher Columbus and can't get the joke approved! | C12: =IF(sample_4a!C12<>sample_4b!C12, sample_4a!C12 & " ≠ " & sample_4b!C12, "") -> N ≠ PI | D12: N
A13: 12 | B13: So today the founder of IKEA passed away... I wonder how long it took his family to build his casket? | C13: =IF(sample_4a!C13<>sample_4b!C13, sample_4a!C13 & " ≠ " & sample_4b!C13, "")
A14: 13 | B14: Say "Unreliable Airline" three times fast. Delta Delta Delta | C14: =IF(sample_4a!C14<>sample_4b!C14, sample_4a!C14 & " ≠ " & sample_4b!C14, "")
A15: 14 | B15: In case of WW3 or any other trouble on Earth, Elon Musk can Become next level Noah With his Elon's Ark. | C15: =IF(sample_4a!C15<>sample_4b!C15, sample_4a!C15 & " ≠ " & sample_4b!C15, "") -> N ≠ R | D15: N
A16: 15 | B16: Once upon a time there was a sperm named Stanley who lived inside a famous movie actor. Stanley was a very healthy sperm. He'd do pushups and somersaults and limber himself up all the time, while the other sperm just lay around on their fat asses not doing a thing. One day, one of them became curious enough to ask Stanley why he exercised all day. Stanley said,"Look, pal, only one sperm gets a woman pregnant and when the right time comes, I am going to be that one." A few days later, they all felt themselves getting hotter and hotter, and they knew that it was getting to be their time to go. They were released abruptly and, sure enough, there was Stanley swimming far ahead of all the others. All of a sudden, Stanley stopped, turned around, and began to swim back with all his might. "Go back! Go Back!" he screamed. "It's a blow job!" | C16: =IF(sample_4a!C16<>sample_4b!C16, sample_4a!C16 & " ≠ " & sample_4b!C16, "") -> G ≠ N | D16: N
A17: 16 | B17: I directed a movie about my broken leg. It had a stellar supporting cast. | C17: =IF(sample_4a!C17<>sample_4b!C17, sample_4a!C17 & " ≠ " & sample_4b!C17, "") -> N ≠ AP | D17: AP
A18: 17 | B18: Grandpa Goes Fishing With His Grandson (NSFW) One day, Grandpa decides to take his Grandson out on the lake to fish. About an hour in, Grandpa pulls out a cigarette and starts smoking. The Grandson looks over, "Hey Grandpa, that looks really cool, can I smoke a cigarette too?" Grandpa, "Well, can you touch your dick to your own asshole?" Grandson, "Uhhh, no?" Grandpa, "Then you're not old enough." So they keep fishing, and about half an hour later Grandpa pulls out a bottle of whiskey. Grandson, "Hey Grandpa, can I drink some whiskey too?" Grandpa, "Can you touch your dick to your own asshole?" Grandson, "No" Grandpa, "Then you're not old enough." Once it started getting dark they decided to pack up and head back home. Once they get home, both of their noses are filled with the wonderful smell of freshly baked cookies that Grandma had made. The Grandson starts chowing down on them, and the Grandpa leans over to his Grandson. Grandpa, "Hey Grandson, that looks pretty good. Do you mind if I have one? Grandson, "Can you touch your dick to your asshole?" Grandpa, "Actually, I can." Grandson, "Then go fuck yourself, these are my cookies!" My absolute go to joke to tell people | C18: =IF(sample_4a!C18<>sample_4b!C18, sample_4a!C18 & " ≠ " & sample_4b!C18, "") -> Age ≠ N | D18: Age
A19: 18 | B19: Doctor: How is your headach Man: She is fine. | C19: =IF(sample_4a!C19<>sample_4b!C19, sample_4a!C19 & " ≠ " & sample_4b!C19, "")
A20: 19 | B20: Swedish Fisherman Once there were two Swedes out fishing in their dory. THen one of the Swedes remared to the other: "Look, theres a leak in our boat!" The other Swede replied: "No worries, we'll just drill a new hole, and the water will flow out again". | C20: =IF(sample_4a!C20<>sample_4b!C20, sample_4a!C20 & " ≠ " & sample_4b!C20, "") -> RE;age ≠ RE | D20: RE
A21: 20 | B21: If you kill 10 children out of a 100.. Only 90 kids will remember | C21: =IF(sample_4a!C21<>sample_4b!C21, sample_4a!C21 & " ≠ " & sample_4b!C21, "") -> Age ≠ N | D21: N
A22: 21 | B22: I used to have a friend called Vince, he was great until we had an argument and we stopped being friends Now he's Vincen't | C22: =IF(sample_4a!C22<>sample_4b!C22, sample_4a!C22 & " ≠ " & sample_4b!C22, "") -> ≠ N | D22: N
A23: 22 | B23: The World Trade Centre ordered pizza They wanted pepperoni but all they got was plain | C23: =IF(sample_4a!C23<>sample_4b!C23, sample_4a!C23 & " ≠ " & sample_4b!C23, "") -> PI ≠ N | D23: N
A24: 23 | B24: What do you call a prostitute who takes cookies as payment? An Oreho. | C24: =IF(sample_4a!C24<>sample_4b!C24, sample_4a!C24 & " ≠ " & sample_4b!C24, "") -> CO;G ≠ CO | D24: CO
A25: 24 | B25: How do you keep bacon from curling in the pan? Take away their brooms. | C25: =IF(sample_4a!C25<>sample_4b!C25, sample_4a!C25 & " ≠ " & sample_4b!C25, "")
A26: 25 | B26: An ice cream man is driving his truck on a hot summer day. He glances in his rear-view mirror, and notices a man running behind the truck. The man looks sweaty and exhausted and it's clear that he's been chasing the truck for blocks, if not longer. The driver immediately pulls over. "I'm sorry I didn't see you!" he says to the man when he gets to the window. "What can I get for you?" "Oh, I don't want any ice cream," says the man, after a long pause to catch his breath. "I just wanted to let you know that I'm vegan." | C26: =IF(sample_4a!C26<>sample_4b!C26, sample_4a!C26 & " ≠ " & sample_4b!C26, "")
A27: 26 | B27: Donald Trump and Hillary Clinton are on a sinking ship in the middle of the ocean. Who survives? AMERICA! | C27: =IF(sample_4a!C27<>sample_4b!C27, sample_4a!C27 & " ≠ " & sample_4b!C27, "")
A28: 27 | B28: What do you call a pig with high aspirations in life? Hambitious | C28: =IF(sample_4a!C28<>sample_4b!C28, sample_4a!C28 & " ≠ " & sample_4b!C28, "")
A29: 28 | B29: What do you call a dog that floats in water? a good buoy | C29: =IF(sample_4a!C29<>sample_4b!C29, sample_4a!C29 & " ≠ " & sample_4b!C29, "")
A30: 29 | B30: Your wife is sick! Angry John barged into the Cardiologist clinic and held him by his collar. John: Did u tell my wife,she has a cute vagina? Doctor: U fuckin' idiot, I told her that she has Acute Angina..!! | C30: =IF(sample_4a!C30<>sample_4b!C30, sample_4a!C30 & " ≠ " & sample_4b!C30, "") -> G;CO ≠ G | D30: G
A31: 30 | B31: Nietzsche's girlfriend said "honey, what's wrong?" He replied "nothing." | C31: =IF(sample_4a!C31<>sample_4b!C31, sample_4a!C31 & " ≠ " & sample_4b!C31, "") -> G ≠ N | D31: N
A32: 31 | B32: Four men are in the hospital waiting room because their wives are having babies. A nurse goes up to the first guy and says, “Congratulations! You’re the father of twins.” “That’s odd,” answers the man. “I work for the Minnesota Twins!” A nurse says to the second guy, “Congratulations! You’re the father of triplets!” “That’s weird,” answers the second man. “I work for the 3M company!” A nurse tells the third man, “Congratulations! You’re the father of quadruplets!” “That’s strange,” he answers. “I work for the Four Seasons hotel!” The last man is groaning and banging his head against the wall. “What’s wrong?” the others ask. “I work for 7 Up!” | C32: =IF(sample_4a!C32<>sample_4b!C32, sample_4a!C32 & " ≠ " & sample_4b!C32, "") -> G;CO ≠ N | D32: N
A33: 32 | B33: Hey did you hear about the fire at the circuis? It was in'tents' | C33: =IF(sample_4a!C33<>sample_4b!C33, sample_4a!C33 & " ≠ " & sample_4b!C33, "")
A34: 33 | B34: The sea level is going to rise 7 feet by 2100.... ...I think he could play center in the NBA. | C34: =IF(sample_4a!C34<>sample_4b!C34, sample_4a!C34 & " ≠ " & sample_4b!C34, "")
A35: 34 | B35: How do you keep a baby from crawling in circles? nail the other hand to the floor. | C35: =IF(sample_4a!C35<>sample_4b!C35, sample_4a!C35 & " ≠ " & sample_4b!C35, "")
A36: 35 | B36: Why is Peter Pan always flying? Because he Neverlands | C36: =IF(sample_4a!C36<>sample_4b!C36, sample_4a!C36 & " ≠ " & sample_4b!C36, "")
A37: 36 | B37: Why don’t skeletons play music in church? Because they got no organs. | C37: =IF(sample_4a!C37<>sample_4b!C37, sample_4a!C37 & " ≠ " & sample_4b!C37, "")
A38: 37 | B38: Honest degree slogans Diploma: Have fun with those loans, guys... Associates: Man, fuck this. Bachelor's: Middle class af Masters: d i f f e r e n t i a t i o n Doctors: You did it for the title, doc Postdoc: The prospect of not going to school scares you. | C38: =IF(sample_4a!C38<>sample_4b!C38, sample_4a!C38 & " ≠ " & sample_4b!C38, "")
A39: 38 | B39: How do you turn a duck into a soul singer? Put it in the microwave until its bill withers | C39: =IF(sample_4a!C39<>sample_4b!C39, sample_4a!C39 & " ≠ " & sample_4b!C39, "")
A40: 39 | B40: A mormon was having an affair with a 15 year old girl who had lied about her age, when he learned the truth he broke it off and over the next few week guilt set in and he confessed to his wife. She screamed at him, "How could you cheat on me like that with an older woman!?!?!?". | C40: =IF(sample_4a!C40<>sample_4b!C40, sample_4a!C40 & " ≠ " & sample_4b!C40, "") -> G;R;Age ≠ R | D40: R
A41: 40 | B41: A scientist performed an expirement on a spider... He put the spider on a table and told it to jump, and it did. Then, he plucked off one of its legs and told it to jump, and it jumped again, but not as high as the first time. The scientist did this again and again, taking off another leg each time until all of its legs were gone. When the spider had no legs, he told it to jump. It just laid there, not jumping. The scientist’s conclusion: Spiders without legs are deaf. | C41: =IF(sample_4a!C41<>sample_4b!C41, sample_4a!C41 & " ≠ " & sample_4b!C41, "") -> N ≠ CO | D41: CO
A42: 41 | B42: Why do Moon Rocks taste better than Earth Rocks? Because they're a little Meteor | C42: =IF(sample_4a!C42<>sample_4b!C42, sample_4a!C42 & " ≠ " & sample_4b!C42, "")
A43: 42 | B43: A math teacher invented something. A math teacher invented the worlds first underwater bulldozer. He called it his 'Sub-tractor.' | C43: =IF(sample_4a!C43<>sample_4b!C43, sample_4a!C43 & " ≠ " & sample_4b!C43, "") -> N ≠ CO | D43: N
A44: 43 | B44: I just found out they made a heart-shaped dairy-lovers pizza Too cheesy for me though | C44: =IF(sample_4a!C44<>sample_4b!C44, sample_4a!C44 & " ≠ " & sample_4b!C44, "")
A45: 44 | B45: how many programmer does it take to change a light bulb? 21, 1 person change it, 20 others to tell they can do better | C45: =IF(sample_4a!C45<>sample_4b!C45, sample_4a!C45 & " ≠ " & sample_4b!C45, "")
A46: 45 | B46: If you have a low IQ.... You can tell your wife she's fucking retarded! | C46: =IF(sample_4a!C46<>sample_4b!C46, sample_4a!C46 & " ≠ " & sample_4b!C46, "")
A47: 46 | B47: I did a self defense course I would't recommend anyone to attack me in slow motion | C47: =IF(sample_4a!C47<>sample_4b!C47, sample_4a!C47 & " ≠ " & sample_4b!C47, "")
A48: 47 | B48: Did you know you can cook a delicious meal without needing to add any oil to the pan to start? The trick is to start every meal by cooking 2 slices of bacon in the pan first. | C48: =IF(sample_4a!C48<>sample_4b!C48, sample_4a!C48 & " ≠ " & sample_4b!C48, "")
A49: 48 | B49: [NSFW] A priest found a boy wondering the side of the road He pulled over and asked the boy "what are you doing out here, my son? Are you alone?" "No" The boy said. "My parents crashed into a tree over there and died, I'm looking for help" The priest nodded understandingly whilst unbuttoning his shirt. "Today's just not your day is it." | C49: =IF(sample_4a!C49<>sample_4b!C49, sample_4a!C49 & " ≠ " & sample_4b!C49, "") -> R ≠ RE | D49: R
A50: 49 | B50: I had to watch my aunt boil my pet's offspring right in front of me. Hopefully next Easter will be more enjoyable. | C50: =IF(sample_4a!C50<>sample_4b!C50, sample_4a!C50 & " ≠ " & sample_4b!C50, "")
A51: 50 | B51: My wife told me she was leaving me because of my obsession with pretending to be a cashier &#x200B; "Do you need any help packing your bags?" I asked her | C51: =IF(sample_4a!C51<>sample_4b!C51, sample_4a!C51 & " ≠ " & sample_4b!C51, "")
A52: 51 | B52: What do you get when you cross Google and a porn star? Just a fucking know it all. | C52: =IF(sample_4a!C52<>sample_4b!C52, sample_4a!C52 & " ≠ " & sample_4b!C52, "") -> N ≠ CO | D52: CO
A53: 52 | B53: They say if you've seen one connected group of stores You've seen a mall | C53: =IF(sample_4a!C53<>sample_4b!C53, sample_4a!C53 & " ≠ " & sample_4b!C53, "")
A54: 53 | B54: What do you get if you cross a Jehovah's Witness with a Gypsy Joker?? Someone who knocks on your door and tells you to fuck off | C54: =IF(sample_4a!C54<>sample_4b!C54, sample_4a!C54 & " ≠ " & sample_4b!C54, "") -> R ≠ RE | D54: R; RE
A55: 54 | B55: What's the difference between golf and Lady Godiva? One is a hunt on a course. | C55: =IF(sample_4a!C55<>sample_4b!C55, sample_4a!C55 & " ≠ " & sample_4b!C55, "") -> N ≠ G | D55: G
A56: 55 | B56: What do you do when you stumble upon a one-armed Polish man stuck in a tree? You wave! | C56: =IF(sample_4a!C56<>sample_4b!C56, sample_4a!C56 & " ≠ " & sample_4b!C56, "")
A57: 56 | B57: Recently I threw a steak at someone and missed It was a terrible miss-steak | C57: =IF(sample_4a!C57<>sample_4b!C57, sample_4a!C57 & " ≠ " & sample_4b!C57, "")
A58: 57 | B58: I don't like to waste food... So I take my leftovers, crumple them up in the paper that came with the food, and leave it outside in the open for that next hungry person who comes by. | C58: =IF(sample_4a!C58<>sample_4b!C58, sample_4a!C58 & " ≠ " & sample_4b!C58, "")
A59: 58 | B59: I think I might be a polygamist ... ... My wife has multiple personality disorder. | C59: =IF(sample_4a!C59<>sample_4b!C59, sample_4a!C59 & " ≠ " & sample_4b!C59, "") -> M ≠ G | D59: M
A60: 59 | B60: Still, my wife doesn't shut up I told my wife: "Let's put it in your ear." She replied: "But I will become deaf, if you do that". I told her: "Don't worry, I've put it in your mouth now for 20 years, and still you did not shut up." | C60: =IF(sample_4a!C60<>sample_4b!C60, sample_4a!C60 & " ≠ " & sample_4b!C60, "")
A61: 60 | B61: A man and a woman walk into a bar A man and a woman walk into a bar and the man turns to the woman and says, "Hey, I've got this magic water that can make me fly." Then the woman says "I don't believe you. Show me." So the man downs a magic water and gets on the top of the roof, jumps off, and flies back on. The woman says "Wow! Do that again!" And so the man goes back downstairs to drink another magic water, gets back on the roof, jumps off, flies back on. The woman says "Whoa! I gotta try that for myself!" The woman goes downstairs, asks the bar tender for some magic water, drinks it, gets on the roof, jumps off, and injures herself badly. When the man comes back downstairs the bar tender says to him, "You know Superman, you're a real jerk when you're drunk." | C61: =IF(sample_4a!C61<>sample_4b!C61, sample_4a!C61 & " ≠ " & sample_4b!C61, "")
A62: 61 | B62: What do you call the preparation for a pub quiz? The National Curriculum | C62: =IF(sample_4a!C62<>sample_4b!C62, sample_4a!C62 & " ≠ " & sample_4b!C62, "") -> N ≠ PI | D62: N
A63: 62 | B63: What do you call a group of baby garbage bins? A litter... | C63: =IF(sample_4a!C63<>sample_4b!C63, sample_4a!C63 & " ≠ " & sample_4b!C63, "") -> Age ≠ N | D63: Age
A64: 63 | B64: How would Nicolas Cage win a rap battle? By using verbal judo | C64: =IF(sample_4a!C64<>sample_4b!C64, sample_4a!C64 & " ≠ " & sample_4b!C64, "")
A65: 64 | B65: What do you call being hit by a homosexual? Fruit punch | C65: =IF(sample_4a!C65<>sample_4b!C65, sample_4a!C65 & " ≠ " & sample_4b!C65, "")
A66: 65 | B66: What’s so alike about a zit and a priest? Waiting till 12 to come on your face. | C66: =IF(sample_4a!C66<>sample_4b!C66, sample_4a!C66 & " ≠ " & sample_4b!C66, "") -> R ≠ RE | D66: R
A67: 66 | B67: When do you known that Chinese Americans are moving into the neighborhood? All the Mexicans are buying auto insurance . | C67: =IF(sample_4a!C67<>sample_4b!C67, sample_4a!C67 & " ≠ " & sample_4b!C67, "")
A68: 67 | B68: A man goes to the doctor for a checkup... After the checkup the man then proceeds to go home. A couple days pass when the man looks at his phone to see the doctor calling. "hello." the man says as he picks up the phone. The doctor greets him back and proceeds to say to the man "Well I have some good news and bad news for you." The man beginning to become worried ask for the good news first. The doctor says "well you have two days left to live" The man outraged at the doctor says "what the HELL doctor, how is that good news, isnt that supposed to be bad news." The doctor with a troubling sound in his voice says "No, the bad news is I've been trying to call you since yesterday". | C68: =IF(sample_4a!C68<>sample_4b!C68, sample_4a!C68 & " ≠ " & sample_4b!C68, "") -> N ≠ AP | D68: N
A69: 68 | B69: How do gay nerds say goodbye on friday? Have a nice geekend! | C69: =IF(sample_4a!C69<>sample_4b!C69, sample_4a!C69 & " ≠ " & sample_4b!C69, "")
A70: 69 | B70: Hey Jesus, what’s your favorite curse word? Jesus replies: evangelism. | C70: =IF(sample_4a!C70<>sample_4b!C70, sample_4a!C70 & " ≠ " & sample_4b!C70, "")
A71: 70 | B71: I beat my wife at dominoes last night... She really needs to remember that **I** choose the toppings. | C71: =IF(sample_4a!C71<>sample_4b!C71, sample_4a!C71 & " ≠ " & sample_4b!C71, "")
A72: 71 | B72: What does a rubix cube and a pp have in common The more you play with it the harder it gets | C72: =IF(sample_4a!C72<>sample_4b!C72, sample_4a!C72 & " ≠ " & sample_4b!C72, "") -> N ≠ S | D72: N
A73: 72 | B73: Where does Kanye West like to go with his son? North West | C73: =IF(sample_4a!C73<>sample_4b!C73, sample_4a!C73 & " ≠ " & sample_4b!C73, "")
A74: 73 | B74: I'd like to die like my grandpa, in my sleep. Not screaming and yelling, like the people in his car. | C74: =IF(sample_4a!C74<>sample_4b!C74, sample_4a!C74 & " ≠ " & sample_4b!C74, "")
A75: 74 | B75: When the police asked me what i did for a living, I said I make money. The reason i was being interrogated was for selling counterfeit bills | C75: =IF(sample_4a!C75<>sample_4b!C75, sample_4a!C75 & " ≠ " & sample_4b!C75, "")
A76: 75 | B76: Damn, girl. Are you from Tennessee? Because you look inbred | C76: =IF(sample_4a!C76<>sample_4b!C76, sample_4a!C76 & " ≠ " & sample_4b!C76, "") -> G ≠ AP | D76: AP
A77: 76 | B77: If Kim Jong Un was a girl... Send nukes | C77: =IF(sample_4a!C77<>sample_4b!C77, sample_4a!C77 & " ≠ " & sample_4b!C77, "") -> PI ≠ G | D77: G
A78: 77 | B78: I told my wife she shops too much, but she wouldn't listen. She's so damn clothes-minded | C78: =IF(sample_4a!C78<>sample_4b!C78, sample_4a!C78 & " ≠ " & sample_4b!C78, "")
A79: 78 | B79: Why Hitler was late to work? He accidently didn't took the second left but the third Reich. | C79: =IF(sample_4a!C79<>sample_4b!C79, sample_4a!C79 & " ≠ " & sample_4b!C79, "")
A80: 79 | B80: What did the guy say when he realized the milk was curdled? NO WHEY! | C80: =IF(sample_4a!C80<>sample_4b!C80, sample_4a!C80 & " ≠ " & sample_4b!C80, "")
A81: 80 | B81: What type of Asians do the most shopping? Shop-anese | C81: =IF(sample_4a!C81<>sample_4b!C81, sample_4a!C81 & " ≠ " & sample_4b!C81, "")
A82: 81 | B82: When they finally convinced me I didn't need to lose any more weight, . . . . . . it was *reductio ad absurdum.* | C82: =IF(sample_4a!C82<>sample_4b!C82, sample_4a!C82 & " ≠ " & sample_4b!C82, "")
A83: 82 | B83: If Mexicans who illegally immigrate to the US are called wetbacks Would Americans who illegally immigrate to Canada be called frostbacks? | C83: =IF(sample_4a!C83<>sample_4b!C83, sample_4a!C83 & " ≠ " & sample_4b!C83, "")
A84: 83 | B84: What do you call the smartest person in the US? A tourist? | C84: =IF(sample_4a!C84<>sample_4b!C84, sample_4a!C84 & " ≠ " & sample_4b!C84, "") -> N ≠ RE | D84: RE
A85: 84 | B85: Russell Crowe & Sheryl Crow walk into a bar... Russell Crowe & Sheryl Crow walk into a bar. The bartender calls 911, "I need to report an attempted murder!" | C85: =IF(sample_4a!C85<>sample_4b!C85, sample_4a!C85 & " ≠ " & sample_4b!C85, "")
A86: 85 | B86: What begins with S, ends with X and will change your life? Smallpox | C86: =IF(sample_4a!C86<>sample_4b!C86, sample_4a!C86 & " ≠ " & sample_4b!C86, "") -> N ≠ AP | D86: N
A87: 86 | B87: I started a summer camp for children with ADD to help with their studies but it's not doing so well... It's called "Concentration Camp" | C87: =IF(sample_4a!C87<>sample_4b!C87, sample_4a!C87 & " ≠ " & sample_4b!C87, "") -> Age;M ≠ AP | D87: AP
A88: 87 | B88: Life is like a box of chocolates It doesn't last very long for fat people. | C88: =IF(sample_4a!C88<>sample_4b!C88, sample_4a!C88 & " ≠ " & sample_4b!C88, "")
A89: 88 | B89: What's the difference between a mosquito and a blonde? A mosquito stops sucking when you smack it. | C89: =IF(sample_4a!C89<>sample_4b!C89, sample_4a!C89 & " ≠ " & sample_4b!C89, "") -> AP ≠ G | D89: G
A90: 89 | B90: A guy walks into a bar carrying 3 ducks...... He has one duck in his left hand, one in his right hand and one under his left arm. The bar is very empty and he is the only patron. He sits down sets his ducks on the bar and has a few drinks. The bartender doesn't say anything because he would rather a weird customer with ducks than no customers at all. After a few drinks the patron gets up to use the restroom and leaves the ducks with the bartender. An awkward silence fills the room and the bartender decides to break it up with some small talk. He turns to the first duck and asks him "Whats your name duck? How was your day? The first duck replies: "My name is Luey and my day was freaking amazing! It was the best day ever! I was in and out of Puddles all freaking day and it was great. Id do it every day for the rest of my existence if I could!" The bartender nods his head and thinks to himself, damn that does sound like a good day for a duck. He then turns to the second duck and repeats the question: "Hey whats your name and how was your day?" The second duck exclaims "My name is Huey and my day was also freaking amazing. I was in and out of Puddles all freaking day and Id do it a million times over if I could!" At this point the bartender is pretty bored speaking with the ducks and is pretty confident he knows what the third duck did. So he turns to the third duck and states "Soo let me guess your name is Stuey and you had a great day in and out of puddles as well?" The third duck looks straight at the bartender with a disgusted face and says "NO my name is Puddles and don't ask me how my fucking day went!!!!" - Poor Puddles | C90: =IF(sample_4a!C90<>sample_4b!C90, sample_4a!C90 & " ≠ " & sample_4b!C90, "")
A91: 90 | B91: Once, I met a pirate with a peg leg, a hook hand, and an eye patch I asked him "What happened to your leg?" "Arr," he responded, "One day I was in a battle at sea and a cannon ball blew my leg right off. I cut the throat of the man who fired the shot though." "That sounds awful. What happened to your hand?" "Arr, one day at sea I was knocked off the ship into shark infested waters and a great white bit my hand right off. I stabbed him with a harpoon after that though. "That sounds terrible. What happened to your eye?" "Arr, one day I was near port and a ton of seagulls were flying overhead. When I looked up into the sky, one of them pooped and it landed right in my eye." "That's...really gross. But why would you lose your eye from that?" "Arr, it was the first day with the hook." | C91: =IF(sample_4a!C91<>sample_4b!C91, sample_4a!C91 & " ≠ " & sample_4b!C91, "") -> N ≠ AP | D91: AP
A92: 91 | B92: 1 + 1 = 3 If you don't use a condom | C92: =IF(sample_4a!C92<>sample_4b!C92, sample_4a!C92 & " ≠ " & sample_4b!C92, "") -> N ≠ S | D92: N
A93: 92 | B93: What do Donald Trump and the iPhone 7 have in common? They both think de-porting is the answer when there's no more Jobs. | C93: =IF(sample_4a!C93<>sample_4b!C93, sample_4a!C93 & " ≠ " & sample_4b!C93, "")
A94: 93 | B94: What do you get if you cross a cocker-spaniel with a poodle and a rooster? A Cockerpoodledoo! | C94: =IF(sample_4a!C94<>sample_4b!C94, sample_4a!C94 & " ≠ " & sample_4b!C94, "") -> N ≠ S | D94: N
A95: 94 | B95: Things single friends say A girlfriend is basically a hooker on retainer | C95: =IF(sample_4a!C95<>sample_4b!C95, sample_4a!C95 & " ≠ " & sample_4b!C95, "") -> N ≠ G | D95: N
A96: 95 | B96: I'm suffering because my girlfriend isn't here Usually the mosquitoes bite her instead. | C96: =IF(sample_4a!C96<>sample_4b!C96, sample_4a!C96 & " ≠ " & sample_4b!C96, "") -> N ≠ G | D96: G
A97: 96 | B97: Bill Clinton: "I sure hope Hillary gets better interns than I did..." "All of mine sucked" | C97: =IF(sample_4a!C97<>sample_4b!C97, sample_4a!C97 & " ≠ " & sample_4b!C97, "") -> PI ≠ G | D97: N
A98: 97 | B98: OH NO NO NO NO # Paddy McCoy, an elderly Irish farmer, recently received a letter from the Department for Work & Pensions stating that they suspected he was not paying his employees the statutory minimum wage and they would send an inspector to interview them. # On the appointed day, the inspector turned up. "Tell me about your staff," he asked Paddy. # "Well," said Paddy, "there's the farm hand, I pay him £240 a week, and he has a free cottage. # Then there's the housekeeper. She gets £190 a week, along with free board and lodging. # There's also the half-wit. He works a 16 hour day, does 90% of the work, earns about £25 a week along with a bottle of whisky and, as a special treat, occasionally gets to sleep with my wife." # "That's disgraceful" said the inspector, "I need to interview the half-wit." # "That'll be me then," said Paddy. | C98: =IF(sample_4a!C98<>sample_4b!C98, sample_4a!C98 & " ≠ " & sample_4b!C98, "") -> RE ≠ N | D98: N
A99: 98 | B99: At work I spend too much time with regular expressions! At work I'm spending so much time with regular expressions that they are starting to invade my personal life! Last night, I was biking home and pedestrians kept entering the bike lane without looking. It was so ridiculous! So I thought "I know how to fix this; I'll use regular expressions!" So I flipped them the bird. Then I shouted "Hey losers, get outta the way!" Now I have two problems. P.S. Hun, please bring the medical card on your way to the hospital! | C99: =IF(sample_4a!C99<>sample_4b!C99, sample_4a!C99 & " ≠ " & sample_4b!C99, "")
A100: 99 | B100: Would you go to the moon? Yes of course! I wouldn't... I heard the last the guy that went there died. | C100: =IF(sample_4a!C100<>sample_4b!C100, sample_4a!C100 & " ≠ " & sample_4b!C100, "")
...

Sheet sample_5a
A1: id | B1: joke | C1: category_human
A2: 1 | B2: What happens when marine life encounters plastic? They get plastuck. | C2: N
A3: 2 | B3: Naming your daughters A man has 3 daughters. One day, the daughters decided to ask their father why they were given the names they had. The first daughter asks: "dad, why did you name me Rose?" The father replies, "well Rose, because when you were born, a rose landed on you as we left the hospital. The second daughter asks: "dad, why did you name me Lily?" The father replies, "well Lily, because when you were born, a lily landed on you as we left the hospital. The third daughter approaches. "Da', y dih u name me-" He cuts her off, saying "shut up, cinderblock" | C3: AP
A4: 3 | B4: Bought some extra sensitive toothpaste the other day... It got really jealous when I used a different toothpaste this morning | C4: N
A5: 4 | B5: There are two goldfish in a tank One fish turns to the other and says: "You man the guns, I'll drive". | C5: N
A6: 5 | B6: When you are assigned the odd problems *accidentally does an even* Me: Noooooooooo (not sure if this belongs here please let me know nicely) | C6: N
A7: 6 | B7: I broke my right hand recently... My buddy asked, "Oh no, isn't that your drinking hand?" I replied, "No, I'm am-beer-dextrious." | C7: N
A8: 7 | B8: Why didn't Russia return the NSA whistleblower to the United States? He was Snowden. | C8: PI
A9: 8 | B9: Why not give the military John Cena costumes to wear No one would see them. | C9: N
A10: 9 | B10: Hmm.......extra virgin olive oil..... ......so that's why I can't get laid. | C10: N
A11: 10 | B11: Spelling is fun Every time I spell analysis, I giggle when I get to anal. | C11: N
A12: 11 | B12: I saw my dwarf neighbor at the bus stop "Jump in, I'll give you a lift home" I said. "Fuck off!" He shouted back. "What an ungrateful little cunt" I thought as I zipped up my backpack and continued to walk. | C12: AP
A13: 12 | B13: What's the most commonly played song at a strip club in Iraq? Baghdad ass up. | C13: N
... A25: 24 | B25: If having a big car means you have a small dick, and having big feet means you have a big dick Then it’s no wonder people are afraid of clowns. | C25: N
A26: 25 | B26: What did Adam say to Eve? Stand back, I don't know how big this thing gets.
A27: 26 | B27: Three guys find a lamp... Three guys find a lamp... One of them picks it up, rubs it, and out pops a Genie. It booms "You have finally freed me after all these years, so I'll grant each one of you 3 wishes." The first guy immediately blurts out "I want a billion dollars." POOF, he's holding a printout that shows his account balance is now in fact 1,000,000,003.50 The second man thinks for a bit, then says "I want to be the richest man alive." POOF, he's holding papers showing his net worth is now well over 100 billion. The third guy thinks even longer about his wish, then says "I want my left arm to rotate clockwise for the rest of my life." POOF, his arm starts rotating. The Genie tells them it's time for their second wish. First guy says: "I want to be married to the most beautiful woman on earth." POOF, a stunning beauty wraps herself around his arm. Second guy says "I want to be good-looking and charismatic, so I can have every girl I want." POOF, his looks change and the first guy's wife immediately starts flirting with him. Third guy says "I want my right arm to rotate counter-clockwise until I die." POOF, now both his arms are rotating, in opposite directions. The genie tells them to think very carefully about their third wish. First guy does, and after a while says "I never want to become sick or injured, I want to stay healthy until I die." POOF, his complexion improves, his acne is gone and his knees don't bother him any more. Second guy says "I never want to grow old. I want to stay 29 forever." POOF, he looks younger already. Third guy smiles triumphantly and says "My last wish is for my head to nod back and forth." POOF, he's now nodding his head and still flailing his arms around. The genie wishes them good luck, disappears, and the men soon go their separate ways. Many years later they meet again and chat about how things have been going. First guy is ecstatic: "I've invested the money and multiplied it many times over, so me and my family will be among the richest of the rich pretty much forever. My wife is a freak in the sheets, and I've never gotten so much as a cold in all these years." Second guy smiles and says "Well, I built charities worldwide with a fraction of my wealth, I'm still the richest guy alive and also revered for my good deeds. I haven't aged a day since we last met, and yes, your wife is pretty wild in bed." Third guy walks in, flailing his arms around and nodding his head, and says: "Guys, I think I fucked up." Stole this joke from /u/Ruft in another subreddit, had to post it here | C27: N
A28: 27 | B28: When it’s April 2nd... And she’s still pregnant. | C28: G
A29: 28 | B29: My wife threw coffee remnants at me this morning My lawyer says I have grounds for divorce | C29: G
A30: 29 | B30: How do you know if a vegan is at your party? He'll interrupt your story about crossfit. | C30: PI
A31: 30 | B31: Bed monsters A guy had a fear that there was a monster living under his bed, and he decided to seek professional help. During the consultation, the shrink told him his situation was unusual but not unheard of. He can be cured, but it would take at minimum 6 session at $250 each. The guy declined citing the large cost. A few month later, he bumps into the same shrink at a bar, who asked if he'd made any progress "Perfect!" he responds, "No more monsters!" "How'd you accomplish this?" the shrink asks "I told a friend, and she solved my problem for a bottle of whiskey!" he responds. "What did she do?" asks the shrink. "Told me to saw the legs off my bed!" | C31: N
A32: 31 | B32: Bartender: What will you be having to drink? - Harambe: I'll have a beer. - Me: No, he'll have just ice. - Bartender: Just ice? - Me: Yes, justice for Harambe | C32: N
A33: 32 | B33: I have excellent chemistry with the girls I stalk these days By chemistry, I mean the reaction of 8-methyl-*N*\\-vanillyl-6-nonenamide with my eyes. | C33: G
A34: 33 | B34: What's the difference between an airplane and a woman? I've been inside an airplane. | C34: G
A35: 34 | B35: ISIS has declared it isn't a terrorist group anymore, and has formed a band. They now use bazookaleles and 47 Assault Kazoos, or a formation known as an AK-47. | C35: PI
A36: 35 | B36: What does a nosey pepper do? Gets jalapeno business! | C36: N
A37: 36 | B37: If you are a fan of Back to the Future and a fan of Bobbleheads.... Is it insensitive to have a bobble head of Marty McFly? | C37: N
A38: 37 | B38: Is it racist if a guy with a small dick calls it his ding dong? | C38: RE
... A101: 100 | B101: I farted in an Apple store yesterday and everyone had to evacuate Because they didn't have Windows | C101: N

Sheet sample_5b
A1: id | B1: joke | C1: category_human
A2: 1 | B2: What happens when marine life encounters plastic? They get plastuck. | C2: N
A3: 2 | B3: Naming your daughters A man has 3 daughters. One day, the daughters decided to ask their father why they were given the names they had. The first daughter asks: "dad, why did you name me Rose?" The father replies, "well Rose, because when you were born, a rose landed on you as we left the hospital. The second daughter asks: "dad, why did you name me Lily?" The father replies, "well Lily, because when you were born, a lily landed on you as we left the hospital. The third daughter approaches. "Da', y dih u name me-" He cuts her off, saying "shut up, cinderblock" | C3: M
A4: 3 | B4: Bought some extra sensitive toothpaste the other day... It got really jealous when I used a different toothpaste this morning | C4: N
A5: 4 | B5: There are two goldfish in a tank One fish turns to the other and says: "You man the guns, I'll drive". | C5: N
A6: 5 | B6: When you are assigned the odd problems *accidentally does an even* Me: Noooooooooo (not sure if this belongs here please let me know nicely) | C6: N
A7: 6 | B7: I broke my right hand recently... My buddy asked, "Oh no, isn't that your drinking hand?" I replied, "No, I'm am-beer-dextrious." | C7: N
A8: 7 | B8: Why didn't Russia return the NSA whistleblower to the United States? He was Snowden. | C8: PI
A9: 8 | B9: Why not give the military John Cena costumes to wear No one would see them. | C9: N
A10: 9 | B10: Hmm.......extra virgin olive oil..... ......so that's why I can't get laid. | C10: N
A11: 10 | B11: Spelling is fun Every time I spell analysis, I giggle when I get to anal. | C11: N
A12: 11 | B12: I saw my dwarf neighbor at the bus stop "Jump in, I'll give you a lift home" I said. "Fuck off!" He shouted back. "What an ungrateful little cunt" I thought as I zipped up my backpack and continued to walk. | C12: AP
A13: 12 | B13: What's the most commonly played song at a strip club in Iraq? Baghdad ass up. | C13: N
... A101: 100 | B101: I farted in an Apple store yesterday and everyone had to evacuate Because they didn't have Windows | C101: N

Sheet conflict_5
A1: id | B1: joke | C1: Conflict | D1: Adjudication
A2: 1 | B2: What happens when marine life encounters plastic? They get plastuck. | C2: =IF(sample_5a!C2<>sample_5b!C2, sample_5a!C2 & " ≠ " & sample_5b!C2, "")
A3: 2 | B3: Naming your daughters A man has 3 daughters. One day, the daughters decided to ask their father why they were given the names they had. The first daughter asks: "dad, why did you name me Rose?" The father replies, "well Rose, because when you were born, a rose landed on you as we left the hospital. The second daughter asks: "dad, why did you name me Lily?" The father replies, "well Lily, because when you were born, a lily landed on you as we left the hospital. The third daughter approaches. "Da', y dih u name me-" He cuts her off, saying "shut up, cinderblock" | C3: =IF(sample_5a!C3<>sample_5b!C3, sample_5a!C3 & " ≠ " & sample_5b!C3, "") -> AP ≠ M | D3: AP
A4: 3 | B4: Bought some extra sensitive toothpaste the other day... It got really jealous when I used a different toothpaste this morning | C4: =IF(sample_5a!C4<>sample_5b!C4, sample_5a!C4 & " ≠ " & sample_5b!C4, "")
A5: 4 | B5: There are two goldfish in a tank One fish turns to the other and says: "You man the guns, I'll drive". | C5: =IF(sample_5a!C5<>sample_5b!C5, sample_5a!C5 & " ≠ " & sample_5b!C5, "")
A6: 5 | B6: When you are assigned the odd problems *accidentally does an even* Me: Noooooooooo (not sure if this belongs here please let me know nicely) | C6: =IF(sample_5a!C6<>sample_5b!C6, sample_5a!C6 & " ≠ " & sample_5b!C6, "")
A7: 6 | B7: I broke my right hand recently... My buddy asked, "Oh no, isn't that your drinking hand?" I replied, "No, I'm am-beer-dextrious." | C7: =IF(sample_5a!C7<>sample_5b!C7, sample_5a!C7 & " ≠ " & sample_5b!C7, "")
A8: 7 | B8: Why didn't Russia return the NSA whistleblower to the United States? He was Snowden. | C8: =IF(sample_5a!C8<>sample_5b!C8, sample_5a!C8 & " ≠ " & sample_5b!C8, "")
A9: 8 | B9: Why not give the military John Cena costumes to wear No one would see them. | C9: =IF(sample_5a!C9<>sample_5b!C9, sample_5a!C9 & " ≠ " & sample_5b!C9, "")
A10: 9 | B10: Hmm.......extra virgin olive oil..... ......so that's why I can't get laid. | C10: =IF(sample_5a!C10<>sample_5b!C10, sample_5a!C10 & " ≠ " & sample_5b!C10, "")
A11: 10 | B11: Spelling is fun Every time I spell analysis, I giggle when I get to anal. | C11: =IF(sample_5a!C11<>sample_5b!C11, sample_5a!C11 & " ≠ " & sample_5b!C11, "")
A12: 11 | B12: I saw my dwarf neighbor at the bus stop "Jump in, I'll give you a lift home" I said. "Fuck off!" He shouted back. "What an ungrateful little cunt" I thought as I zipped up my backpack and continued to walk. | C12: =IF(sample_5a!C12<>sample_5b!C12, sample_5a!C12 & " ≠ " & sample_5b!C12, "")
A13: 12 | B13: What's the most commonly played song at a strip club in Iraq? Baghdad ass up. | C13: =IF(sample_5a!C13<>sample_5b!C13, sample_5a!C13 & " ≠ " & sample_5b!C13, "")
A14: 13 | B14: The Alpine Find An archaeological dig team was on an expedition to the Alps when they discovered a mummified human buried in the ice. Upon closer inspection, it appeared to be a young male from the Neolithic period. The team was split into two sections: Section One was to climb the slope and retrieve the mummy, while Section Two was to wait below for further orders. Jack, a member of Section Two, decided to tag along with Section One in order to see the recovery process firsthand. When the group was all assembled, and had begun chipping away at the ice which bound the prehistoric boy's remains, Jack got a radio call from his buddy in Section Two. &#x200B; "Hey, buddy, where are ya?" the voice asked. &#x200B; Jack replied: "Cracking open a cold boy with the ones." | C14: =IF(sample_5a!C14<>sample_5b!C14, sample_5a!C14 & " ≠ " & sample_5b!C14, "")
A15: 14 | B15: To all the ladies that turned me down Man you dodged a bullet | C15: =IF(sample_5a!C15<>sample_5b!C15, sample_5a!C15 & " ≠ " & sample_5b!C15, "")
A16: 15 | B16: I was asked to grade Caitlyn Jenner I went with a D- | C16: =IF(sample_5a!C16<>sample_5b!C16, sample_5a!C16 & " ≠ " & sample_5b!C16, "") -> S ≠ N | D16: S
A17: 16 | B17: What's the difference between a cat and a comma? One has claws at the end of its paws and the other is a pause at the end of a clause. | C17: =IF(sample_5a!C17<>sample_5b!C17, sample_5a!C17 & " ≠ " & sample_5b!C17, "")
A18: 17 | B18: I just finished a book on how WD-40 came about. It’s non friction. | C18: =IF(sample_5a!C18<>sample_5b!C18, sample_5a!C18 & " ≠ " & sample_5b!C18, "")
A19: 18 | B19: A little boy goes to his dad and asks, "What is alternative?" A little boy goes to his dad and asks, "What is alternative?" Dad says, “It may be difficult for you to understand, so let me give you an example. Imagine that you work at a factory. You work hard, struggle year after year and you finally save up enough money to purchase a small farm. You buy a dozen eggs and start raising chickens. You feed them, clean the hen house, take care of them every day, so they start laying more eggs. You put them in an incubator and eventually you have thousands of chickens, and these chickens lay even more eggs. You’re a succesful farmer now! Suddenly a nearby river floods your farm, everything’s fucking destroyed, all chickens are dead, the whole farm business goes belly-up…” “So dad, what is alternative?” “Ducks, son! Ducks are the alternative!” | C19: =IF(sample_5a!C19<>sample_5b!C19, sample_5a!C19 & " ≠ " & sample_5b!C19, "")
A20: 19 | B20: An 85-year-old man was requested by his doctor for a sperm count as part of his physical exam. The doctor gave the man a jar and said, "Take this jar home and bring back a semen sample tomorrow." The next day the 85-year-old man reappeared at the doctor's office and gave him the jar, which was as clean and empty as on the previous day. The doctor asked, what happened and the man explained. "Well, doc, it's like this--first I tried with my right hand, but nothing. Then I tried with my left hand, but still nothing. Then I asked my wife for help. She tried with her right hand, then with her left, still nothing. She tried with her mouth, first with the teeth in, then with her teeth out, still nothing. We even called up Arleen, the lady next door and she tried too, first with both hands, then an armpit, and she even tried squeezin' it between her knees, but still nothing." The doctor was shocked! "You asked your neighbor?" The old man replied, "Yep, none of us could get the jar open. | C20: =IF(sample_5a!C20<>sample_5b!C20, sample_5a!C20 & " ≠ " & sample_5b!C20, "")
A21: 20 | B21: Dirty Joke An old joke I heard my dad tell my older brother years ago when I was just a little kid. Sorry if it has ever been posted before. I have never heard it anywhere else. So this guy gets off work and goes to a bar. He starts having a few drinks when he notices a lady across the bar watching him so he decides to go try his luck and he talks to her for a while. After a few hours and many drinks, they both decide to take a cab back to his place. As they arrive he struggles with the key for a moment, but as he finds success she grabs his arm and stops him. "Wait. How you open the door will determine how the sex will turn out. If you barely open the door the sex may be too soft and will be forgettable. If you just slam the door open then the sex might be too rough and I might get hurt. How will you open the door?" The guy stares at her for a few minutes before shrugging and replying "I will probably lick the doorknob for a little while and then come in the backdoor." | C21: =IF(sample_5a!C21<>sample_5b!C21, sample_5a!C21 & " ≠ " & sample_5b!C21, "")
A22: 21 | B22: My wife said that I'm a lousy lover... My wife said that I'm a lousy lover... How can she know that after only two minutes? | C22: =IF(sample_5a!C22<>sample_5b!C22, sample_5a!C22 & " ≠ " & sample_5b!C22, "")
A23: 22 | B23: Funny Comeback Dad: you better pass your exam or else forget me as your father! son: ..... son: sure, whatever dad. FIVE HOURS LATER Dad: so how was your exam? Son: who the hell are you? | C23: =IF(sample_5a!C23<>sample_5b!C23, sample_5a!C23 & " ≠ " & sample_5b!C23, "")
A24: 23 | B24: There so much messed up kinds of porn these days What's the world coming to? | C24: =IF(sample_5a!C24<>sample_5b!C24, sample_5a!C24 & " ≠ " & sample_5b!C24, "")
A25: 24 | B25: If having a big car means you have a small dick, and having big feet means you have a big dick Then it’s no wonder people are afraid of clowns. | C25: =IF(sample_5a!C25<>sample_5b!C25, sample_5a!C25 & " ≠ " & sample_5b!C25, "") -> N ≠ AP | D25: AP
A26: 25 | B26: What did Adam say to Eve? Stand back, I don't know how big this thing gets. | C26: =IF(sample_5a!C26<>sample_5b!C26, sample_5a!C26 & " ≠ " & sample_5b!C26, "") -> ≠ N | D26: R
A27: 26 | B27: Three guys find a lamp... Three guys find a lamp... One of them picks it up, rubs it, and out pops a Genie. It booms "You have finally freed me after all these years, so I'll grant each one of you 3 wishes." The first guy immediately blurts out "I want a billion dollars." POOF, he's holding a printout that shows his account balance is now in fact 1,000,000,003.50 The second man thinks for a bit, then says "I want to be the richest man alive." POOF, he's holding papers showing his net worth is now well over 100 billion. The third guy thinks even longer about his wish, then says "I want my left arm to rotate clockwise for the rest of my life." POOF, his arm starts rotating. The Genie tells them it's time for their second wish. First guy says: "I want to be married to the most beautiful woman on earth." POOF, a stunning beauty wraps herself around his arm. Second guy says "I want to be good-looking and charismatic, so I can have every girl I want." POOF, his looks change and the first guy's wife immediately starts flirting with him. Third guy says "I want my right arm to rotate counter-clockwise until I die." POOF, now both his arms are rotating, in opposite directions. The genie tells them to think very carefully about their third wish. First guy does, and after a while says "I never want to become sick or injured, I want to stay healthy until I die." POOF, his complexion improves, his acne is gone and his knees don't bother him any more. Second guy says "I never want to grow old. I want to stay 29 forever." POOF, he looks younger already. Third guy smiles triumphantly and says "My last wish is for my head to nod back and forth." POOF, he's now nodding his head and still flailing his arms around. The genie wishes them good luck, disappears, and the men soon go their separate ways. Many years later they meet again and chat about how things have been going. First guy is ecstatic: "I've invested the money and multiplied it many times over, so me and my family will be among the richest of the rich pretty much forever. My wife is a freak in the sheets, and I've never gotten so much as a cold in all these years." Second guy smiles and says "Well, I built charities worldwide with a fraction of my wealth, I'm still the richest guy alive and also revered for my good deeds. I haven't aged a day since we last met, and yes, your wife is pretty wild in bed." Third guy walks in, flailing his arms around and nodding his head, and says: "Guys, I think I fucked up." Stole this joke from /u/Ruft in another subreddit, had to post it here | C27: =IF(sample_5a!C27<>sample_5b!C27, sample_5a!C27 & " ≠ " & sample_5b!C27, "")
A28: 27 | B28: When it’s April 2nd... And she’s still pregnant. | C28: =IF(sample_5a!C28<>sample_5b!C28, sample_5a!C28 & " ≠ " & sample_5b!C28, "") -> G ≠ N | D28: G
A29: 28 | B29: My wife threw coffee remnants at me this morning My lawyer says I have grounds for divorce | C29: =IF(sample_5a!C29<>sample_5b!C29, sample_5a!C29 & " ≠ " & sample_5b!C29, "") -> G ≠ N | D29: G
A30: 29 | B30: How do you know if a vegan is at your party? He'll interrupt your story about crossfit. | C30: =IF(sample_5a!C30<>sample_5b!C30, sample_5a!C30 & " ≠ " & sample_5b!C30, "")
A31: 30 | B31: Bed monsters A guy had a fear that there was a monster living under his bed, and he decided to seek professional help. During the consultation, the shrink told him his situation was unusual but not unheard of. He can be cured, but it would take at minimum 6 session at $250 each. The guy declined citing the large cost. A few month later, he bumps into the same shrink at a bar, who asked if he'd made any progress "Perfect!" he responds, "No more monsters!" "How'd you accomplish this?" the shrink asks "I told a friend, and she solved my problem for a bottle of whiskey!" he responds. "What did she do?" asks the shrink. "Told me to saw the legs off my bed!" | C31: =IF(sample_5a!C31<>sample_5b!C31, sample_5a!C31 & " ≠ " & sample_5b!C31, "")
A32: 31 | B32: Bartender: What will you be having to drink? - Harambe: I'll have a beer. - Me: No, he'll have just ice. - Bartender: Just ice? - Me: Yes, justice for Harambe | C32: =IF(sample_5a!C32<>sample_5b!C32, sample_5a!C32 & " ≠ " & sample_5b!C32, "")
A33: 32 | B33: I have excellent chemistry with the girls I stalk these days By chemistry, I mean the reaction of 8-methyl-*N*\\-vanillyl-6-nonenamide with my eyes. | C33: =IF(sample_5a!C33<>sample_5b!C33, sample_5a!C33 & " ≠ " & sample_5b!C33, "") -> G ≠ N | D33: G
A34: 33 | B34: What's the difference between an airplane and a woman? I've been inside an airplane. | C34: =IF(sample_5a!C34<>sample_5b!C34, sample_5a!C34 & " ≠ " & sample_5b!C34, "")
A35: 34 | B35: ISIS has declared it isn't a terrorist group anymore, and has formed a band. They now use bazookaleles and 47 Assault Kazoos, or a formation known as an AK-47. | C35: =IF(sample_5a!C35<>sample_5b!C35, sample_5a!C35 & " ≠ " & sample_5b!C35, "") -> PI ≠ N | D35: PI
A36: 35 | B36: What does a nosey pepper do? Gets jalapeno business! | C36: =IF(sample_5a!C36<>sample_5b!C36, sample_5a!C36 & " ≠ " & sample_5b!C36, "")
A37: 36 | B37: If you are a fan of Back to the Future and a fan of Bobbleheads.... Is it insensitive to have a bobble head of Marty McFly? | C37: =IF(sample_5a!C37<>sample_5b!C37, sample_5a!C37 & " ≠ " & sample_5b!C37, "")
A38: 37 | B38: Is it racist if a guy with a small dick calls it his ding dong? | C38: =IF(sample_5a!C38<>sample_5b!C38, sample_5a!C38 & " ≠ " & sample_5b!C38, "")
A39: 38 | B39: Why didn't Snoop Dogg cross the road? He would have to change his name to Snoop Chickenn. | C39: =IF(sample_5a!C39<>sample_5b!C39, sample_5a!C39 & " ≠ " & sample_5b!C39, "")
A40: 39 | B40: What's the difference between squirrels and alcoholism? Squirrels aren't tearing my family apart. | C40: =IF(sample_5a!C40<>sample_5b!C40, sample_5a!C40 & " ≠ " & sample_5b!C40, "")
A41: 40 | B41: What did the paraplegic retard get for Christmas? Cancer. | C41: =IF(sample_5a!C41<>sample_5b!C41, sample_5a!C41 & " ≠ " & sample_5b!C41, "")
A42: 41 | B42: I started reading a book on anorgasmia ...but I just couldn't finish. | C42: =IF(sample_5a!C42<>sample_5b!C42, sample_5a!C42 & " ≠ " & sample_5b!C42, "")
A43: 42 | B43: Dear God, why do you allow violence in schools? \\<RETURNED TO SENDER, ADDRESSEE UNKNOWN> | C43: =IF(sample_5a!C43<>sample_5b!C43, sample_5a!C43 & " ≠ " & sample_5b!C43, "")
A44: 43 | B44: I'm like a goat... in that I can't do analogies nor comprahend the english language very wel. | C44: =IF(sample_5a!C44<>sample_5b!C44, sample_5a!C44 & " ≠ " & sample_5b!C44, "")
A45: 44 | B45: What sound do chickens make in China? Woof | C45: =IF(sample_5a!C45<>sample_5b!C45, sample_5a!C45 & " ≠ " & sample_5b!C45, "")
A46: 45 | B46: Verbs Without them we wouldn't get a lot done. | C46: =IF(sample_5a!C46<>sample_5b!C46, sample_5a!C46 & " ≠ " & sample_5b!C46, "")
A47: 46 | B47: Daughter asks her father if she is showing too much cleavage. Father replies:"If you don't have chest hair, then yes." | C47: =IF(sample_5a!C47<>sample_5b!C47, sample_5a!C47 & " ≠ " & sample_5b!C47, "") -> G ≠ N | D47: G
A48: 47 | B48: I have a date for Valentinesday 14. February | C48: =IF(sample_5a!C48<>sample_5b!C48, sample_5a!C48 & " ≠ " & sample_5b!C48, "")
A49: 48 | B49: I now know how batteries feel... Because I'm rarely included in anything. | C49: =IF(sample_5a!C49<>sample_5b!C49, sample_5a!C49 & " ≠ " & sample_5b!C49, "")
A50: 49 | B50: doctor, doctor im i dying copyright are not fun to deal with in real life. | C50: =IF(sample_5a!C50<>sample_5b!C50, sample_5a!C50 & " ≠ " & sample_5b!C50, "")
A51: 50 | B51: How did the schizophrenic do on their math test? They passed with flying colors. | C51: =IF(sample_5a!C51<>sample_5b!C51, sample_5a!C51 & " ≠ " & sample_5b!C51, "")
A52: 51 | B52: Donald Trump, Robert Mueller, and Vladimir Putin find themselves standing at the Pearly Gates. “Are we dead?”, Mueller asks. “No,” Saint Peter says. “You’ll be going back shortly. I need to correct a mistake that was made before any of you were born. We mixed up your names! See,” he turns to Mueller, “you were supposed to be named Trump, to symbolize how, like a Trumpet, you are to sound the loud alert about injustice in the world.” “I can live with that”, Mueller says. “And Vladimir, you were supposed to be named Mueller, to symbolize how, like a mule, you are strong but stubborn.” “I can live with that,” Putin says. Then Donald turns bright orange and shouts, “Are you telling me I’m supposed to be named Putin, symbolizing somebody who is ‘pootin’, as in full of smelly farts?” St Peter laughs and says, “No, but that would have been a good one. Truth is, you haven’t been named yet...” he looks at Mueller, “but it’s only a matter of time.” | C52: =IF(sample_5a!C52<>sample_5b!C52, sample_5a!C52 & " ≠ " & sample_5b!C52, "")
A53: 52 | B53: My wife asked me if I was going to stop singing Oasis songs. I said maaaybee.. | C53: =IF(sample_5a!C53<>sample_5b!C53, sample_5a!C53 & " ≠ " & sample_5b!C53, "")
A54: 53 | B54: Airplay doesnt work in space because theres no air | C54: =IF(sample_5a!C54<>sample_5b!C54, sample_5a!C54 & " ≠ " & sample_5b!C54, "")
A55: 54 | B55: A man is standing in line... Waiting to purchase train tickets. He waits patiently in line and passes the time by making idle conversation with the man behind him. He hears the lady at the booth say "Next Please"... and turns to realize... the woman at the teller is a knock-out! Holy Moly! She is beautiful, *VERY* large breasted, blonde, and may be the most lovely specimen of the opposite sex he has ever laid eyes on. He manages... "I uh... n-need to p-purchase two pickets to Titsburgh" and then realizes what he just uttered. He then stammers... "Errr... Uhm... so sorry... I need to purchase two tickets to Pittsburgh". He turns red as the lovely lady sighs to herself, completes the transaction and sends him on his way. The fella he had been talking to behind him catches him and says "Don't worry about it, pal. Classic Freudian blunder there. Happens to the best of us. In fact, just this morning, I did the same thing." "Oh?" says the man... regaining his composure. "Yep. I was having breakfast at the table with my wife. Now, I MEANT to say 'Honey, please pass me the milk' but *instead* I said 'You fucking bitch, you've ruined my life'". | C55: =IF(sample_5a!C55<>sample_5b!C55, sample_5a!C55 & " ≠ " & sample_5b!C55, "") -> G ≠ N | D55: G
A56: 55 | B56: Only person faster than Usain Bolt The only person faster than Usain Bolt is the person who said: *MutualFundInvestmentsAreSubjectToMarketRisk.ReadTheOfferDocumentsCarefullyBeforeInvesting* | C56: =IF(sample_5a!C56<>sample_5b!C56, sample_5a!C56 & " ≠ " & sample_5b!C56, "")
A57: 56 | B57: I got kicked out of the orchestra last night for smoking weed. It turns out the conductor was telling me to hit the gong, not the bong. | C57: =IF(sample_5a!C57<>sample_5b!C57, sample_5a!C57 & " ≠ " & sample_5b!C57, "")
A58: 57 | B58: My friend has a disease that makes him afraid of sunlight. I don’t know why, but he’s really in the dark about it. | C58: =IF(sample_5a!C58<>sample_5b!C58, sample_5a!C58 & " ≠ " & sample_5b!C58, "")
A59: 58 | B59: Kids today are all snap and no chat. | C59: =IF(sample_5a!C59<>sample_5b!C59, sample_5a!C59 & " ≠ " & sample_5b!C59, "")
A60: 59 | B60: What is a lawyers favorite diaper? Depends | C60: =IF(sample_5a!C60<>sample_5b!C60, sample_5a!C60 & " ≠ " & sample_5b!C60, "") -> N ≠ CO | D60: CO
A61: 60 | B61: Arguing with a woman is like reading a software license agreement In the end you ignore it all, wait for the end and click "I agree" | C61: =IF(sample_5a!C61<>sample_5b!C61, sample_5a!C61 & " ≠ " & sample_5b!C61, "")
A62: 61 | B62: My customer service rep asked if everything was good, after I posed the same Q in three different ways I said, I like my answers like I like my butter: clarified. | C62: =IF(sample_5a!C62<>sample_5b!C62, sample_5a!C62 & " ≠ " & sample_5b!C62, "")
A63: 62 | B63: What do gay horses eat? Each other | C63: =IF(sample_5a!C63<>sample_5b!C63, sample_5a!C63 & " ≠ " & sample_5b!C63, "")
A64: 63 | B64: Q: why did the elephant paint his balls red? A: to hide in the cherry tree ...... Q: what's the loudest noise in the jungle? A: a monkey picking cherries... | C64: =IF(sample_5a!C64<>sample_5b!C64, sample_5a!C64 & " ≠ " & sample_5b!C64, "")
A65: 64 | B65: Went to a fancy restaurant and ordered tuna, but they brought something else instead Obvious catfish situation | C65: =IF(sample_5a!C65<>sample_5b!C65, sample_5a!C65 & " ≠ " & sample_5b!C65, "") -> CO ≠ N | D65: N
A66: 65 | B66: A fly is hovering above a pond And there is a fish looking at the fly thinking if that fly just came down 3 inches I would be able to jump up and catch it. There is a bear thinking if that fly came down 3 inches that fish would jump up to catch it and I will be able to swipe at the fish. There is a Hunter and he is thinking if that fly goes down 3 inches that fish will jump up to catch it and that bear will swipe at it and I will be able to get a clean shot at the bear. There is a mouse thinking if that fly goes down 3 inches that fish will jump up to catch it, the bear will swipe at it and the hunter will get a clean shot at the bear and get so excited he’ll drop his sandwich and I can eat the sandwich. There’s a cat thinking if that fly dropped down 3 inches the fish will jump up to catch it, the bear will swipe at the fish the hunter will get a clean shot at the bear and he will be so excited he will drop his sandwich, the mouse will run to the sandwich and I can pounce at the mouse but that would never happen. Sure enough, it’s happened. The fly came down 3 inches the fish jumped up to catch it the bear swiped at the fish, the Hunter got his clean shot and was so excited he dropped his sandwich, the mouse ran to the sandwich, the cat pounced at the mouse and missed and landed in the pond. Moral of the story, every time a fly goes down 3 inches you’ll find a wet pussy | C66: =IF(sample_5a!C66<>sample_5b!C66, sample_5a!C66 & " ≠ " & sample_5b!C66, "")
A67: 66 | B67: When phones die ... ... they go to phoney heaven | C67: =IF(sample_5a!C67<>sample_5b!C67, sample_5a!C67 & " ≠ " & sample_5b!C67, "")
A68: 67 | B68: What do you get when you cross an agnostic, a insomniac, and a dyslexic? A person who stays up at night wondering if there really is a dog. | C68: =IF(sample_5a!C68<>sample_5b!C68, sample_5a!C68 & " ≠ " & sample_5b!C68, "")
A69: 68 | B69: The angel who "came over" mother Mary must have been an asian. His dick was so small that she remained a virgin. | C69: =IF(sample_5a!C69<>sample_5b!C69, sample_5a!C69 & " ≠ " & sample_5b!C69, "")
A70: 69 | B70: A boy comes home from school crying. “What the hell is wrong with you?” His dad asks. “I lost the spelling bee today because I didn’t spell the word ‘posse’ correctly.” “Well no wonder you lost, you can’t even say it right!” | C70: =IF(sample_5a!C70<>sample_5b!C70, sample_5a!C70 & " ≠ " & sample_5b!C70, "")
A71: 70 | B71: What did the pirate say on his eightieth birthday? Aye, Matey! | C71: =IF(sample_5a!C71<>sample_5b!C71, sample_5a!C71 & " ≠ " & sample_5b!C71, "")
A72: 71 | B72: I remember when I discovered Santa Claus was just my dad I still don't know how he snuck out every year to deliver presents all over the world. | C72: =IF(sample_5a!C72<>sample_5b!C72, sample_5a!C72 & " ≠ " & sample_5b!C72, "")
A73: 72 | B73: I was looking for a lighter on amazon... But they only had 112.422 matches. | C73: =IF(sample_5a!C73<>sample_5b!C73, sample_5a!C73 & " ≠ " & sample_5b!C73, "")
A74: 73 | B74: Just because you're a nobody doesn't mean no on wants you Polyphemus is looking for you | C74: =IF(sample_5a!C74<>sample_5b!C74, sample_5a!C74 & " ≠ " & sample_5b!C74, "") -> AP ≠ N | D74: M
A75: 74 | B75: How does Moses make tea? Hebrews it. | C75: =IF(sample_5a!C75<>sample_5b!C75, sample_5a!C75 & " ≠ " & sample_5b!C75, "") -> RE ≠ R | D75: RE
A76: 75 | B76: A cannibal is sitting next to a big pile of poop and crying His friend comes along and says “hey buddy why are you upset?” The cannibal replies “I just dumped my girlfriend” | C76: =IF(sample_5a!C76<>sample_5b!C76, sample_5a!C76 & " ≠ " & sample_5b!C76, "")
A77: 76 | B77: Today I saw two blind people fighting, So then i shouted "i'm supporting the one with the knife" they both ran away. (was told this joke yesterday thought I'd share) Edit. Swapped 'a' for 'the'. | C77: =IF(sample_5a!C77<>sample_5b!C77, sample_5a!C77 & " ≠ " & sample_5b!C77, "")
A78: 77 | B78: Sex is a lot like a life I've never had either :( | C78: =IF(sample_5a!C78<>sample_5b!C78, sample_5a!C78 & " ≠ " & sample_5b!C78, "")
A79: 78 | B79: A girl walks in on her parents having sex. The girl asks,"Mommy what are you doing on top of daddy?" The mother nervously responds," I'm just letting out some air from your father because he's too fat." The girl replies,"You're wasting your time, the neighbour will just blow him back up again tomorrow like she usually does!" | C79: =IF(sample_5a!C79<>sample_5b!C79, sample_5a!C79 & " ≠ " & sample_5b!C79, "")
A80: 79 | B80: You know what separates the men from the boys? Social services. | C80: =IF(sample_5a!C80<>sample_5b!C80, sample_5a!C80 & " ≠ " & sample_5b!C80, "") -> G ≠ N | D80: CO/ G
A81: 80 | B81: Why do married men die first? BECAUSE THEY WANT TO! | C81: =IF(sample_5a!C81<>sample_5b!C81, sample_5a!C81 & " ≠ " & sample_5b!C81, "")
A82: 81 | B82: Why did the asteroid not get worried when he was flying to the planet? Because he wanted to meet his Crater. | C82: =IF(sample_5a!C82<>sample_5b!C82, sample_5a!C82 & " ≠ " & sample_5b!C82, "")
A83: 82 | B83: What happens when a Jewish man runs into a wall face first with an erection? He hits his nose._x007f_ | C83: =IF(sample_5a!C83<>sample_5b!C83, sample_5a!C83 & " ≠ " & sample_5b!C83, "")
